{"meta": {"eleccion": "2013-12_presidencial_2v", "label": "Presidencial 2ª v.", "tipo": "Presidencial", "has_local": true, "n_cand": 2}, "candidatos": [{"i": 0, "nombre": "MICHELLE BACHELET", "ape1": "BACHELET", "bloque": "Centro-izquierda", "eje": 3.2, "vn": 3470379}, {"i": 1, "nombre": "EVELYN MATTHEI", "ape1": "MATTHEI", "bloque": "Derecha", "eje": 7.8, "vn": 2111891}], "comuna": {"10101": {"val": 58407, "part": 36.6, "v": {"0": 34709, "1": 23698}}, "10102": {"val": 10071, "part": 35.0, "v": {"1": 4017, "0": 6054}}, "10103": {"val": 1382, "part": 32.7, "v": {"0": 730, "1": 652}}, "10104": {"val": 5959, "part": 51.6, "v": {"0": 3929, "1": 2030}}, "10105": {"val": 7132, "part": 51.3, "v": {"0": 4708, "1": 2424}}, "10106": {"val": 6852, "part": 46.0, "v": {"0": 4032, "1": 2820}}, "10107": {"val": 7123, "part": 50.0, "v": {"1": 1953, "0": 5170}}, "10108": {"val": 5792, "part": 39.8, "v": {"0": 3506, "1": 2286}}, "10109": {"val": 15217, "part": 45.1, "v": {"1": 7135, "0": 8082}}, "10201": {"val": 13365, "part": 37.0, "v": {"0": 9189, "1": 4176}}, "10202": {"val": 13703, "part": 38.3, "v": {"0": 8434, "1": 5269}}, "10203": {"val": 4906, "part": 42.5, "v": {"1": 1261, "0": 3645}}, "10204": {"val": 1483, "part": 45.2, "v": {"0": 1131, "1": 352}}, "10205": {"val": 4197, "part": 39.8, "v": {"1": 1402, "0": 2795}}, "10206": {"val": 1643, "part": 39.6, "v": {"1": 336, "0": 1307}}, "10207": {"val": 2115, "part": 38.2, "v": {"1": 797, "0": 1318}}, "10208": {"val": 7101, "part": 35.9, "v": {"0": 4727, "1": 2374}}, "10209": {"val": 3071, "part": 37.2, "v": {"1": 1137, "0": 1934}}, "10210": {"val": 2936, "part": 33.4, "v": {"0": 2325, "1": 611}}, "10301": {"val": 55676, "part": 41.8, "v": {"0": 36826, "1": 18850}}, "10302": {"val": 3996, "part": 47.7, "v": {"0": 2968, "1": 1028}}, "10303": {"val": 8957, "part": 47.0, "v": {"0": 6288, "1": 2669}}, "10304": {"val": 5305, "part": 50.1, "v": {"1": 1379, "0": 3926}}, "10305": {"val": 6233, "part": 49.2, "v": {"0": 4362, "1": 1871}}, "10306": {"val": 3717, "part": 50.0, "v": {"0": 2716, "1": 1001}}, "10307": {"val": 4742, "part": 50.7, "v": {"0": 3463, "1": 1279}}, "10401": {"val": 1328, "part": 25.9, "v": {"1": 442, "0": 886}}, "10402": {"val": 994, "part": 29.5, "v": {"1": 425, "0": 569}}, "10403": {"val": 3030, "part": 39.0, "v": {"1": 1102, "0": 1928}}, "10404": {"val": 780, "part": 36.4, "v": {"0": 575, "1": 205}}, "1101": {"val": 45803, "part": 31.0, "v": {"1": 20860, "0": 24943}}, "1107": {"val": 11223, "part": 27.4, "v": {"1": 3859, "0": 7364}}, "11101": {"val": 17394, "part": 35.1, "v": {"1": 5896, "0": 11498}}, "11102": {"val": 389, "part": 38.6, "v": {"1": 186, "0": 203}}, "11201": {"val": 7439, "part": 36.3, "v": {"1": 2176, "0": 5263}}, "11202": {"val": 1564, "part": 39.0, "v": {"0": 978, "1": 586}}, "11203": {"val": 510, "part": 36.8, "v": {"0": 333, "1": 177}}, "11301": {"val": 1063, "part": 35.3, "v": {"1": 470, "0": 593}}, "11302": {"val": 173, "part": 27.8, "v": {"1": 60, "0": 113}}, "11303": {"val": 198, "part": 42.9, "v": {"1": 92, "0": 106}}, "11401": {"val": 1788, "part": 29.9, "v": {"0": 1269, "1": 519}}, "11402": {"val": 1044, "part": 41.7, "v": {"1": 476, "0": 568}}, "12101": {"val": 38931, "part": 33.8, "v": {"1": 12208, "0": 26723}}, "12102": {"val": 227, "part": 23.1, "v": {"0": 141, "1": 86}}, "12103": {"val": 195, "part": 22.5, "v": {"1": 92, "0": 103}}, "12104": {"val": 173, "part": 16.6, "v": {"0": 108, "1": 65}}, "12201": {"val": 461, "part": 26.9, "v": {"1": 281, "0": 180}}, "12202": {"val": 21, "part": 5.9, "v": {"1": 15, "0": 6}}, "12301": {"val": 1696, "part": 27.2, "v": {"0": 1283, "1": 413}}, "12302": {"val": 266, "part": 20.9, "v": {"0": 205, "1": 61}}, "12303": {"val": 83, "part": 10.6, "v": {"1": 42, "0": 41}}, "12401": {"val": 6663, "part": 32.4, "v": {"0": 4981, "1": 1682}}, "12402": {"val": 377, "part": 25.4, "v": {"1": 147, "0": 230}}, "13101": {"val": 95502, "part": 34.9, "v": {"0": 54616, "1": 40886}}, "13102": {"val": 26763, "part": 41.1, "v": {"0": 17080, "1": 9683}}, "13103": {"val": 46512, "part": 40.8, "v": {"1": 12870, "0": 33642}}, "13104": {"val": 49462, "part": 42.2, "v": {"1": 16832, "0": 32630}}, "13105": {"val": 55190, "part": 41.4, "v": {"1": 18320, "0": 36870}}, "13106": {"val": 49660, "part": 39.8, "v": {"0": 32739, "1": 16921}}, "13107": {"val": 27573, "part": 45.7, "v": {"0": 17729, "1": 9844}}, "13108": {"val": 29353, "part": 38.1, "v": {"1": 11768, "0": 17585}}, "13109": {"val": 34538, "part": 42.6, "v": {"1": 14754, "0": 19784}}, "13110": {"val": 121317, "part": 43.0, "v": {"1": 45954, "0": 75363}}, "13111": {"val": 39005, "part": 38.5, "v": {"1": 11232, "0": 27773}}, "13112": {"val": 43142, "part": 34.2, "v": {"0": 32657, "1": 10485}}, "13113": {"val": 43708, "part": 52.2, "v": {"1": 23179, "0": 20529}}, "13114": {"val": 126442, "part": 54.9, "v": {"0": 30895, "1": 95547}}, "13115": {"val": 34472, "part": 54.8, "v": {"1": 26894, "0": 7578}}, "13116": {"val": 37011, "part": 40.5, "v": {"0": 27952, "1": 9059}}, "13117": {"val": 38329, "part": 43.9, "v": {"0": 26741, "1": 11588}}, "13118": {"val": 43984, "part": 46.0, "v": {"1": 17043, "0": 26941}}, "13119": {"val": 134103, "part": 40.0, "v": {"1": 50841, "0": 83262}}, "13120": {"val": 88571, "part": 51.8, "v": {"0": 47417, "1": 41154}}, "13121": {"val": 42914, "part": 45.5, "v": {"1": 11440, "0": 31474}}, "13122": {"val": 73406, "part": 43.1, "v": {"0": 47789, "1": 25617}}, "13123": {"val": 69871, "part": 45.0, "v": {"1": 41174, "0": 28697}}, "13124": {"val": 58877, "part": 40.0, "v": {"1": 18307, "0": 40570}}, "13125": {"val": 42764, "part": 38.4, "v": {"1": 15076, "0": 27688}}, "13126": {"val": 39895, "part": 40.8, "v": {"0": 25743, "1": 14152}}, "13127": {"val": 54210, "part": 40.5, "v": {"0": 34710, "1": 19500}}, "13128": {"val": 41908, "part": 38.8, "v": {"1": 12562, "0": 29346}}, "13129": {"val": 34988, "part": 42.8, "v": {"1": 10437, "0": 24551}}, "13130": {"val": 38968, "part": 41.8, "v": {"0": 23308, "1": 15660}}, "13131": {"val": 34958, "part": 43.1, "v": {"1": 9454, "0": 25504}}, "13132": {"val": 48976, "part": 63.1, "v": {"1": 40000, "0": 8976}}, "13201": {"val": 107603, "part": 32.5, "v": {"1": 37855, "0": 69748}}, "13202": {"val": 8525, "part": 45.6, "v": {"1": 4071, "0": 4454}}, "13203": {"val": 6572, "part": 47.1, "v": {"1": 2313, "0": 4259}}, "13301": {"val": 28555, "part": 42.3, "v": {"0": 13938, "1": 14617}}, "13302": {"val": 17080, "part": 41.4, "v": {"1": 6715, "0": 10365}}, "13303": {"val": 5676, "part": 44.8, "v": {"1": 2005, "0": 3671}}, "13401": {"val": 75338, "part": 36.7, "v": {"1": 27652, "0": 47686}}, "13402": {"val": 25996, "part": 43.7, "v": {"0": 15078, "1": 10918}}, "13403": {"val": 9663, "part": 51.9, "v": {"1": 4769, "0": 4894}}, "13404": {"val": 20322, "part": 45.8, "v": {"1": 8112, "0": 12210}}, "13501": {"val": 37789, "part": 44.1, "v": {"0": 24003, "1": 13786}}, "13502": {"val": 2127, "part": 34.2, "v": {"0": 1545, "1": 582}}, "13503": {"val": 10821, "part": 48.9, "v": {"1": 3916, "0": 6905}}, "13504": {"val": 4569, "part": 48.8, "v": {"0": 3154, "1": 1415}}, "13505": {"val": 3585, "part": 49.7, "v": {"1": 1294, "0": 2291}}, "13601": {"val": 23957, "part": 47.7, "v": {"1": 10386, "0": 13571}}, "13602": {"val": 11702, "part": 48.5, "v": {"1": 4292, "0": 7410}}, "13603": {"val": 10844, "part": 46.5, "v": {"1": 4043, "0": 6801}}, "13604": {"val": 15333, "part": 45.0, "v": {"0": 10362, "1": 4971}}, "13605": {"val": 26821, "part": 43.3, "v": {"1": 9708, "0": 17113}}, "1401": {"val": 3034, "part": 30.1, "v": {"1": 1137, "0": 1897}}, "1402": {"val": 712, "part": 26.2, "v": {"0": 257, "1": 455}}, "1403": {"val": 384, "part": 15.0, "v": {"0": 132, "1": 252}}, "1404": {"val": 1190, "part": 13.4, "v": {"1": 458, "0": 732}}, "1405": {"val": 1623, "part": 36.2, "v": {"0": 1018, "1": 605}}, "14101": {"val": 51712, "part": 41.7, "v": {"0": 34711, "1": 17001}}, "14102": {"val": 2367, "part": 46.0, "v": {"1": 583, "0": 1784}}, "14103": {"val": 6825, "part": 45.7, "v": {"1": 2600, "0": 4225}}, "14104": {"val": 7551, "part": 43.3, "v": {"0": 5364, "1": 2187}}, "14105": {"val": 3026, "part": 45.9, "v": {"0": 2013, "1": 1013}}, "14106": {"val": 7358, "part": 44.2, "v": {"0": 5284, "1": 2074}}, "14107": {"val": 8457, "part": 46.6, "v": {"1": 2765, "0": 5692}}, "14108": {"val": 12446, "part": 39.6, "v": {"0": 7802, "1": 4644}}, "14201": {"val": 14300, "part": 42.4, "v": {"1": 5413, "0": 8887}}, "14202": {"val": 5334, "part": 40.9, "v": {"1": 1957, "0": 3377}}, "14203": {"val": 4003, "part": 46.5, "v": {"1": 1832, "0": 2171}}, "14204": {"val": 12494, "part": 43.3, "v": {"1": 4802, "0": 7692}}, "15101": {"val": 52562, "part": 33.2, "v": {"0": 31957, "1": 20605}}, "15102": {"val": 611, "part": 16.8, "v": {"0": 346, "1": 265}}, "15201": {"val": 923, "part": 15.4, "v": {"0": 510, "1": 413}}, "15202": {"val": 318, "part": 13.2, "v": {"0": 171, "1": 147}}, "16101": {"val": 62547, "part": 44.9, "v": {"1": 23334, "0": 39213}}, "16102": {"val": 9519, "part": 49.7, "v": {"0": 6202, "1": 3317}}, "16103": {"val": 9393, "part": 52.2, "v": {"1": 3194, "0": 6199}}, "16104": {"val": 5614, "part": 47.8, "v": {"0": 3110, "1": 2504}}, "16105": {"val": 3779, "part": 50.3, "v": {"1": 1437, "0": 2342}}, "16106": {"val": 5217, "part": 50.1, "v": {"0": 2585, "1": 2632}}, "16107": {"val": 6711, "part": 48.2, "v": {"1": 2479, "0": 4232}}, "16108": {"val": 6759, "part": 50.5, "v": {"1": 2366, "0": 4393}}, "16109": {"val": 6661, "part": 44.6, "v": {"1": 2400, "0": 4261}}, "16201": {"val": 5496, "part": 52.8, "v": {"0": 4046, "1": 1450}}, "16202": {"val": 2791, "part": 54.1, "v": {"0": 1749, "1": 1042}}, "16203": {"val": 7776, "part": 53.9, "v": {"1": 2345, "0": 5431}}, "16204": {"val": 2976, "part": 52.0, "v": {"0": 1829, "1": 1147}}, "16205": {"val": 2869, "part": 52.1, "v": {"0": 1948, "1": 921}}, "16206": {"val": 2858, "part": 52.7, "v": {"0": 1950, "1": 908}}, "16207": {"val": 3061, "part": 56.4, "v": {"1": 844, "0": 2217}}, "16301": {"val": 20702, "part": 47.0, "v": {"0": 12422, "1": 8280}}, "16302": {"val": 9816, "part": 50.0, "v": {"1": 3366, "0": 6450}}, "16303": {"val": 4745, "part": 48.4, "v": {"1": 1902, "0": 2843}}, "16304": {"val": 2130, "part": 47.7, "v": {"1": 635, "0": 1495}}, "16305": {"val": 5072, "part": 53.9, "v": {"1": 1429, "0": 3643}}, "2101": {"val": 73355, "part": 30.7, "v": {"1": 28109, "0": 45246}}, "2102": {"val": 2731, "part": 33.0, "v": {"1": 904, "0": 1827}}, "2103": {"val": 474, "part": 17.0, "v": {"1": 127, "0": 347}}, "2104": {"val": 3304, "part": 34.9, "v": {"0": 2481, "1": 823}}, "2201": {"val": 37780, "part": 32.8, "v": {"1": 14260, "0": 23520}}, "2202": {"val": 148, "part": 9.6, "v": {"0": 106, "1": 42}}, "2203": {"val": 1730, "part": 34.4, "v": {"0": 1017, "1": 713}}, "2301": {"val": 7164, "part": 33.8, "v": {"0": 5403, "1": 1761}}, "2302": {"val": 1626, "part": 23.6, "v": {"0": 1294, "1": 332}}, "3101": {"val": 37424, "part": 34.3, "v": {"1": 13108, "0": 24316}}, "3102": {"val": 5136, "part": 40.9, "v": {"1": 1480, "0": 3656}}, "3103": {"val": 4334, "part": 40.4, "v": {"1": 1088, "0": 3246}}, "3201": {"val": 4164, "part": 36.3, "v": {"0": 2938, "1": 1226}}, "3202": {"val": 4446, "part": 31.7, "v": {"1": 732, "0": 3714}}, "3301": {"val": 16389, "part": 38.6, "v": {"0": 11667, "1": 4722}}, "3302": {"val": 1799, "part": 38.4, "v": {"1": 480, "0": 1319}}, "3303": {"val": 2287, "part": 42.7, "v": {"1": 460, "0": 1827}}, "3304": {"val": 3186, "part": 42.7, "v": {"0": 2436, "1": 750}}, "4101": {"val": 59892, "part": 41.3, "v": {"1": 21703, "0": 38189}}, "4102": {"val": 53564, "part": 38.3, "v": {"1": 18160, "0": 35404}}, "4103": {"val": 4960, "part": 45.9, "v": {"0": 3807, "1": 1153}}, "4104": {"val": 1850, "part": 46.8, "v": {"0": 1516, "1": 334}}, "4105": {"val": 2045, "part": 45.9, "v": {"1": 616, "0": 1429}}, "4106": {"val": 9306, "part": 45.6, "v": {"0": 6741, "1": 2565}}, "4201": {"val": 10995, "part": 42.7, "v": {"1": 2362, "0": 8633}}, "4202": {"val": 4153, "part": 49.9, "v": {"0": 3431, "1": 722}}, "4203": {"val": 7181, "part": 43.8, "v": {"0": 5307, "1": 1874}}, "4204": {"val": 8872, "part": 42.9, "v": {"0": 6657, "1": 2215}}, "4301": {"val": 34272, "part": 41.5, "v": {"1": 8813, "0": 25459}}, "4302": {"val": 5415, "part": 45.5, "v": {"0": 4345, "1": 1070}}, "4303": {"val": 11288, "part": 44.2, "v": {"0": 9302, "1": 1986}}, "4304": {"val": 4474, "part": 47.1, "v": {"1": 764, "0": 3710}}, "4305": {"val": 2021, "part": 43.9, "v": {"1": 611, "0": 1410}}, "5101": {"val": 97539, "part": 35.4, "v": {"1": 35284, "0": 62255}}, "5102": {"val": 9150, "part": 46.8, "v": {"0": 5886, "1": 3264}}, "5103": {"val": 15319, "part": 49.8, "v": {"0": 7414, "1": 7905}}, "5104": {"val": 242, "part": 31.6, "v": {"1": 93, "0": 149}}, "5105": {"val": 5783, "part": 46.3, "v": {"1": 2229, "0": 3554}}, "5107": {"val": 9011, "part": 43.7, "v": {"1": 3552, "0": 5459}}, "5109": {"val": 112689, "part": 39.9, "v": {"1": 55633, "0": 57056}}, "5201": {"val": 1348, "part": 28.6, "v": {"0": 933, "1": 415}}, "5301": {"val": 21567, "part": 41.8, "v": {"0": 14059, "1": 7508}}, "5302": {"val": 5116, "part": 51.2, "v": {"1": 1184, "0": 3932}}, "5303": {"val": 4028, "part": 51.7, "v": {"0": 2892, "1": 1136}}, "5304": {"val": 6512, "part": 49.6, "v": {"0": 4757, "1": 1755}}, "5401": {"val": 13130, "part": 47.8, "v": {"0": 9180, "1": 3950}}, "5402": {"val": 7786, "part": 46.0, "v": {"1": 1651, "0": 6135}}, "5403": {"val": 2556, "part": 52.9, "v": {"0": 1422, "1": 1134}}, "5404": {"val": 4255, "part": 48.3, "v": {"0": 3461, "1": 794}}, "5405": {"val": 3614, "part": 53.6, "v": {"1": 1930, "0": 1684}}, "5501": {"val": 27843, "part": 40.8, "v": {"1": 11525, "0": 16318}}, "5502": {"val": 18219, "part": 43.5, "v": {"0": 12834, "1": 5385}}, "5503": {"val": 6387, "part": 45.8, "v": {"0": 4158, "1": 2229}}, "5504": {"val": 5930, "part": 48.9, "v": {"1": 2487, "0": 3443}}, "5506": {"val": 8641, "part": 47.5, "v": {"0": 6519, "1": 2122}}, "5601": {"val": 31987, "part": 43.5, "v": {"0": 23808, "1": 8179}}, "5602": {"val": 5278, "part": 49.8, "v": {"1": 2701, "0": 2577}}, "5603": {"val": 7612, "part": 47.5, "v": {"0": 4535, "1": 3077}}, "5604": {"val": 5284, "part": 51.1, "v": {"1": 2222, "0": 3062}}, "5605": {"val": 4420, "part": 52.9, "v": {"1": 1813, "0": 2607}}, "5606": {"val": 5946, "part": 59.1, "v": {"1": 2988, "0": 2958}}, "5701": {"val": 23054, "part": 41.7, "v": {"0": 14842, "1": 8212}}, "5702": {"val": 5235, "part": 46.9, "v": {"1": 1296, "0": 3939}}, "5703": {"val": 9074, "part": 47.3, "v": {"1": 2462, "0": 6612}}, "5704": {"val": 3014, "part": 51.3, "v": {"1": 869, "0": 2145}}, "5705": {"val": 5921, "part": 47.1, "v": {"1": 1347, "0": 4574}}, "5706": {"val": 5617, "part": 51.0, "v": {"1": 1505, "0": 4112}}, "5801": {"val": 47637, "part": 40.5, "v": {"0": 26973, "1": 20664}}, "5802": {"val": 14531, "part": 42.5, "v": {"0": 8478, "1": 6053}}, "5803": {"val": 6248, "part": 45.5, "v": {"1": 2546, "0": 3702}}, "5804": {"val": 33817, "part": 41.0, "v": {"1": 15739, "0": 18078}}, "6101": {"val": 74079, "part": 41.6, "v": {"1": 28073, "0": 46006}}, "6102": {"val": 4742, "part": 47.4, "v": {"0": 3360, "1": 1382}}, "6103": {"val": 3032, "part": 47.4, "v": {"1": 1083, "0": 1949}}, "6104": {"val": 6374, "part": 45.5, "v": {"1": 1877, "0": 4497}}, "6105": {"val": 7718, "part": 46.7, "v": {"0": 5487, "1": 2231}}, "6106": {"val": 11520, "part": 47.8, "v": {"0": 7902, "1": 3618}}, "6107": {"val": 8575, "part": 47.8, "v": {"0": 5742, "1": 2833}}, "6108": {"val": 12708, "part": 45.3, "v": {"1": 4490, "0": 8218}}, "6109": {"val": 5867, "part": 51.6, "v": {"1": 2054, "0": 3813}}, "6110": {"val": 8765, "part": 47.8, "v": {"1": 2694, "0": 6071}}, "6111": {"val": 5485, "part": 50.0, "v": {"1": 1813, "0": 3672}}, "6112": {"val": 6012, "part": 50.6, "v": {"0": 4331, "1": 1681}}, "6113": {"val": 7563, "part": 49.5, "v": {"1": 2088, "0": 5475}}, "6114": {"val": 5948, "part": 52.5, "v": {"1": 1929, "0": 4019}}, "6115": {"val": 20522, "part": 46.8, "v": {"0": 14533, "1": 5989}}, "6116": {"val": 9896, "part": 49.1, "v": {"0": 6845, "1": 3051}}, "6117": {"val": 16944, "part": 47.0, "v": {"1": 5558, "0": 11386}}, "6201": {"val": 5858, "part": 49.0, "v": {"1": 2228, "0": 3630}}, "6202": {"val": 1665, "part": 53.0, "v": {"0": 1088, "1": 577}}, "6203": {"val": 2963, "part": 54.7, "v": {"0": 2017, "1": 946}}, "6204": {"val": 3197, "part": 50.2, "v": {"1": 942, "0": 2255}}, "6205": {"val": 2738, "part": 51.6, "v": {"0": 1988, "1": 750}}, "6206": {"val": 2885, "part": 48.1, "v": {"1": 721, "0": 2164}}, "6301": {"val": 25468, "part": 44.5, "v": {"1": 9500, "0": 15968}}, "6302": {"val": 5901, "part": 45.9, "v": {"0": 3549, "1": 2352}}, "6303": {"val": 12593, "part": 46.0, "v": {"0": 8415, "1": 4178}}, "6304": {"val": 3334, "part": 52.1, "v": {"0": 2278, "1": 1056}}, "6305": {"val": 6813, "part": 48.8, "v": {"1": 2062, "0": 4751}}, "6306": {"val": 4969, "part": 51.3, "v": {"0": 3453, "1": 1516}}, "6307": {"val": 4658, "part": 49.9, "v": {"1": 1441, "0": 3217}}, "6308": {"val": 3746, "part": 51.2, "v": {"1": 1211, "0": 2535}}, "6309": {"val": 1659, "part": 47.0, "v": {"1": 490, "0": 1169}}, "6310": {"val": 12870, "part": 44.9, "v": {"0": 8090, "1": 4780}}, "7101": {"val": 74200, "part": 45.0, "v": {"0": 49991, "1": 24209}}, "7102": {"val": 16965, "part": 46.1, "v": {"1": 4831, "0": 12134}}, "7103": {"val": 4786, "part": 48.3, "v": {"0": 3529, "1": 1257}}, "7104": {"val": 2186, "part": 52.7, "v": {"1": 751, "0": 1435}}, "7105": {"val": 8444, "part": 49.5, "v": {"1": 2283, "0": 6161}}, "7106": {"val": 3919, "part": 51.5, "v": {"1": 1267, "0": 2652}}, "7107": {"val": 5363, "part": 56.4, "v": {"1": 1637, "0": 3726}}, "7108": {"val": 5421, "part": 52.5, "v": {"1": 1484, "0": 3937}}, "7109": {"val": 15899, "part": 47.8, "v": {"0": 12371, "1": 3528}}, "7110": {"val": 3937, "part": 54.0, "v": {"0": 2848, "1": 1089}}, "7201": {"val": 17385, "part": 48.1, "v": {"1": 7341, "0": 10044}}, "7202": {"val": 5187, "part": 57.9, "v": {"1": 2001, "0": 3186}}, "7203": {"val": 3523, "part": 57.2, "v": {"0": 2279, "1": 1244}}, "7301": {"val": 47430, "part": 45.2, "v": {"1": 17014, "0": 30416}}, "7302": {"val": 4909, "part": 56.0, "v": {"0": 3717, "1": 1192}}, "7303": {"val": 3240, "part": 49.9, "v": {"1": 805, "0": 2435}}, "7304": {"val": 18063, "part": 50.3, "v": {"1": 4598, "0": 13465}}, "7305": {"val": 4784, "part": 53.1, "v": {"1": 1353, "0": 3431}}, "7306": {"val": 6278, "part": 50.6, "v": {"1": 2082, "0": 4196}}, "7307": {"val": 7886, "part": 53.9, "v": {"1": 1785, "0": 6101}}, "7308": {"val": 9804, "part": 44.3, "v": {"0": 6643, "1": 3161}}, "7309": {"val": 2365, "part": 50.9, "v": {"1": 848, "0": 1517}}, "7401": {"val": 34096, "part": 45.3, "v": {"1": 12720, "0": 21376}}, "7402": {"val": 7652, "part": 48.1, "v": {"0": 6049, "1": 1603}}, "7403": {"val": 11883, "part": 48.7, "v": {"0": 8238, "1": 3645}}, "7404": {"val": 17279, "part": 49.2, "v": {"0": 10652, "1": 6627}}, "7405": {"val": 7537, "part": 49.3, "v": {"1": 2967, "0": 4570}}, "7406": {"val": 17000, "part": 48.0, "v": {"0": 11523, "1": 5477}}, "7407": {"val": 6434, "part": 51.9, "v": {"0": 4263, "1": 2171}}, "7408": {"val": 6965, "part": 52.2, "v": {"0": 4946, "1": 2019}}, "8101": {"val": 81403, "part": 42.1, "v": {"0": 47123, "1": 34280}}, "8102": {"val": 34383, "part": 43.1, "v": {"0": 23693, "1": 10690}}, "8103": {"val": 25848, "part": 44.0, "v": {"1": 8719, "0": 17129}}, "8104": {"val": 5041, "part": 51.0, "v": {"1": 1510, "0": 3531}}, "8105": {"val": 8465, "part": 47.3, "v": {"1": 2379, "0": 6086}}, "8106": {"val": 21440, "part": 46.1, "v": {"1": 5464, "0": 15976}}, "8107": {"val": 19340, "part": 49.5, "v": {"0": 14538, "1": 4802}}, "8108": {"val": 31042, "part": 44.5, "v": {"0": 19119, "1": 11923}}, "8109": {"val": 5302, "part": 45.7, "v": {"1": 1866, "0": 3436}}, "8110": {"val": 50114, "part": 38.9, "v": {"1": 19214, "0": 30900}}, "8111": {"val": 21150, "part": 45.6, "v": {"0": 14626, "1": 6524}}, "8112": {"val": 32420, "part": 44.7, "v": {"1": 9795, "0": 22625}}, "8201": {"val": 8995, "part": 43.4, "v": {"1": 2288, "0": 6707}}, "8202": {"val": 13203, "part": 47.0, "v": {"0": 9161, "1": 4042}}, "8203": {"val": 11566, "part": 42.9, "v": {"0": 7384, "1": 4182}}, "8204": {"val": 2579, "part": 47.2, "v": {"0": 1593, "1": 986}}, "8205": {"val": 12409, "part": 43.0, "v": {"0": 8811, "1": 3598}}, "8206": {"val": 7800, "part": 48.8, "v": {"0": 5392, "1": 2408}}, "8207": {"val": 3926, "part": 48.0, "v": {"0": 2139, "1": 1787}}, "8301": {"val": 60103, "part": 41.9, "v": {"0": 33517, "1": 26586}}, "8302": {"val": 1851, "part": 43.9, "v": {"0": 1425, "1": 426}}, "8303": {"val": 10647, "part": 47.9, "v": {"1": 3054, "0": 7593}}, "8304": {"val": 8703, "part": 42.9, "v": {"1": 2855, "0": 5848}}, "8305": {"val": 11202, "part": 44.9, "v": {"1": 2977, "0": 8225}}, "8306": {"val": 9698, "part": 42.3, "v": {"1": 3292, "0": 6406}}, "8307": {"val": 4111, "part": 50.7, "v": {"0": 2729, "1": 1382}}, "8308": {"val": 1973, "part": 48.1, "v": {"0": 1369, "1": 604}}, "8309": {"val": 4290, "part": 48.5, "v": {"0": 2895, "1": 1395}}, "8310": {"val": 2009, "part": 48.6, "v": {"0": 1515, "1": 494}}, "8311": {"val": 5288, "part": 43.0, "v": {"1": 2176, "0": 3112}}, "8312": {"val": 5558, "part": 46.7, "v": {"1": 1321, "0": 4237}}, "8313": {"val": 9334, "part": 49.6, "v": {"1": 2887, "0": 6447}}, "8314": {"val": 1700, "part": 36.9, "v": {"0": 1051, "1": 649}}, "9101": {"val": 86338, "part": 40.3, "v": {"0": 46104, "1": 40234}}, "9102": {"val": 10322, "part": 44.3, "v": {"1": 3785, "0": 6537}}, "9103": {"val": 7216, "part": 38.8, "v": {"1": 2976, "0": 4240}}, "9104": {"val": 2736, "part": 36.4, "v": {"1": 1231, "0": 1505}}, "9105": {"val": 8855, "part": 41.9, "v": {"0": 5651, "1": 3204}}, "9106": {"val": 5135, "part": 45.5, "v": {"1": 1706, "0": 3429}}, "9107": {"val": 6634, "part": 44.3, "v": {"0": 3471, "1": 3163}}, "9108": {"val": 13285, "part": 43.5, "v": {"0": 8456, "1": 4829}}, "9109": {"val": 8944, "part": 41.7, "v": {"0": 5437, "1": 3507}}, "9110": {"val": 2242, "part": 32.2, "v": {"1": 1018, "0": 1224}}, "9111": {"val": 12975, "part": 45.6, "v": {"0": 8396, "1": 4579}}, "9112": {"val": 19848, "part": 39.6, "v": {"0": 11941, "1": 7907}}, "9113": {"val": 3179, "part": 51.6, "v": {"1": 990, "0": 2189}}, "9114": {"val": 9016, "part": 43.2, "v": {"0": 5251, "1": 3765}}, "9115": {"val": 7827, "part": 34.9, "v": {"0": 3532, "1": 4295}}, "9116": {"val": 5199, "part": 42.2, "v": {"1": 1612, "0": 3587}}, "9117": {"val": 6547, "part": 49.6, "v": {"1": 3081, "0": 3466}}, "9118": {"val": 4456, "part": 44.6, "v": {"0": 2332, "1": 2124}}, "9119": {"val": 9465, "part": 43.9, "v": {"1": 3406, "0": 6059}}, "9120": {"val": 17900, "part": 38.4, "v": {"1": 8564, "0": 9336}}, "9121": {"val": 4561, "part": 50.4, "v": {"0": 2770, "1": 1791}}, "9201": {"val": 19409, "part": 44.1, "v": {"1": 7896, "0": 11513}}, "9202": {"val": 9432, "part": 45.9, "v": {"1": 2812, "0": 6620}}, "9203": {"val": 7045, "part": 35.0, "v": {"0": 4364, "1": 2681}}, "9204": {"val": 3275, "part": 43.4, "v": {"0": 1999, "1": 1276}}, "9205": {"val": 3992, "part": 36.7, "v": {"1": 1976, "0": 2016}}, "9206": {"val": 3701, "part": 52.4, "v": {"1": 1238, "0": 2463}}, "9207": {"val": 4200, "part": 47.4, "v": {"1": 1521, "0": 2679}}, "9208": {"val": 5327, "part": 46.5, "v": {"1": 2009, "0": 3318}}, "9209": {"val": 4157, "part": 48.1, "v": {"1": 1245, "0": 2912}}, "9210": {"val": 8339, "part": 46.4, "v": {"0": 5569, "1": 2770}}, "9211": {"val": 12962, "part": 41.8, "v": {"1": 4836, "0": 8126}}}, "local": {"00001": {"val": 2945, "part": 44.6, "v": {"1": 895, "0": 2050}}, "00002": {"val": 1709, "part": 33.6, "v": {"0": 1076, "1": 633}}, "00003": {"val": 686, "part": 7.5, "v": {"1": 315, "0": 371}}, "00013": {"val": 712, "part": 26.2, "v": {"1": 455, "0": 257}}, "00014": {"val": 384, "part": 15.0, "v": {"1": 252, "0": 132}}, "00015": {"val": 29, "part": 31.3, "v": {"1": 9, "0": 20}}, "00016": {"val": 1161, "part": 13.2, "v": {"0": 712, "1": 449}}, "00024": {"val": 1326, "part": 32.1, "v": {"0": 683, "1": 643}}, "00025": {"val": 2929, "part": 35.8, "v": {"1": 1342, "0": 1587}}, "00026": {"val": 1913, "part": 28.6, "v": {"0": 1107, "1": 806}}, "00027": {"val": 2163, "part": 41.6, "v": {"1": 1111, "0": 1052}}, "00028": {"val": 1543, "part": 24.1, "v": {"0": 915, "1": 628}}, "00029": {"val": 2531, "part": 26.4, "v": {"0": 1340, "1": 1191}}, "00030": {"val": 2229, "part": 33.0, "v": {"1": 931, "0": 1298}}, "00031": {"val": 3153, "part": 33.4, "v": {"1": 1563, "0": 1590}}, "00032": {"val": 2667, "part": 32.7, "v": {"1": 1284, "0": 1383}}, "00037": {"val": 3094, "part": 31.4, "v": {"0": 1844, "1": 1250}}, "00042": {"val": 1889, "part": 28.4, "v": {"0": 983, "1": 906}}, "00043": {"val": 2317, "part": 28.6, "v": {"0": 1298, "1": 1019}}, "00050": {"val": 1243, "part": 36.9, "v": {"0": 615, "1": 628}}, "00053": {"val": 1132, "part": 22.9, "v": {"0": 573, "1": 559}}, "00054": {"val": 2632, "part": 31.2, "v": {"1": 1136, "0": 1496}}, "00055": {"val": 1021, "part": 36.6, "v": {"0": 448, "1": 573}}, "00056": {"val": 3315, "part": 33.8, "v": {"0": 1896, "1": 1419}}, "00063": {"val": 1623, "part": 36.2, "v": {"1": 605, "0": 1018}}, "00065": {"val": 133, "part": 40.6, "v": {"1": 33, "0": 100}}, "00066": {"val": 1400, "part": 31.7, "v": {"0": 881, "1": 519}}, "00067": {"val": 1501, "part": 28.1, "v": {"0": 916, "1": 585}}, "00083": {"val": 2587, "part": 31.9, "v": {"0": 1736, "1": 851}}, "00086": {"val": 2314, "part": 29.4, "v": {"1": 800, "0": 1514}}, "00127": {"val": 3898, "part": 38.9, "v": {"1": 1474, "0": 2424}}, "00133": {"val": 1721, "part": 30.4, "v": {"1": 682, "0": 1039}}, "00134": {"val": 1687, "part": 27.7, "v": {"1": 674, "0": 1013}}, "00144": {"val": 4323, "part": 31.5, "v": {"0": 2642, "1": 1681}}, "00161": {"val": 74, "part": 41.1, "v": {"0": 50, "1": 24}}, "00185": {"val": 478, "part": 44.9, "v": {"0": 342, "1": 136}}, "00193": {"val": 4164, "part": 36.3, "v": {"0": 2938, "1": 1226}}, "00197": {"val": 6299, "part": 40.4, "v": {"0": 4280, "1": 2019}}, "00198": {"val": 4895, "part": 29.6, "v": {"0": 3059, "1": 1836}}, "00202": {"val": 5930, "part": 34.8, "v": {"1": 1948, "0": 3982}}, "00216": {"val": 5501, "part": 42.8, "v": {"0": 3666, "1": 1835}}, "00222": {"val": 2920, "part": 28.9, "v": {"0": 2403, "1": 517}}, "00227": {"val": 3186, "part": 42.7, "v": {"1": 750, "0": 2436}}, "00233": {"val": 485, "part": 48.7, "v": {"0": 439, "1": 46}}, "00239": {"val": 3850, "part": 36.5, "v": {"0": 2694, "1": 1156}}, "00243": {"val": 2442, "part": 44.3, "v": {"1": 535, "0": 1907}}, "00248": {"val": 2504, "part": 44.1, "v": {"0": 2022, "1": 482}}, "00249": {"val": 2911, "part": 46.7, "v": {"1": 588, "0": 2323}}, "00253": {"val": 4264, "part": 41.9, "v": {"0": 2760, "1": 1504}}, "00260": {"val": 4003, "part": 39.7, "v": {"0": 2434, "1": 1569}}, "00261": {"val": 1336, "part": 29.7, "v": {"0": 813, "1": 523}}, "00272": {"val": 3357, "part": 47.4, "v": {"1": 732, "0": 2625}}, "00278": {"val": 4731, "part": 47.0, "v": {"0": 3184, "1": 1547}}, "00280": {"val": 4229, "part": 42.0, "v": {"1": 1625, "0": 2604}}, "00281": {"val": 4613, "part": 45.7, "v": {"0": 3189, "1": 1424}}, "00292": {"val": 4807, "part": 47.6, "v": {"1": 1596, "0": 3211}}, "00294": {"val": 4919, "part": 49.0, "v": {"1": 2071, "0": 2848}}, "00297": {"val": 1899, "part": 20.3, "v": {"0": 1409, "1": 490}}, "00298": {"val": 4723, "part": 46.7, "v": {"1": 1003, "0": 3720}}, "00302": {"val": 491, "part": 50.6, "v": {"0": 403, "1": 88}}, "00303": {"val": 2440, "part": 35.9, "v": {"0": 1740, "1": 700}}, "00304": {"val": 2477, "part": 46.1, "v": {"0": 1793, "1": 684}}, "00308": {"val": 2014, "part": 45.6, "v": {"0": 1695, "1": 319}}, "00309": {"val": 1788, "part": 74.6, "v": {"1": 224, "0": 1564}}, "00311": {"val": 2360, "part": 31.4, "v": {"0": 1922, "1": 438}}, "00313": {"val": 884, "part": 48.5, "v": {"0": 698, "1": 186}}, "00315": {"val": 1680, "part": 69.4, "v": {"0": 1280, "1": 400}}, "00316": {"val": 3993, "part": 46.8, "v": {"1": 902, "0": 3091}}, "00318": {"val": 960, "part": 21.5, "v": {"1": 343, "0": 617}}, "00329": {"val": 3792, "part": 44.8, "v": {"0": 2900, "1": 892}}, "00337": {"val": 573, "part": 53.6, "v": {"0": 345, "1": 228}}, "00341": {"val": 4054, "part": 43.4, "v": {"1": 1014, "0": 3040}}, "00344": {"val": 4782, "part": 48.5, "v": {"0": 3434, "1": 1348}}, "00345": {"val": 4524, "part": 42.8, "v": {"1": 1217, "0": 3307}}, "00351": {"val": 3948, "part": 48.1, "v": {"0": 3129, "1": 819}}, "00356": {"val": 4950, "part": 34.6, "v": {"1": 1646, "0": 3304}}, "00357": {"val": 3582, "part": 49.0, "v": {"0": 2558, "1": 1024}}, "00361": {"val": 2498, "part": 52.9, "v": {"1": 583, "0": 1915}}, "00363": {"val": 4203, "part": 47.9, "v": {"1": 1688, "0": 2515}}, "00365": {"val": 3409, "part": 46.9, "v": {"1": 1389, "0": 2020}}, "00366": {"val": 4740, "part": 42.6, "v": {"0": 3048, "1": 1692}}, "00377": {"val": 4032, "part": 48.7, "v": {"1": 1890, "0": 2142}}, "00379": {"val": 2877, "part": 51.7, "v": {"0": 1646, "1": 1231}}, "00381": {"val": 4420, "part": 52.9, "v": {"0": 2607, "1": 1813}}, "00384": {"val": 3328, "part": 48.6, "v": {"1": 1164, "0": 2164}}, "00387": {"val": 2590, "part": 47.4, "v": {"0": 1543, "1": 1047}}, "00394": {"val": 6931, "part": 53.7, "v": {"0": 4844, "1": 2087}}, "00411": {"val": 6348, "part": 44.6, "v": {"1": 1986, "0": 4362}}, "00412": {"val": 5047, "part": 45.9, "v": {"0": 3188, "1": 1859}}, "00417": {"val": 2632, "part": 48.6, "v": {"1": 786, "0": 1846}}, "00420": {"val": 1914, "part": 46.8, "v": {"1": 694, "0": 1220}}, "00425": {"val": 3190, "part": 45.0, "v": {"0": 2613, "1": 577}}, "00430": {"val": 2923, "part": 51.3, "v": {"0": 2267, "1": 656}}, "00438": {"val": 1748, "part": 52.9, "v": {"1": 839, "0": 909}}, "00443": {"val": 2081, "part": 41.1, "v": {"0": 1278, "1": 803}}, "00444": {"val": 1691, "part": 40.5, "v": {"0": 1104, "1": 587}}, "00448": {"val": 3108, "part": 29.1, "v": {"1": 1634, "0": 1474}}, "00456": {"val": 4656, "part": 41.9, "v": {"0": 2722, "1": 1934}}, "00457": {"val": 3065, "part": 41.4, "v": {"0": 1824, "1": 1241}}, "00463": {"val": 5207, "part": 39.5, "v": {"0": 3168, "1": 2039}}, "00469": {"val": 4631, "part": 45.1, "v": {"0": 2840, "1": 1791}}, "00471": {"val": 1915, "part": 43.6, "v": {"0": 1200, "1": 715}}, "00474": {"val": 2142, "part": 52.4, "v": {"0": 1530, "1": 612}}, "00481": {"val": 3647, "part": 42.0, "v": {"1": 874, "0": 2773}}, "00494": {"val": 3380, "part": 45.6, "v": {"0": 2461, "1": 919}}, "00497": {"val": 3899, "part": 41.6, "v": {"1": 1509, "0": 2390}}, "00508": {"val": 1816, "part": 37.5, "v": {"0": 1247, "1": 569}}, "00515": {"val": 1797, "part": 36.9, "v": {"1": 560, "0": 1237}}, "00519": {"val": 1299, "part": 40.0, "v": {"0": 836, "1": 463}}, "00530": {"val": 3120, "part": 31.6, "v": {"0": 1982, "1": 1138}}, "00534": {"val": 3136, "part": 51.8, "v": {"0": 2169, "1": 967}}, "00539": {"val": 2881, "part": 34.2, "v": {"1": 1009, "0": 1872}}, "00542": {"val": 3710, "part": 36.7, "v": {"0": 2509, "1": 1201}}, "00559": {"val": 930, "part": 32.6, "v": {"1": 394, "0": 536}}, "00566": {"val": 5387, "part": 51.8, "v": {"0": 2760, "1": 2627}}, "00568": {"val": 2874, "part": 23.6, "v": {"0": 1291, "1": 1583}}, "00575": {"val": 4441, "part": 43.9, "v": {"1": 1925, "0": 2516}}, "00576": {"val": 3644, "part": 44.8, "v": {"0": 2194, "1": 1450}}, "00578": {"val": 2753, "part": 60.4, "v": {"0": 1246, "1": 1507}}, "00579": {"val": 5681, "part": 47.6, "v": {"1": 2199, "0": 3482}}, "00581": {"val": 3885, "part": 39.0, "v": {"0": 1946, "1": 1939}}, "00588": {"val": 4967, "part": 44.3, "v": {"1": 1848, "0": 3119}}, "00592": {"val": 2813, "part": 54.3, "v": {"0": 721, "1": 2092}}, "00596": {"val": 4668, "part": 38.8, "v": {"1": 2255, "0": 2413}}, "00598": {"val": 5797, "part": 39.3, "v": {"1": 2178, "0": 3619}}, "00599": {"val": 794, "part": 21.0, "v": {"1": 552, "0": 242}}, "00602": {"val": 6324, "part": 42.5, "v": {"1": 2254, "0": 4070}}, "00603": {"val": 1349, "part": 40.4, "v": {"1": 601, "0": 748}}, "00621": {"val": 3989, "part": 30.5, "v": {"0": 1175, "1": 2814}}, "00624": {"val": 5727, "part": 42.8, "v": {"1": 3839, "0": 1888}}, "00625": {"val": 2501, "part": 22.4, "v": {"0": 981, "1": 1520}}, "00627": {"val": 3963, "part": 32.9, "v": {"1": 2108, "0": 1855}}, "00635": {"val": 5301, "part": 42.6, "v": {"0": 3339, "1": 1962}}, "00636": {"val": 3895, "part": 39.0, "v": {"1": 2290, "0": 1605}}, "00641": {"val": 5901, "part": 45.9, "v": {"1": 2352, "0": 3549}}, "00644": {"val": 6097, "part": 44.0, "v": {"1": 2014, "0": 4083}}, "00647": {"val": 2328, "part": 47.3, "v": {"1": 674, "0": 1654}}, "00648": {"val": 2414, "part": 47.6, "v": {"1": 708, "0": 1706}}, "00653": {"val": 3141, "part": 51.5, "v": {"0": 2242, "1": 899}}, "00654": {"val": 2578, "part": 40.7, "v": {"0": 1782, "1": 796}}, "00655": {"val": 2572, "part": 42.9, "v": {"1": 769, "0": 1803}}, "00656": {"val": 1232, "part": 60.2, "v": {"0": 898, "1": 334}}, "00657": {"val": 1336, "part": 62.9, "v": {"1": 332, "0": 1004}}, "00660": {"val": 5633, "part": 48.3, "v": {"0": 3895, "1": 1738}}, "00661": {"val": 5887, "part": 47.5, "v": {"0": 4007, "1": 1880}}, "00662": {"val": 1665, "part": 53.0, "v": {"1": 577, "0": 1088}}, "00663": {"val": 2404, "part": 65.6, "v": {"0": 1553, "1": 851}}, "00664": {"val": 3059, "part": 44.6, "v": {"1": 941, "0": 2118}}, "00665": {"val": 3112, "part": 42.0, "v": {"1": 1041, "0": 2071}}, "00666": {"val": 1430, "part": 54.1, "v": {"0": 976, "1": 454}}, "00667": {"val": 1619, "part": 53.0, "v": {"0": 1112, "1": 507}}, "00668": {"val": 1715, "part": 51.4, "v": {"1": 549, "0": 1166}}, "00669": {"val": 1176, "part": 62.7, "v": {"0": 910, "1": 266}}, "00670": {"val": 5250, "part": 50.4, "v": {"1": 1782, "0": 3468}}, "00673": {"val": 1470, "part": 28.2, "v": {"1": 785, "0": 685}}, "00674": {"val": 4812, "part": 45.8, "v": {"1": 1657, "0": 3155}}, "00676": {"val": 4057, "part": 46.4, "v": {"0": 2574, "1": 1483}}, "00685": {"val": 3370, "part": 52.9, "v": {"1": 1043, "0": 2327}}, "00697": {"val": 1201, "part": 47.0, "v": {"0": 921, "1": 280}}, "00700": {"val": 2324, "part": 49.6, "v": {"1": 732, "0": 1592}}, "00701": {"val": 2334, "part": 50.2, "v": {"0": 1625, "1": 709}}, "00702": {"val": 6012, "part": 50.6, "v": {"1": 1681, "0": 4331}}, "00706": {"val": 3931, "part": 46.0, "v": {"1": 1052, "0": 2879}}, "00707": {"val": 3632, "part": 53.9, "v": {"0": 2596, "1": 1036}}, "00708": {"val": 2942, "part": 49.3, "v": {"1": 1084, "0": 1858}}, "00710": {"val": 2916, "part": 48.8, "v": {"1": 1144, "0": 1772}}, "00712": {"val": 3746, "part": 51.2, "v": {"1": 1211, "0": 2535}}, "00714": {"val": 2882, "part": 51.3, "v": {"1": 974, "0": 1908}}, "00715": {"val": 3066, "part": 53.7, "v": {"1": 955, "0": 2111}}, "00717": {"val": 1207, "part": 17.2, "v": {"1": 629, "0": 578}}, "00720": {"val": 5095, "part": 48.2, "v": {"1": 2120, "0": 2975}}, "00721": {"val": 4183, "part": 41.7, "v": {"1": 1510, "0": 2673}}, "00729": {"val": 6489, "part": 49.7, "v": {"1": 2323, "0": 4166}}, "00734": {"val": 4237, "part": 46.6, "v": {"0": 2653, "1": 1584}}, "00737": {"val": 4502, "part": 39.5, "v": {"0": 2876, "1": 1626}}, "00738": {"val": 1881, "part": 17.8, "v": {"0": 1112, "1": 769}}, "00739": {"val": 3295, "part": 46.7, "v": {"0": 2063, "1": 1232}}, "00740": {"val": 2451, "part": 23.8, "v": {"1": 1030, "0": 1421}}, "00743": {"val": 3832, "part": 52.3, "v": {"0": 2443, "1": 1389}}, "00748": {"val": 5516, "part": 51.6, "v": {"1": 1562, "0": 3954}}, "00753": {"val": 4993, "part": 47.4, "v": {"0": 3726, "1": 1267}}, "00758": {"val": 1189, "part": 43.7, "v": {"0": 822, "1": 367}}, "00759": {"val": 4343, "part": 49.4, "v": {"0": 3017, "1": 1326}}, "00761": {"val": 4364, "part": 50.5, "v": {"1": 1358, "0": 3006}}, "00767": {"val": 2880, "part": 41.2, "v": {"0": 1607, "1": 1273}}, "00770": {"val": 2840, "part": 44.1, "v": {"1": 1314, "0": 1526}}, "00771": {"val": 4400, "part": 43.2, "v": {"0": 2874, "1": 1526}}, "00772": {"val": 4805, "part": 47.5, "v": {"1": 1603, "0": 3202}}, "00778": {"val": 6229, "part": 52.2, "v": {"1": 2019, "0": 4210}}, "00780": {"val": 5924, "part": 49.5, "v": {"0": 4201, "1": 1723}}, "00782": {"val": 3647, "part": 35.5, "v": {"1": 1493, "0": 2154}}, "00788": {"val": 3878, "part": 46.3, "v": {"0": 2220, "1": 1658}}, "00789": {"val": 4621, "part": 45.9, "v": {"0": 2963, "1": 1658}}, "00792": {"val": 6230, "part": 46.8, "v": {"0": 3677, "1": 2553}}, "00794": {"val": 7526, "part": 47.5, "v": {"0": 4385, "1": 3141}}, "00796": {"val": 453, "part": 53.8, "v": {"0": 193, "1": 260}}, "00797": {"val": 436, "part": 52.9, "v": {"1": 168, "0": 268}}, "00798": {"val": 2680, "part": 57.4, "v": {"1": 1028, "0": 1652}}, "00799": {"val": 2507, "part": 58.5, "v": {"0": 1534, "1": 973}}, "00800": {"val": 3857, "part": 50.0, "v": {"0": 3030, "1": 827}}, "00802": {"val": 3795, "part": 46.3, "v": {"1": 776, "0": 3019}}, "00804": {"val": 3398, "part": 45.6, "v": {"0": 2377, "1": 1021}}, "00807": {"val": 2719, "part": 49.9, "v": {"1": 680, "0": 2039}}, "00809": {"val": 3715, "part": 51.8, "v": {"1": 1119, "0": 2596}}, "00811": {"val": 1846, "part": 45.5, "v": {"0": 1479, "1": 367}}, "00815": {"val": 1685, "part": 43.2, "v": {"0": 1259, "1": 426}}, "00816": {"val": 484, "part": 61.7, "v": {"0": 311, "1": 173}}, "00817": {"val": 880, "part": 67.2, "v": {"1": 252, "0": 628}}, "00823": {"val": 7115, "part": 49.6, "v": {"0": 4923, "1": 2192}}, "00826": {"val": 7130, "part": 53.4, "v": {"1": 2338, "0": 4792}}, "00834": {"val": 7433, "part": 52.3, "v": {"0": 4615, "1": 2818}}, "00846": {"val": 1959, "part": 54.8, "v": {"1": 419, "0": 1540}}, "00848": {"val": 691, "part": 73.2, "v": {"1": 228, "0": 463}}, "00850": {"val": 2587, "part": 47.9, "v": {"1": 634, "0": 1953}}, "00855": {"val": 6307, "part": 41.7, "v": {"1": 2894, "0": 3413}}, "00858": {"val": 7222, "part": 49.9, "v": {"0": 4702, "1": 2520}}, "00861": {"val": 3158, "part": 46.1, "v": {"1": 1068, "0": 2090}}, "00862": {"val": 7042, "part": 48.2, "v": {"1": 2362, "0": 4680}}, "00864": {"val": 3408, "part": 49.7, "v": {"0": 2430, "1": 978}}, "00865": {"val": 2803, "part": 41.5, "v": {"0": 1835, "1": 968}}, "00866": {"val": 944, "part": 63.5, "v": {"1": 299, "0": 645}}, "00870": {"val": 3397, "part": 50.2, "v": {"0": 2509, "1": 888}}, "00873": {"val": 5071, "part": 55.9, "v": {"0": 4046, "1": 1025}}, "00875": {"val": 3754, "part": 49.8, "v": {"1": 1066, "0": 2688}}, "00879": {"val": 6957, "part": 47.4, "v": {"1": 1998, "0": 4959}}, "00883": {"val": 985, "part": 44.5, "v": {"0": 592, "1": 393}}, "00885": {"val": 5037, "part": 49.6, "v": {"0": 3199, "1": 1838}}, "00886": {"val": 8262, "part": 51.3, "v": {"1": 3139, "0": 5123}}, "00898": {"val": 3919, "part": 51.5, "v": {"0": 2652, "1": 1267}}, "00900": {"val": 413, "part": 75.1, "v": {"0": 298, "1": 115}}, "00901": {"val": 4641, "part": 54.6, "v": {"0": 3203, "1": 1438}}, "00903": {"val": 309, "part": 67.2, "v": {"1": 84, "0": 225}}, "00904": {"val": 2398, "part": 53.0, "v": {"0": 1718, "1": 680}}, "00908": {"val": 1838, "part": 49.6, "v": {"0": 1092, "1": 746}}, "00910": {"val": 3920, "part": 48.9, "v": {"1": 1538, "0": 2382}}, "00911": {"val": 5421, "part": 52.5, "v": {"0": 3937, "1": 1484}}, "00914": {"val": 6278, "part": 50.6, "v": {"1": 2082, "0": 4196}}, "00917": {"val": 1441, "part": 64.3, "v": {"0": 989, "1": 452}}, "00919": {"val": 2196, "part": 54.6, "v": {"0": 1635, "1": 561}}, "00920": {"val": 2768, "part": 33.5, "v": {"1": 828, "0": 1940}}, "00921": {"val": 5401, "part": 49.7, "v": {"1": 1023, "0": 4378}}, "00925": {"val": 316, "part": 56.9, "v": {"1": 119, "0": 197}}, "00927": {"val": 729, "part": 56.3, "v": {"1": 207, "0": 522}}, "00932": {"val": 4036, "part": 47.7, "v": {"0": 2868, "1": 1168}}, "00934": {"val": 3873, "part": 44.7, "v": {"0": 2473, "1": 1400}}, "00935": {"val": 3937, "part": 54.0, "v": {"1": 1089, "0": 2848}}, "00936": {"val": 4006, "part": 51.6, "v": {"1": 1173, "0": 2833}}, "00937": {"val": 1788, "part": 36.6, "v": {"1": 722, "0": 1066}}, "00939": {"val": 3993, "part": 50.9, "v": {"0": 2722, "1": 1271}}, "00941": {"val": 3931, "part": 51.8, "v": {"1": 1115, "0": 2816}}, "00942": {"val": 1442, "part": 19.2, "v": {"0": 724, "1": 718}}, "00943": {"val": 3591, "part": 47.6, "v": {"0": 2613, "1": 978}}, "00946": {"val": 3832, "part": 49.3, "v": {"1": 1083, "0": 2749}}, "00948": {"val": 3532, "part": 48.6, "v": {"1": 1181, "0": 2351}}, "00950": {"val": 1244, "part": 16.5, "v": {"0": 638, "1": 606}}, "00952": {"val": 3511, "part": 48.1, "v": {"0": 1972, "1": 1539}}, "00953": {"val": 3849, "part": 50.4, "v": {"0": 2493, "1": 1356}}, "00956": {"val": 3448, "part": 45.6, "v": {"0": 2455, "1": 993}}, "00958": {"val": 3892, "part": 51.4, "v": {"0": 2901, "1": 991}}, "00961": {"val": 3374, "part": 45.1, "v": {"1": 1037, "0": 2337}}, "00971": {"val": 4553, "part": 49.7, "v": {"0": 3122, "1": 1431}}, "00974": {"val": 5251, "part": 40.5, "v": {"0": 3521, "1": 1730}}, "00979": {"val": 1271, "part": 45.2, "v": {"1": 490, "0": 781}}, "00981": {"val": 3543, "part": 53.3, "v": {"1": 1215, "0": 2328}}, "00986": {"val": 905, "part": 80.0, "v": {"0": 600, "1": 305}}, "00987": {"val": 2976, "part": 49.7, "v": {"1": 833, "0": 2143}}, "00990": {"val": 3084, "part": 49.5, "v": {"1": 881, "0": 2203}}, "00994": {"val": 1700, "part": 36.9, "v": {"1": 649, "0": 1051}}, "00999": {"val": 2172, "part": 34.5, "v": {"0": 1319, "1": 853}}, "01002": {"val": 2597, "part": 49.4, "v": {"1": 656, "0": 1941}}, "01003": {"val": 1713, "part": 54.4, "v": {"0": 1279, "1": 434}}, "01009": {"val": 3518, "part": 49.7, "v": {"1": 1114, "0": 2404}}, "01010": {"val": 2315, "part": 44.7, "v": {"0": 1670, "1": 645}}, "01018": {"val": 3573, "part": 42.2, "v": {"1": 1275, "0": 2298}}, "01033": {"val": 3035, "part": 57.0, "v": {"0": 2119, "1": 916}}, "01035": {"val": 1964, "part": 50.2, "v": {"1": 824, "0": 1140}}, "01049": {"val": 1161, "part": 20.9, "v": {"1": 700, "0": 461}}, "01059": {"val": 6772, "part": 43.8, "v": {"0": 3843, "1": 2929}}, "01060": {"val": 1485, "part": 32.2, "v": {"1": 740, "0": 745}}, "01062": {"val": 2764, "part": 38.1, "v": {"0": 1144, "1": 1620}}, "01065": {"val": 2544, "part": 37.5, "v": {"1": 1359, "0": 1185}}, "01066": {"val": 2156, "part": 32.4, "v": {"0": 1182, "1": 974}}, "01069": {"val": 3249, "part": 44.5, "v": {"0": 1969, "1": 1280}}, "01071": {"val": 1414, "part": 48.6, "v": {"0": 878, "1": 536}}, "01083": {"val": 3828, "part": 45.8, "v": {"1": 1096, "0": 2732}}, "01087": {"val": 612, "part": 58.2, "v": {"0": 358, "1": 254}}, "01097": {"val": 2961, "part": 47.1, "v": {"0": 2146, "1": 815}}, "01101": {"val": 2121, "part": 49.7, "v": {"0": 1485, "1": 636}}, "01102": {"val": 2920, "part": 51.9, "v": {"1": 874, "0": 2046}}, "01104": {"val": 2731, "part": 48.3, "v": {"1": 1098, "0": 1633}}, "01110": {"val": 3527, "part": 42.0, "v": {"0": 2487, "1": 1040}}, "01111": {"val": 1632, "part": 40.4, "v": {"1": 444, "0": 1188}}, "01112": {"val": 1872, "part": 46.5, "v": {"1": 502, "0": 1370}}, "01123": {"val": 1421, "part": 42.0, "v": {"0": 909, "1": 512}}, "01128": {"val": 3205, "part": 46.3, "v": {"1": 845, "0": 2360}}, "01129": {"val": 3416, "part": 46.4, "v": {"1": 817, "0": 2599}}, "01130": {"val": 2153, "part": 35.8, "v": {"0": 1574, "1": 579}}, "01135": {"val": 3937, "part": 51.9, "v": {"0": 2725, "1": 1212}}, "01142": {"val": 1383, "part": 15.9, "v": {"0": 470, "1": 913}}, "01143": {"val": 617, "part": 11.6, "v": {"0": 217, "1": 400}}, "01144": {"val": 2367, "part": 41.0, "v": {"0": 1368, "1": 999}}, "01152": {"val": 3760, "part": 45.0, "v": {"1": 2108, "0": 1652}}, "01155": {"val": 1282, "part": 15.2, "v": {"0": 524, "1": 758}}, "01167": {"val": 2909, "part": 57.9, "v": {"1": 942, "0": 1967}}, "01168": {"val": 2631, "part": 50.0, "v": {"1": 636, "0": 1995}}, "01172": {"val": 1736, "part": 49.6, "v": {"1": 453, "0": 1283}}, "01173": {"val": 2594, "part": 48.1, "v": {"0": 1998, "1": 596}}, "01176": {"val": 3335, "part": 43.5, "v": {"0": 2477, "1": 858}}, "01177": {"val": 3815, "part": 48.7, "v": {"1": 867, "0": 2948}}, "01179": {"val": 2495, "part": 39.6, "v": {"0": 1793, "1": 702}}, "01184": {"val": 2125, "part": 34.6, "v": {"1": 794, "0": 1331}}, "01185": {"val": 3746, "part": 45.0, "v": {"1": 1232, "0": 2514}}, "01188": {"val": 1528, "part": 61.6, "v": {"1": 298, "0": 1230}}, "01192": {"val": 1547, "part": 40.9, "v": {"1": 579, "0": 968}}, "01197": {"val": 1973, "part": 48.1, "v": {"1": 604, "0": 1369}}, "01200": {"val": 1478, "part": 26.0, "v": {"1": 590, "0": 888}}, "01201": {"val": 1895, "part": 62.9, "v": {"0": 1249, "1": 646}}, "01205": {"val": 1385, "part": 27.1, "v": {"0": 621, "1": 764}}, "01206": {"val": 3882, "part": 46.2, "v": {"1": 1367, "0": 2515}}, "01208": {"val": 3373, "part": 46.4, "v": {"1": 1181, "0": 2192}}, "01213": {"val": 3873, "part": 51.0, "v": {"1": 1324, "0": 2549}}, "01214": {"val": 2009, "part": 48.6, "v": {"0": 1515, "1": 494}}, "01220": {"val": 2651, "part": 44.3, "v": {"0": 1656, "1": 995}}, "01224": {"val": 1219, "part": 22.1, "v": {"0": 680, "1": 539}}, "01226": {"val": 1108, "part": 35.5, "v": {"0": 498, "1": 610}}, "01227": {"val": 3203, "part": 50.3, "v": {"0": 2291, "1": 912}}, "01229": {"val": 1756, "part": 41.0, "v": {"0": 1023, "1": 733}}, "01238": {"val": 1632, "part": 36.8, "v": {"1": 839, "0": 793}}, "01239": {"val": 2277, "part": 44.0, "v": {"0": 1452, "1": 825}}, "01246": {"val": 14550, "part": 39.0, "v": {"0": 9199, "1": 5351}}, "01259": {"val": 3374, "part": 47.2, "v": {"0": 2357, "1": 1017}}, "01268": {"val": 745, "part": 48.3, "v": {"0": 523, "1": 222}}, "01269": {"val": 2941, "part": 49.1, "v": {"0": 1954, "1": 987}}, "01272": {"val": 982, "part": 52.1, "v": {"0": 742, "1": 240}}, "01274": {"val": 2969, "part": 46.5, "v": {"0": 1845, "1": 1124}}, "01276": {"val": 1804, "part": 38.1, "v": {"1": 797, "0": 1007}}, "01283": {"val": 368, "part": 76.6, "v": {"1": 113, "0": 255}}, "01291": {"val": 1872, "part": 43.5, "v": {"0": 1220, "1": 652}}, "01292": {"val": 2241, "part": 44.8, "v": {"0": 1516, "1": 725}}, "01294": {"val": 2310, "part": 43.4, "v": {"1": 626, "0": 1684}}, "01298": {"val": 2478, "part": 41.0, "v": {"1": 1027, "0": 1451}}, "01299": {"val": 1928, "part": 38.3, "v": {"0": 1124, "1": 804}}, "01300": {"val": 1545, "part": 57.4, "v": {"1": 569, "0": 976}}, "01301": {"val": 1433, "part": 27.5, "v": {"0": 860, "1": 573}}, "01302": {"val": 3488, "part": 39.6, "v": {"0": 2163, "1": 1325}}, "01303": {"val": 2124, "part": 34.6, "v": {"0": 1341, "1": 783}}, "01309": {"val": 2821, "part": 41.3, "v": {"1": 1110, "0": 1711}}, "01312": {"val": 1622, "part": 32.8, "v": {"1": 570, "0": 1052}}, "01313": {"val": 1504, "part": 30.8, "v": {"1": 561, "0": 943}}, "01315": {"val": 2303, "part": 59.2, "v": {"1": 801, "0": 1502}}, "01316": {"val": 648, "part": 56.2, "v": {"0": 439, "1": 209}}, "01317": {"val": 2438, "part": 46.4, "v": {"0": 1652, "1": 786}}, "01318": {"val": 2697, "part": 44.7, "v": {"1": 920, "0": 1777}}, "01322": {"val": 994, "part": 52.7, "v": {"0": 459, "1": 535}}, "01323": {"val": 382, "part": 61.4, "v": {"0": 208, "1": 174}}, "01332": {"val": 994, "part": 54.7, "v": {"1": 365, "0": 629}}, "01336": {"val": 4023, "part": 42.1, "v": {"0": 2484, "1": 1539}}, "01337": {"val": 1870, "part": 38.3, "v": {"0": 1123, "1": 747}}, "01339": {"val": 2238, "part": 39.2, "v": {"0": 1372, "1": 866}}, "01342": {"val": 1766, "part": 35.9, "v": {"0": 890, "1": 876}}, "01346": {"val": 3701, "part": 52.4, "v": {"0": 2463, "1": 1238}}, "01347": {"val": 1637, "part": 64.5, "v": {"0": 875, "1": 762}}, "01348": {"val": 2023, "part": 37.8, "v": {"0": 1537, "1": 486}}, "01352": {"val": 2242, "part": 32.2, "v": {"0": 1224, "1": 1018}}, "01357": {"val": 3244, "part": 44.0, "v": {"0": 2146, "1": 1098}}, "01362": {"val": 1158, "part": 23.5, "v": {"0": 597, "1": 561}}, "01363": {"val": 2955, "part": 46.3, "v": {"0": 1848, "1": 1107}}, "01365": {"val": 1202, "part": 19.0, "v": {"0": 627, "1": 575}}, "01371": {"val": 2436, "part": 42.8, "v": {"1": 918, "0": 1518}}, "01389": {"val": 2383, "part": 44.9, "v": {"0": 1471, "1": 912}}, "01393": {"val": 1827, "part": 46.7, "v": {"0": 1267, "1": 560}}, "01400": {"val": 1627, "part": 25.5, "v": {"1": 1033, "0": 594}}, "01401": {"val": 2874, "part": 42.7, "v": {"1": 1368, "0": 1506}}, "01402": {"val": 1810, "part": 41.6, "v": {"1": 887, "0": 923}}, "01405": {"val": 3020, "part": 45.9, "v": {"1": 1577, "0": 1443}}, "01406": {"val": 3155, "part": 41.4, "v": {"1": 1587, "0": 1568}}, "01410": {"val": 2731, "part": 41.1, "v": {"0": 1428, "1": 1303}}, "01411": {"val": 2774, "part": 41.2, "v": {"1": 1234, "0": 1540}}, "01423": {"val": 1588, "part": 22.9, "v": {"1": 666, "0": 922}}, "01424": {"val": 1909, "part": 19.7, "v": {"1": 1221, "0": 688}}, "01427": {"val": 3860, "part": 46.0, "v": {"1": 1535, "0": 2325}}, "01429": {"val": 2748, "part": 43.4, "v": {"1": 1109, "0": 1639}}, "01430": {"val": 2669, "part": 40.6, "v": {"1": 1168, "0": 1501}}, "01440": {"val": 3184, "part": 41.5, "v": {"0": 1922, "1": 1262}}, "01452": {"val": 2338, "part": 61.9, "v": {"1": 973, "0": 1365}}, "01454": {"val": 1641, "part": 42.6, "v": {"1": 871, "0": 770}}, "01455": {"val": 1780, "part": 42.8, "v": {"0": 907, "1": 873}}, "01459": {"val": 1873, "part": 49.7, "v": {"0": 1200, "1": 673}}, "01461": {"val": 2125, "part": 44.4, "v": {"0": 1409, "1": 716}}, "01462": {"val": 2038, "part": 40.8, "v": {"1": 628, "0": 1410}}, "01465": {"val": 627, "part": 51.5, "v": {"1": 261, "0": 366}}, "01466": {"val": 2992, "part": 45.0, "v": {"1": 1132, "0": 1860}}, "01473": {"val": 1648, "part": 57.5, "v": {"0": 1137, "1": 511}}, "01475": {"val": 3492, "part": 36.8, "v": {"0": 2132, "1": 1360}}, "01484": {"val": 2986, "part": 42.0, "v": {"0": 1561, "1": 1425}}, "01486": {"val": 2740, "part": 39.9, "v": {"0": 1547, "1": 1193}}, "01487": {"val": 3670, "part": 47.2, "v": {"1": 1702, "0": 1968}}, "01491": {"val": 4123, "part": 44.2, "v": {"0": 2578, "1": 1545}}, "01495": {"val": 5341, "part": 33.1, "v": {"0": 3285, "1": 2056}}, "01497": {"val": 746, "part": 46.1, "v": {"0": 442, "1": 304}}, "01500": {"val": 3266, "part": 37.9, "v": {"1": 1348, "0": 1918}}, "01501": {"val": 835, "part": 21.7, "v": {"1": 348, "0": 487}}, "01506": {"val": 389, "part": 50.9, "v": {"1": 160, "0": 229}}, "01508": {"val": 310, "part": 25.8, "v": {"1": 195, "0": 115}}, "01509": {"val": 778, "part": 52.0, "v": {"1": 207, "0": 571}}, "01511": {"val": 1122, "part": 28.6, "v": {"0": 748, "1": 374}}, "01512": {"val": 2458, "part": 28.7, "v": {"1": 892, "0": 1566}}, "01515": {"val": 2096, "part": 48.1, "v": {"1": 597, "0": 1499}}, "01517": {"val": 3387, "part": 38.6, "v": {"1": 1007, "0": 2380}}, "01520": {"val": 332, "part": 37.4, "v": {"0": 210, "1": 122}}, "01521": {"val": 332, "part": 37.2, "v": {"0": 231, "1": 101}}, "01524": {"val": 417, "part": 20.7, "v": {"0": 281, "1": 136}}, "01526": {"val": 811, "part": 29.6, "v": {"0": 553, "1": 258}}, "01527": {"val": 4095, "part": 46.5, "v": {"0": 3092, "1": 1003}}, "01530": {"val": 568, "part": 23.2, "v": {"0": 306, "1": 262}}, "01531": {"val": 223, "part": 41.3, "v": {"0": 104, "1": 119}}, "01532": {"val": 591, "part": 47.7, "v": {"0": 320, "1": 271}}, "01533": {"val": 1483, "part": 45.2, "v": {"0": 1131, "1": 352}}, "01534": {"val": 3836, "part": 39.4, "v": {"1": 1232, "0": 2604}}, "01536": {"val": 361, "part": 44.9, "v": {"0": 191, "1": 170}}, "01542": {"val": 608, "part": 57.7, "v": {"1": 150, "0": 458}}, "01548": {"val": 994, "part": 29.5, "v": {"0": 569, "1": 425}}, "01550": {"val": 1590, "part": 34.1, "v": {"0": 1043, "1": 547}}, "01551": {"val": 287, "part": 44.4, "v": {"0": 150, "1": 137}}, "01554": {"val": 2626, "part": 52.3, "v": {"1": 695, "0": 1931}}, "01559": {"val": 698, "part": 56.5, "v": {"0": 410, "1": 288}}, "01562": {"val": 2073, "part": 44.1, "v": {"0": 1209, "1": 864}}, "01567": {"val": 1093, "part": 46.5, "v": {"0": 721, "1": 372}}, "01569": {"val": 1100, "part": 37.5, "v": {"0": 604, "1": 496}}, "01573": {"val": 505, "part": 43.6, "v": {"1": 153, "0": 352}}, "01577": {"val": 2094, "part": 43.6, "v": {"1": 725, "0": 1369}}, "01580": {"val": 3797, "part": 46.5, "v": {"1": 1058, "0": 2739}}, "01581": {"val": 1721, "part": 42.1, "v": {"0": 962, "1": 759}}, "01582": {"val": 2157, "part": 42.4, "v": {"1": 680, "0": 1477}}, "01585": {"val": 3089, "part": 37.6, "v": {"1": 1068, "0": 2021}}, "01587": {"val": 639, "part": 15.3, "v": {"1": 276, "0": 363}}, "01589": {"val": 3881, "part": 46.5, "v": {"0": 2690, "1": 1191}}, "01590": {"val": 2202, "part": 28.4, "v": {"0": 1186, "1": 1016}}, "01592": {"val": 1942, "part": 43.9, "v": {"0": 991, "1": 951}}, "01594": {"val": 2362, "part": 44.5, "v": {"0": 1805, "1": 557}}, "01595": {"val": 2507, "part": 47.1, "v": {"1": 572, "0": 1935}}, "01596": {"val": 993, "part": 18.2, "v": {"0": 672, "1": 321}}, "01599": {"val": 3710, "part": 39.0, "v": {"1": 1236, "0": 2474}}, "01600": {"val": 1836, "part": 39.3, "v": {"1": 723, "0": 1113}}, "01602": {"val": 780, "part": 36.4, "v": {"1": 205, "0": 575}}, "01604": {"val": 2867, "part": 32.4, "v": {"0": 2057, "1": 810}}, "01611": {"val": 315, "part": 37.9, "v": {"1": 178, "0": 137}}, "01613": {"val": 317, "part": 45.3, "v": {"1": 171, "0": 146}}, "01616": {"val": 3070, "part": 35.6, "v": {"0": 1695, "1": 1375}}, "01619": {"val": 4008, "part": 46.1, "v": {"0": 2452, "1": 1556}}, "01621": {"val": 3961, "part": 45.2, "v": {"1": 1471, "0": 2490}}, "01623": {"val": 3836, "part": 44.0, "v": {"1": 1426, "0": 2410}}, "01632": {"val": 3546, "part": 40.7, "v": {"1": 1349, "0": 2197}}, "01650": {"val": 3431, "part": 40.7, "v": {"0": 1728, "1": 1703}}, "01652": {"val": 2729, "part": 32.1, "v": {"0": 1340, "1": 1389}}, "01659": {"val": 420, "part": 66.0, "v": {"0": 290, "1": 130}}, "01660": {"val": 1761, "part": 45.0, "v": {"0": 1316, "1": 445}}, "01661": {"val": 1815, "part": 47.4, "v": {"1": 453, "0": 1362}}, "01664": {"val": 423, "part": 40.0, "v": {"0": 260, "1": 163}}, "01665": {"val": 857, "part": 55.5, "v": {"1": 303, "0": 554}}, "01668": {"val": 2392, "part": 52.2, "v": {"0": 1142, "1": 1250}}, "01669": {"val": 3317, "part": 38.3, "v": {"0": 1495, "1": 1822}}, "01676": {"val": 238, "part": 45.1, "v": {"1": 103, "0": 135}}, "01677": {"val": 1643, "part": 39.6, "v": {"1": 336, "0": 1307}}, "01680": {"val": 505, "part": 51.9, "v": {"1": 170, "0": 335}}, "01681": {"val": 2310, "part": 49.4, "v": {"0": 1597, "1": 713}}, "01682": {"val": 2177, "part": 43.7, "v": {"1": 567, "0": 1610}}, "01686": {"val": 4011, "part": 50.5, "v": {"1": 1042, "0": 2969}}, "01687": {"val": 1294, "part": 48.8, "v": {"0": 957, "1": 337}}, "01689": {"val": 2115, "part": 38.2, "v": {"0": 1318, "1": 797}}, "01691": {"val": 437, "part": 14.7, "v": {"0": 293, "1": 144}}, "01692": {"val": 3276, "part": 39.1, "v": {"0": 2149, "1": 1127}}, "01693": {"val": 3388, "part": 40.3, "v": {"1": 1103, "0": 2285}}, "01698": {"val": 276, "part": 49.6, "v": {"1": 115, "0": 161}}, "01699": {"val": 201, "part": 65.8, "v": {"1": 56, "0": 145}}, "01701": {"val": 1349, "part": 33.3, "v": {"1": 510, "0": 839}}, "01704": {"val": 327, "part": 38.2, "v": {"1": 76, "0": 251}}, "01706": {"val": 398, "part": 50.2, "v": {"1": 75, "0": 323}}, "01707": {"val": 1229, "part": 34.5, "v": {"1": 247, "0": 982}}, "01708": {"val": 982, "part": 27.4, "v": {"1": 213, "0": 769}}, "01709": {"val": 835, "part": 54.3, "v": {"0": 532, "1": 303}}, "01711": {"val": 1840, "part": 46.4, "v": {"1": 485, "0": 1355}}, "01712": {"val": 1704, "part": 44.8, "v": {"1": 507, "0": 1197}}, "01713": {"val": 597, "part": 57.9, "v": {"1": 160, "0": 437}}, "01728": {"val": 373, "part": 44.2, "v": {"0": 269, "1": 104}}, "01729": {"val": 1421, "part": 26.9, "v": {"1": 354, "0": 1067}}, "01734": {"val": 229, "part": 57.6, "v": {"0": 167, "1": 62}}, "01737": {"val": 193, "part": 47.7, "v": {"0": 133, "1": 60}}, "01741": {"val": 4104, "part": 39.9, "v": {"0": 2717, "1": 1387}}, "01743": {"val": 2123, "part": 31.6, "v": {"1": 707, "0": 1416}}, "01745": {"val": 1864, "part": 28.5, "v": {"1": 656, "0": 1208}}, "01748": {"val": 144, "part": 49.8, "v": {"0": 113, "1": 31}}, "01749": {"val": 214, "part": 62.7, "v": {"1": 83, "0": 131}}, "01752": {"val": 230, "part": 36.1, "v": {"0": 118, "1": 112}}, "01756": {"val": 198, "part": 50.2, "v": {"1": 121, "0": 77}}, "01762": {"val": 461, "part": 26.9, "v": {"1": 281, "0": 180}}, "01763": {"val": 227, "part": 23.1, "v": {"0": 141, "1": 86}}, "01765": {"val": 1577, "part": 36.4, "v": {"0": 1189, "1": 388}}, "01767": {"val": 1620, "part": 38.4, "v": {"0": 1230, "1": 390}}, "01768": {"val": 1410, "part": 27.1, "v": {"1": 455, "0": 955}}, "01769": {"val": 2016, "part": 30.3, "v": {"0": 1575, "1": 441}}, "01770": {"val": 40, "part": 28.7, "v": {"1": 8, "0": 32}}, "01772": {"val": 1696, "part": 27.2, "v": {"0": 1283, "1": 413}}, "01773": {"val": 266, "part": 20.9, "v": {"0": 205, "1": 61}}, "01775": {"val": 1170, "part": 34.6, "v": {"0": 827, "1": 343}}, "01776": {"val": 888, "part": 23.9, "v": {"0": 553, "1": 335}}, "01777": {"val": 978, "part": 30.8, "v": {"1": 321, "0": 657}}, "01779": {"val": 2344, "part": 45.0, "v": {"1": 831, "0": 1513}}, "01781": {"val": 1417, "part": 34.8, "v": {"1": 385, "0": 1032}}, "01782": {"val": 1498, "part": 27.6, "v": {"1": 500, "0": 998}}, "01783": {"val": 1642, "part": 33.0, "v": {"0": 1193, "1": 449}}, "01784": {"val": 1328, "part": 26.8, "v": {"0": 804, "1": 524}}, "01786": {"val": 1487, "part": 27.7, "v": {"0": 877, "1": 610}}, "01788": {"val": 1566, "part": 31.8, "v": {"1": 435, "0": 1131}}, "01789": {"val": 3179, "part": 37.7, "v": {"0": 2385, "1": 794}}, "01790": {"val": 2054, "part": 38.5, "v": {"0": 1261, "1": 793}}, "01791": {"val": 1473, "part": 35.7, "v": {"0": 970, "1": 503}}, "01798": {"val": 1630, "part": 31.0, "v": {"0": 1196, "1": 434}}, "01799": {"val": 1689, "part": 34.0, "v": {"0": 1257, "1": 432}}, "01800": {"val": 3198, "part": 38.8, "v": {"1": 863, "0": 2335}}, "01802": {"val": 1727, "part": 39.9, "v": {"0": 1260, "1": 467}}, "01803": {"val": 1085, "part": 33.0, "v": {"0": 812, "1": 273}}, "01808": {"val": 173, "part": 16.6, "v": {"1": 65, "0": 108}}, "01810": {"val": 377, "part": 25.4, "v": {"1": 147, "0": 230}}, "01811": {"val": 2127, "part": 34.2, "v": {"0": 1545, "1": 582}}, "01821": {"val": 9663, "part": 51.9, "v": {"0": 4894, "1": 4769}}, "01827": {"val": 3502, "part": 34.9, "v": {"0": 2207, "1": 1295}}, "01829": {"val": 3146, "part": 44.1, "v": {"0": 2073, "1": 1073}}, "01831": {"val": 3570, "part": 42.0, "v": {"1": 1313, "0": 2257}}, "01832": {"val": 3279, "part": 43.3, "v": {"0": 2087, "1": 1192}}, "01839": {"val": 2724, "part": 42.4, "v": {"1": 747, "0": 1977}}, "01840": {"val": 2957, "part": 43.6, "v": {"1": 809, "0": 2148}}, "01841": {"val": 2861, "part": 43.0, "v": {"0": 2067, "1": 794}}, "01843": {"val": 4850, "part": 42.4, "v": {"1": 1486, "0": 3364}}, "01845": {"val": 3757, "part": 42.9, "v": {"0": 2786, "1": 971}}, "01848": {"val": 2610, "part": 43.3, "v": {"1": 724, "0": 1886}}, "01849": {"val": 1991, "part": 39.0, "v": {"1": 577, "0": 1414}}, "01853": {"val": 3932, "part": 46.3, "v": {"1": 1025, "0": 2907}}, "01855": {"val": 4124, "part": 61.8, "v": {"0": 822, "1": 3302}}, "01860": {"val": 4359, "part": 49.3, "v": {"1": 1870, "0": 2489}}, "01865": {"val": 3305, "part": 37.4, "v": {"1": 1515, "0": 1790}}, "01866": {"val": 3493, "part": 39.6, "v": {"0": 1917, "1": 1576}}, "01876": {"val": 3034, "part": 40.3, "v": {"0": 1987, "1": 1047}}, "01879": {"val": 3812, "part": 35.4, "v": {"0": 2516, "1": 1296}}, "01887": {"val": 3378, "part": 40.9, "v": {"1": 1127, "0": 2251}}, "01889": {"val": 4543, "part": 54.1, "v": {"1": 1429, "0": 3114}}, "01890": {"val": 3751, "part": 38.0, "v": {"1": 1270, "0": 2481}}, "01891": {"val": 5244, "part": 57.2, "v": {"1": 1898, "0": 3346}}, "01893": {"val": 821, "part": 21.9, "v": {"0": 453, "1": 368}}, "01898": {"val": 8018, "part": 50.4, "v": {"0": 4846, "1": 3172}}, "01899": {"val": 4039, "part": 45.1, "v": {"1": 1943, "0": 2096}}, "01901": {"val": 4215, "part": 42.5, "v": {"0": 3032, "1": 1183}}, "01906": {"val": 3810, "part": 45.3, "v": {"0": 2615, "1": 1195}}, "01908": {"val": 3586, "part": 42.5, "v": {"1": 1040, "0": 2546}}, "01910": {"val": 6487, "part": 43.0, "v": {"0": 4515, "1": 1972}}, "01911": {"val": 3606, "part": 43.1, "v": {"1": 1070, "0": 2536}}, "01913": {"val": 1047, "part": 12.9, "v": {"1": 452, "0": 595}}, "01916": {"val": 5340, "part": 44.9, "v": {"1": 1952, "0": 3388}}, "01917": {"val": 6362, "part": 52.0, "v": {"1": 2340, "0": 4022}}, "01919": {"val": 6267, "part": 36.1, "v": {"1": 2365, "0": 3902}}, "01920": {"val": 6201, "part": 37.5, "v": {"1": 2561, "0": 3640}}, "01923": {"val": 7505, "part": 42.2, "v": {"0": 4611, "1": 2894}}, "01928": {"val": 5054, "part": 35.6, "v": {"1": 2092, "0": 2962}}, "01934": {"val": 10405, "part": 47.0, "v": {"0": 7170, "1": 3235}}, "01937": {"val": 3970, "part": 45.6, "v": {"0": 2895, "1": 1075}}, "01941": {"val": 2275, "part": 37.8, "v": {"1": 1314, "0": 961}}, "01943": {"val": 3648, "part": 51.6, "v": {"0": 1677, "1": 1971}}, "01945": {"val": 8726, "part": 43.4, "v": {"0": 5460, "1": 3266}}, "01949": {"val": 6963, "part": 35.1, "v": {"1": 2850, "0": 4113}}, "01951": {"val": 4803, "part": 48.8, "v": {"0": 3057, "1": 1746}}, "01953": {"val": 6041, "part": 44.9, "v": {"1": 2297, "0": 3744}}, "01957": {"val": 3319, "part": 42.9, "v": {"1": 1380, "0": 1939}}, "01959": {"val": 3497, "part": 41.8, "v": {"0": 1998, "1": 1499}}, "01961": {"val": 3410, "part": 41.7, "v": {"1": 1469, "0": 1941}}, "01963": {"val": 2012, "part": 55.3, "v": {"1": 891, "0": 1121}}, "01964": {"val": 3186, "part": 35.1, "v": {"1": 1390, "0": 1796}}, "01967": {"val": 10127, "part": 45.7, "v": {"0": 6387, "1": 3740}}, "01970": {"val": 8296, "part": 50.4, "v": {"1": 2994, "0": 5302}}, "01972": {"val": 2764, "part": 41.8, "v": {"0": 1797, "1": 967}}, "01980": {"val": 3117, "part": 46.5, "v": {"1": 1269, "0": 1848}}, "01988": {"val": 8724, "part": 45.6, "v": {"1": 3299, "0": 5425}}, "01990": {"val": 5129, "part": 47.4, "v": {"1": 1983, "0": 3146}}, "01992": {"val": 8966, "part": 49.3, "v": {"1": 3413, "0": 5553}}, "01998": {"val": 6660, "part": 47.0, "v": {"1": 2807, "0": 3853}}, "02001": {"val": 1882, "part": 39.9, "v": {"0": 1291, "1": 591}}, "02002": {"val": 4676, "part": 52.5, "v": {"1": 1364, "0": 3312}}, "02006": {"val": 2751, "part": 40.8, "v": {"0": 1972, "1": 779}}, "02007": {"val": 3188, "part": 43.2, "v": {"1": 929, "0": 2259}}, "02010": {"val": 2791, "part": 42.2, "v": {"0": 2003, "1": 788}}, "02011": {"val": 2593, "part": 38.7, "v": {"0": 1858, "1": 735}}, "02013": {"val": 2721, "part": 40.4, "v": {"0": 1962, "1": 759}}, "02014": {"val": 2635, "part": 39.2, "v": {"1": 722, "0": 1913}}, "02017": {"val": 4135, "part": 48.6, "v": {"1": 926, "0": 3209}}, "02020": {"val": 2515, "part": 11.6, "v": {"1": 966, "0": 1549}}, "02023": {"val": 3393, "part": 41.9, "v": {"0": 2670, "1": 723}}, "02028": {"val": 4212, "part": 48.4, "v": {"1": 947, "0": 3265}}, "02035": {"val": 6951, "part": 46.8, "v": {"0": 3409, "1": 3542}}, "02038": {"val": 3506, "part": 60.5, "v": {"0": 1510, "1": 1996}}, "02041": {"val": 9334, "part": 67.3, "v": {"0": 4550, "1": 4784}}, "02045": {"val": 6665, "part": 46.0, "v": {"1": 3459, "0": 3206}}, "02046": {"val": 2996, "part": 53.1, "v": {"0": 1421, "1": 1575}}, "02049": {"val": 7514, "part": 54.1, "v": {"0": 4739, "1": 2775}}, "02051": {"val": 6829, "part": 49.0, "v": {"1": 2665, "0": 4164}}, "02052": {"val": 2737, "part": 20.5, "v": {"1": 1275, "0": 1462}}, "02057": {"val": 4498, "part": 51.4, "v": {"1": 3299, "0": 1199}}, "02066": {"val": 5198, "part": 48.8, "v": {"0": 1550, "1": 3648}}, "02075": {"val": 12971, "part": 56.4, "v": {"1": 10466, "0": 2505}}, "02076": {"val": 15154, "part": 60.2, "v": {"0": 3420, "1": 11734}}, "02078": {"val": 10781, "part": 46.9, "v": {"1": 8509, "0": 2272}}, "02089": {"val": 4865, "part": 47.5, "v": {"1": 4260, "0": 605}}, "02093": {"val": 3691, "part": 63.9, "v": {"0": 2817, "1": 874}}, "02095": {"val": 3431, "part": 50.1, "v": {"1": 740, "0": 2691}}, "02098": {"val": 12599, "part": 39.1, "v": {"0": 9455, "1": 3144}}, "02107": {"val": 8277, "part": 45.8, "v": {"1": 2532, "0": 5745}}, "02110": {"val": 3617, "part": 42.5, "v": {"1": 1084, "0": 2533}}, "02111": {"val": 4569, "part": 43.0, "v": {"1": 1311, "0": 3258}}, "02112": {"val": 3783, "part": 46.6, "v": {"0": 2619, "1": 1164}}, "02114": {"val": 3610, "part": 42.2, "v": {"0": 2594, "1": 1016}}, "02116": {"val": 3782, "part": 44.7, "v": {"1": 1137, "0": 2645}}, "02123": {"val": 2563, "part": 46.7, "v": {"0": 1559, "1": 1004}}, "02124": {"val": 6006, "part": 55.1, "v": {"0": 3860, "1": 2146}}, "02126": {"val": 6250, "part": 30.6, "v": {"0": 3521, "1": 2729}}, "02133": {"val": 3736, "part": 45.9, "v": {"0": 2250, "1": 1486}}, "02144": {"val": 7911, "part": 51.9, "v": {"0": 4765, "1": 3146}}, "02146": {"val": 6019, "part": 39.2, "v": {"0": 3351, "1": 2668}}, "02147": {"val": 4810, "part": 24.3, "v": {"0": 2466, "1": 2344}}, "02151": {"val": 4177, "part": 49.2, "v": {"0": 2618, "1": 1559}}, "02154": {"val": 4136, "part": 41.1, "v": {"1": 1663, "0": 2473}}, "02160": {"val": 6851, "part": 49.4, "v": {"1": 2360, "0": 4491}}, "02162": {"val": 4602, "part": 51.4, "v": {"0": 2844, "1": 1758}}, "02165": {"val": 8335, "part": 43.2, "v": {"1": 3013, "0": 5322}}, "02166": {"val": 6887, "part": 35.4, "v": {"0": 4052, "1": 2835}}, "02167": {"val": 4119, "part": 43.9, "v": {"0": 2569, "1": 1550}}, "02171": {"val": 3738, "part": 46.3, "v": {"0": 2312, "1": 1426}}, "02172": {"val": 5622, "part": 41.9, "v": {"0": 3360, "1": 2262}}, "02174": {"val": 5259, "part": 48.5, "v": {"0": 3402, "1": 1857}}, "02176": {"val": 3473, "part": 44.6, "v": {"0": 2137, "1": 1336}}, "02178": {"val": 5805, "part": 44.2, "v": {"0": 3892, "1": 1913}}, "02184": {"val": 3081, "part": 45.3, "v": {"0": 2153, "1": 928}}, "02185": {"val": 12204, "part": 43.9, "v": {"1": 3766, "0": 8438}}, "02186": {"val": 4297, "part": 17.1, "v": {"0": 2338, "1": 1959}}, "02187": {"val": 4569, "part": 48.8, "v": {"1": 1415, "0": 3154}}, "02195": {"val": 8869, "part": 51.8, "v": {"0": 5976, "1": 2893}}, "02203": {"val": 3397, "part": 40.8, "v": {"1": 1698, "0": 1699}}, "02208": {"val": 4334, "part": 45.3, "v": {"1": 2343, "0": 1991}}, "02209": {"val": 4331, "part": 60.3, "v": {"0": 2408, "1": 1923}}, "02217": {"val": 2915, "part": 44.2, "v": {"0": 1496, "1": 1419}}, "02220": {"val": 11447, "part": 51.8, "v": {"1": 5084, "0": 6363}}, "02221": {"val": 5846, "part": 43.7, "v": {"1": 2767, "0": 3079}}, "02236": {"val": 6811, "part": 46.0, "v": {"1": 2658, "0": 4153}}, "02239": {"val": 7362, "part": 36.3, "v": {"1": 2957, "0": 4405}}, "02241": {"val": 3523, "part": 42.0, "v": {"1": 1038, "0": 2485}}, "02243": {"val": 4023, "part": 41.3, "v": {"0": 2761, "1": 1262}}, "02246": {"val": 5146, "part": 53.3, "v": {"1": 1461, "0": 3685}}, "02248": {"val": 4579, "part": 34.9, "v": {"0": 3424, "1": 1155}}, "02250": {"val": 6381, "part": 63.0, "v": {"1": 1425, "0": 4956}}, "02254": {"val": 2402, "part": 36.7, "v": {"1": 602, "0": 1800}}, "02256": {"val": 3610, "part": 60.8, "v": {"0": 2764, "1": 846}}, "02258": {"val": 3645, "part": 43.4, "v": {"0": 2378, "1": 1267}}, "02260": {"val": 3779, "part": 52.4, "v": {"1": 1452, "0": 2327}}, "02262": {"val": 3854, "part": 39.1, "v": {"1": 1346, "0": 2508}}, "02266": {"val": 4340, "part": 44.0, "v": {"1": 1492, "0": 2848}}, "02267": {"val": 3310, "part": 39.2, "v": {"0": 2169, "1": 1141}}, "02272": {"val": 4801, "part": 41.4, "v": {"0": 3288, "1": 1513}}, "02273": {"val": 4678, "part": 56.9, "v": {"1": 1930, "0": 2748}}, "02275": {"val": 4447, "part": 40.3, "v": {"1": 1337, "0": 3110}}, "02279": {"val": 5705, "part": 38.3, "v": {"0": 3630, "1": 2075}}, "02285": {"val": 4524, "part": 45.1, "v": {"1": 1324, "0": 3200}}, "02286": {"val": 8273, "part": 45.3, "v": {"0": 5442, "1": 2831}}, "02289": {"val": 8994, "part": 47.7, "v": {"1": 3302, "0": 5692}}, "02290": {"val": 9300, "part": 51.7, "v": {"0": 5919, "1": 3381}}, "02297": {"val": 15577, "part": 46.7, "v": {"0": 6341, "1": 9236}}, "02305": {"val": 8011, "part": 46.7, "v": {"0": 3443, "1": 4568}}, "02306": {"val": 5501, "part": 41.0, "v": {"0": 1959, "1": 3542}}, "02308": {"val": 2749, "part": 39.4, "v": {"0": 1071, "1": 1678}}, "02309": {"val": 6382, "part": 54.4, "v": {"1": 3559, "0": 2823}}, "02310": {"val": 2557, "part": 36.5, "v": {"0": 945, "1": 1612}}, "02311": {"val": 2948, "part": 29.3, "v": {"1": 1952, "0": 996}}, "02312": {"val": 1913, "part": 23.6, "v": {"0": 727, "1": 1186}}, "02321": {"val": 6023, "part": 44.8, "v": {"1": 1761, "0": 4262}}, "02323": {"val": 3979, "part": 42.3, "v": {"0": 2754, "1": 1225}}, "02324": {"val": 2365, "part": 16.1, "v": {"1": 946, "0": 1419}}, "02326": {"val": 4025, "part": 46.3, "v": {"0": 2841, "1": 1184}}, "02340": {"val": 4940, "part": 45.2, "v": {"1": 1506, "0": 3434}}, "02341": {"val": 3900, "part": 15.6, "v": {"1": 1753, "0": 2147}}, "02342": {"val": 1541, "part": 14.1, "v": {"0": 805, "1": 736}}, "02344": {"val": 1047, "part": 10.7, "v": {"1": 521, "0": 526}}, "02347": {"val": 2631, "part": 43.4, "v": {"0": 1783, "1": 848}}, "02348": {"val": 5890, "part": 43.4, "v": {"1": 1896, "0": 3994}}, "02352": {"val": 7288, "part": 54.0, "v": {"1": 2549, "0": 4739}}, "02355": {"val": 963, "part": 12.7, "v": {"0": 556, "1": 407}}, "02356": {"val": 4275, "part": 42.9, "v": {"0": 2790, "1": 1485}}, "02357": {"val": 6214, "part": 46.1, "v": {"0": 4142, "1": 2072}}, "02358": {"val": 3826, "part": 36.2, "v": {"0": 2586, "1": 1240}}, "02362": {"val": 6543, "part": 45.5, "v": {"1": 2366, "0": 4177}}, "02368": {"val": 5545, "part": 44.1, "v": {"0": 3743, "1": 1802}}, "02369": {"val": 5382, "part": 39.8, "v": {"1": 1705, "0": 3677}}, "02374": {"val": 2693, "part": 13.8, "v": {"1": 1285, "0": 1408}}, "02381": {"val": 1540, "part": 12.5, "v": {"0": 759, "1": 781}}, "02382": {"val": 1942, "part": 27.0, "v": {"0": 1190, "1": 752}}, "02385": {"val": 3978, "part": 53.2, "v": {"0": 2670, "1": 1308}}, "02386": {"val": 4490, "part": 51.5, "v": {"0": 2920, "1": 1570}}, "02391": {"val": 2595, "part": 16.0, "v": {"0": 1412, "1": 1183}}, "02394": {"val": 4656, "part": 51.1, "v": {"1": 1701, "0": 2955}}, "02395": {"val": 5464, "part": 50.5, "v": {"0": 3691, "1": 1773}}, "02396": {"val": 2487, "part": 34.3, "v": {"0": 1593, "1": 894}}, "02398": {"val": 4770, "part": 46.7, "v": {"1": 1694, "0": 3076}}, "02399": {"val": 5606, "part": 54.7, "v": {"0": 3960, "1": 1646}}, "02404": {"val": 4021, "part": 35.9, "v": {"1": 1539, "0": 2482}}, "02405": {"val": 5074, "part": 42.9, "v": {"1": 1764, "0": 3310}}, "02408": {"val": 5803, "part": 41.2, "v": {"1": 2076, "0": 3727}}, "02412": {"val": 5254, "part": 45.3, "v": {"1": 1901, "0": 3353}}, "02420": {"val": 3664, "part": 51.0, "v": {"1": 1182, "0": 2482}}, "02421": {"val": 4415, "part": 44.7, "v": {"1": 1394, "0": 3021}}, "02423": {"val": 359, "part": 12.0, "v": {"0": 244, "1": 115}}, "02429": {"val": 5955, "part": 41.0, "v": {"1": 2321, "0": 3634}}, "02441": {"val": 2813, "part": 38.1, "v": {"0": 1997, "1": 816}}, "02444": {"val": 4735, "part": 42.0, "v": {"0": 3321, "1": 1414}}, "02450": {"val": 5425, "part": 41.3, "v": {"0": 3688, "1": 1737}}, "02458": {"val": 2788, "part": 51.8, "v": {"1": 903, "0": 1885}}, "02459": {"val": 1941, "part": 12.4, "v": {"1": 945, "0": 996}}, "02460": {"val": 3264, "part": 20.0, "v": {"1": 1569, "0": 1695}}, "02462": {"val": 2502, "part": 35.3, "v": {"1": 944, "0": 1558}}, "02468": {"val": 2878, "part": 40.3, "v": {"0": 1849, "1": 1029}}, "02469": {"val": 3512, "part": 52.1, "v": {"0": 2214, "1": 1298}}, "02471": {"val": 4056, "part": 41.3, "v": {"0": 2671, "1": 1385}}, "02473": {"val": 1011, "part": 28.7, "v": {"1": 419, "0": 592}}, "02474": {"val": 7233, "part": 46.4, "v": {"0": 4743, "1": 2490}}, "02480": {"val": 2821, "part": 37.7, "v": {"0": 1744, "1": 1077}}, "02487": {"val": 2994, "part": 42.3, "v": {"1": 939, "0": 2055}}, "02488": {"val": 2959, "part": 39.6, "v": {"1": 904, "0": 2055}}, "02489": {"val": 2924, "part": 41.5, "v": {"0": 2044, "1": 880}}, "02491": {"val": 2196, "part": 44.4, "v": {"0": 1573, "1": 623}}, "02493": {"val": 2558, "part": 39.0, "v": {"0": 1805, "1": 753}}, "02494": {"val": 2774, "part": 53.6, "v": {"0": 1951, "1": 823}}, "02497": {"val": 2678, "part": 37.9, "v": {"1": 799, "0": 1879}}, "02498": {"val": 3148, "part": 41.8, "v": {"1": 940, "0": 2208}}, "02501": {"val": 3359, "part": 48.2, "v": {"1": 1194, "0": 2165}}, "02502": {"val": 3213, "part": 46.1, "v": {"0": 2094, "1": 1119}}, "02505": {"val": 4363, "part": 41.0, "v": {"0": 2580, "1": 1783}}, "02511": {"val": 4766, "part": 48.9, "v": {"1": 1858, "0": 2908}}, "02513": {"val": 5061, "part": 48.7, "v": {"0": 3109, "1": 1952}}, "02514": {"val": 4242, "part": 40.2, "v": {"0": 2557, "1": 1685}}, "02515": {"val": 3767, "part": 35.6, "v": {"1": 1605, "0": 2162}}, "02516": {"val": 6880, "part": 47.4, "v": {"0": 4188, "1": 2692}}, "02519": {"val": 3103, "part": 46.9, "v": {"0": 2333, "1": 770}}, "02520": {"val": 2605, "part": 46.2, "v": {"0": 1938, "1": 667}}, "02524": {"val": 2681, "part": 46.2, "v": {"0": 1953, "1": 728}}, "02525": {"val": 2274, "part": 39.6, "v": {"0": 1606, "1": 668}}, "02526": {"val": 3651, "part": 43.0, "v": {"0": 2709, "1": 942}}, "02527": {"val": 2718, "part": 42.8, "v": {"0": 1872, "1": 846}}, "02529": {"val": 1562, "part": 31.1, "v": {"1": 469, "0": 1093}}, "02531": {"val": 1809, "part": 41.2, "v": {"1": 521, "0": 1288}}, "02538": {"val": 3171, "part": 29.2, "v": {"0": 1867, "1": 1304}}, "02539": {"val": 2847, "part": 44.1, "v": {"1": 1045, "0": 1802}}, "02540": {"val": 1565, "part": 15.6, "v": {"0": 880, "1": 685}}, "02541": {"val": 4539, "part": 24.6, "v": {"1": 1639, "0": 2900}}, "02544": {"val": 9516, "part": 40.0, "v": {"0": 5767, "1": 3749}}, "02545": {"val": 1569, "part": 11.6, "v": {"1": 852, "0": 717}}, "02549": {"val": 5158, "part": 35.3, "v": {"1": 2187, "0": 2971}}, "02553": {"val": 4162, "part": 56.2, "v": {"0": 2441, "1": 1721}}, "02558": {"val": 3859, "part": 48.9, "v": {"1": 1544, "0": 2315}}, "02559": {"val": 2873, "part": 55.6, "v": {"1": 1150, "0": 1723}}, "02561": {"val": 2642, "part": 34.5, "v": {"1": 1097, "0": 1545}}, "02562": {"val": 3530, "part": 36.4, "v": {"1": 1581, "0": 1949}}, "02566": {"val": 3575, "part": 47.2, "v": {"1": 1472, "0": 2103}}, "02568": {"val": 2172, "part": 52.5, "v": {"0": 1301, "1": 871}}, "02569": {"val": 2223, "part": 43.8, "v": {"1": 936, "0": 1287}}, "02570": {"val": 3593, "part": 34.6, "v": {"1": 1643, "0": 1950}}, "02571": {"val": 3362, "part": 39.1, "v": {"1": 1354, "0": 2008}}, "02573": {"val": 3058, "part": 36.3, "v": {"1": 1392, "0": 1666}}, "02574": {"val": 3053, "part": 35.9, "v": {"0": 1618, "1": 1435}}, "02578": {"val": 7039, "part": 56.2, "v": {"0": 4145, "1": 2894}}, "02579": {"val": 2573, "part": 48.0, "v": {"0": 1343, "1": 1230}}, "02581": {"val": 8002, "part": 51.1, "v": {"1": 3218, "0": 4784}}, "02585": {"val": 8592, "part": 54.3, "v": {"1": 6709, "0": 1883}}, "02587": {"val": 10593, "part": 61.0, "v": {"1": 8771, "0": 1822}}, "02592": {"val": 10229, "part": 75.3, "v": {"1": 8541, "0": 1688}}, "02594": {"val": 9155, "part": 56.2, "v": {"1": 7241, "0": 1914}}, "02601": {"val": 932, "part": 49.8, "v": {"1": 354, "0": 578}}, "02603": {"val": 1064, "part": 44.7, "v": {"1": 365, "0": 699}}, "02604": {"val": 1275, "part": 40.8, "v": {"0": 761, "1": 514}}, "02606": {"val": 2172, "part": 40.4, "v": {"1": 822, "0": 1350}}, "02608": {"val": 1397, "part": 47.4, "v": {"1": 535, "0": 862}}, "02609": {"val": 1216, "part": 40.7, "v": {"1": 427, "0": 789}}, "02610": {"val": 1642, "part": 44.8, "v": {"1": 570, "0": 1072}}, "02614": {"val": 2934, "part": 45.0, "v": {"0": 1726, "1": 1208}}, "02615": {"val": 1069, "part": 51.2, "v": {"0": 445, "1": 624}}, "02620": {"val": 1521, "part": 53.2, "v": {"0": 1010, "1": 511}}, "02624": {"val": 1394, "part": 40.1, "v": {"1": 462, "0": 932}}, "02628": {"val": 1495, "part": 45.2, "v": {"1": 522, "0": 973}}, "02629": {"val": 1531, "part": 46.6, "v": {"1": 491, "0": 1040}}, "02631": {"val": 2092, "part": 46.5, "v": {"0": 1491, "1": 601}}, "02632": {"val": 2505, "part": 41.9, "v": {"0": 1806, "1": 699}}, "02633": {"val": 2191, "part": 44.4, "v": {"1": 574, "0": 1617}}, "02634": {"val": 570, "part": 46.6, "v": {"0": 370, "1": 200}}, "02637": {"val": 1481, "part": 41.6, "v": {"1": 432, "0": 1049}}, "02638": {"val": 2096, "part": 46.5, "v": {"1": 695, "0": 1401}}, "02640": {"val": 521, "part": 57.1, "v": {"1": 152, "0": 369}}, "02641": {"val": 601, "part": 48.2, "v": {"0": 364, "1": 237}}, "02642": {"val": 514, "part": 46.0, "v": {"0": 371, "1": 143}}, "02643": {"val": 730, "part": 44.1, "v": {"0": 390, "1": 340}}, "02645": {"val": 901, "part": 42.2, "v": {"1": 455, "0": 446}}, "02647": {"val": 1066, "part": 47.1, "v": {"1": 211, "0": 855}}, "02648": {"val": 800, "part": 16.8, "v": {"1": 359, "0": 441}}, "02651": {"val": 2263, "part": 40.3, "v": {"1": 762, "0": 1501}}, "02652": {"val": 2827, "part": 45.2, "v": {"0": 1783, "1": 1044}}, "02655": {"val": 869, "part": 55.1, "v": {"1": 260, "0": 609}}, "02659": {"val": 2526, "part": 44.9, "v": {"1": 999, "0": 1527}}, "02664": {"val": 1097, "part": 43.9, "v": {"0": 681, "1": 416}}, "02668": {"val": 2829, "part": 38.3, "v": {"0": 1938, "1": 891}}, "02670": {"val": 398, "part": 12.9, "v": {"1": 187, "0": 211}}, "02671": {"val": 2286, "part": 45.6, "v": {"0": 1652, "1": 634}}, "02672": {"val": 2662, "part": 38.6, "v": {"0": 1684, "1": 978}}, "02674": {"val": 1206, "part": 36.7, "v": {"1": 510, "0": 696}}, "02675": {"val": 2822, "part": 34.4, "v": {"1": 1117, "0": 1705}}, "02676": {"val": 1642, "part": 42.4, "v": {"1": 656, "0": 986}}, "02680": {"val": 3904, "part": 46.5, "v": {"1": 1173, "0": 2731}}, "02687": {"val": 3943, "part": 48.2, "v": {"1": 1496, "0": 2447}}, "02695": {"val": 2495, "part": 32.9, "v": {"0": 1459, "1": 1036}}, "02698": {"val": 1635, "part": 34.4, "v": {"1": 568, "0": 1067}}, "02699": {"val": 2228, "part": 33.7, "v": {"0": 1436, "1": 792}}, "02710": {"val": 2498, "part": 38.3, "v": {"1": 881, "0": 1617}}, "02712": {"val": 1888, "part": 29.8, "v": {"0": 1082, "1": 806}}, "02716": {"val": 1347, "part": 31.6, "v": {"0": 799, "1": 548}}, "02719": {"val": 1951, "part": 31.2, "v": {"0": 1243, "1": 708}}, "02723": {"val": 1487, "part": 26.2, "v": {"0": 853, "1": 634}}, "02727": {"val": 2346, "part": 36.5, "v": {"0": 1256, "1": 1090}}, "02733": {"val": 1001, "part": 27.7, "v": {"0": 585, "1": 416}}, "02734": {"val": 1437, "part": 38.3, "v": {"0": 891, "1": 546}}, "02742": {"val": 1940, "part": 31.4, "v": {"0": 1243, "1": 697}}, "02743": {"val": 123, "part": 14.7, "v": {"0": 76, "1": 47}}, "02744": {"val": 488, "part": 17.5, "v": {"1": 218, "0": 270}}, "02748": {"val": 715, "part": 13.5, "v": {"0": 392, "1": 323}}, "02752": {"val": 3787, "part": 47.9, "v": {"1": 1308, "0": 2479}}, "02763": {"val": 4031, "part": 46.1, "v": {"1": 1502, "0": 2529}}, "02773": {"val": 4587, "part": 53.3, "v": {"1": 2042, "0": 2545}}, "02774": {"val": 1813, "part": 46.1, "v": {"1": 952, "0": 861}}, "02785": {"val": 3973, "part": 43.9, "v": {"0": 2578, "1": 1395}}, "02786": {"val": 3534, "part": 42.2, "v": {"0": 2413, "1": 1121}}, "02796": {"val": 3040, "part": 52.5, "v": {"0": 2001, "1": 1039}}, "02797": {"val": 4475, "part": 55.2, "v": {"1": 1476, "0": 2999}}, "02802": {"val": 1358, "part": 54.6, "v": {"0": 855, "1": 503}}, "02804": {"val": 3395, "part": 52.8, "v": {"0": 2417, "1": 978}}, "02809": {"val": 204, "part": 78.4, "v": {"1": 40, "0": 164}}, "02814": {"val": 3093, "part": 51.3, "v": {"1": 1085, "0": 2008}}, "02819": {"val": 2976, "part": 52.0, "v": {"1": 1147, "0": 1829}}, "02822": {"val": 2135, "part": 51.6, "v": {"1": 798, "0": 1337}}, "02826": {"val": 2114, "part": 48.8, "v": {"1": 1015, "0": 1099}}, "02827": {"val": 1020, "part": 61.0, "v": {"1": 571, "0": 449}}, "02837": {"val": 2858, "part": 52.7, "v": {"1": 908, "0": 1950}}, "02850": {"val": 2130, "part": 47.7, "v": {"0": 1495, "1": 635}}, "02855": {"val": 4245, "part": 52.9, "v": {"0": 2794, "1": 1451}}, "02860": {"val": 898, "part": 49.1, "v": {"1": 158, "0": 740}}, "02863": {"val": 2941, "part": 42.9, "v": {"0": 1805, "1": 1136}}, "02885": {"val": 13593, "part": 50.0, "v": {"1": 5554, "0": 8039}}, "02901": {"val": 3685, "part": 43.8, "v": {"0": 2390, "1": 1295}}, "02904": {"val": 2878, "part": 36.9, "v": {"0": 1747, "1": 1131}}, "02927": {"val": 2673, "part": 50.3, "v": {"0": 1303, "1": 1370}}, "02939": {"val": 1561, "part": 19.8, "v": {"0": 1038, "1": 523}}, "02980": {"val": 3886, "part": 51.3, "v": {"1": 1065, "0": 2821}}, "03062": {"val": 1848, "part": 24.8, "v": {"1": 770, "0": 1078}}, "03087": {"val": 4301, "part": 42.1, "v": {"0": 2919, "1": 1382}}, "03089": {"val": 3256, "part": 40.1, "v": {"0": 1452, "1": 1804}}, "03111": {"val": 5274, "part": 39.4, "v": {"0": 2030, "1": 3244}}, "03173": {"val": 2515, "part": 58.8, "v": {"0": 1607, "1": 908}}, "03205": {"val": 1265, "part": 26.2, "v": {"1": 576, "0": 689}}, "03242": {"val": 4116, "part": 49.0, "v": {"0": 2223, "1": 1893}}, "03246": {"val": 2138, "part": 50.8, "v": {"0": 1380, "1": 758}}, "03260": {"val": 29459, "part": 54.3, "v": {"0": 15963, "1": 13496}}, "03318": {"val": 3422, "part": 45.1, "v": {"1": 822, "0": 2600}}, "03322": {"val": 739, "part": 48.8, "v": {"1": 402, "0": 337}}, "03354": {"val": 2124, "part": 46.4, "v": {"0": 1766, "1": 358}}, "03365": {"val": 4648, "part": 46.4, "v": {"1": 1677, "0": 2971}}, "03388": {"val": 2022, "part": 32.2, "v": {"1": 717, "0": 1305}}, "03397": {"val": 574, "part": 17.1, "v": {"1": 266, "0": 308}}, "03447": {"val": 3213, "part": 40.0, "v": {"0": 2373, "1": 840}}, "03474": {"val": 1348, "part": 28.6, "v": {"0": 933, "1": 415}}, "03491": {"val": 2015, "part": 35.5, "v": {"1": 761, "0": 1254}}, "03525": {"val": 995, "part": 34.2, "v": {"1": 370, "0": 625}}, "03570": {"val": 2331, "part": 48.0, "v": {"0": 1433, "1": 898}}, "03648": {"val": 4105, "part": 47.0, "v": {"1": 914, "0": 3191}}, "04597": {"val": 4014, "part": 47.0, "v": {"0": 3062, "1": 952}}, "07295": {"val": 3743, "part": 43.2, "v": {"0": 2562, "1": 1181}}, "09391": {"val": 2710, "part": 32.8, "v": {"0": 1912, "1": 798}}, "09458": {"val": 83, "part": 10.6, "v": {"1": 42, "0": 41}}, "11127": {"val": 2079, "part": 13.1, "v": {"1": 997, "0": 1082}}, "11581": {"val": 5571, "part": 46.6, "v": {"1": 2069, "0": 3502}}, "12576": {"val": 3499, "part": 45.2, "v": {"0": 2111, "1": 1388}}, "13176": {"val": 21, "part": 5.9, "v": {"1": 15, "0": 6}}, "13193": {"val": 7101, "part": 54.9, "v": {"1": 2198, "0": 4903}}}}