{"meta": {"eleccion": "2020-10_plebiscito", "label": "Plebiscito", "tipo": "Plebiscito", "has_local": false, "n_cand": 4}, "candidatos": [{"i": 0, "nombre": "APRUEBO", "ape1": null, "bloque": null, "eje": null, "vn": 5874199}, {"i": 1, "nombre": "RECHAZO", "ape1": null, "bloque": null, "eje": null, "vn": 1628875}, {"i": 2, "nombre": "VOTOS NULOS", "ape1": null, "bloque": null, "eje": null, "vn": 27329}, {"i": 3, "nombre": "VOTOS EN BLANCO", "ape1": null, "bloque": null, "eje": null, "vn": 12313}], "comuna": {"10101": {"val": 88316, "part": 47.9, "v": {"0": 65567, "3": 159, "1": 22314, "2": 276}, "nb": 0}, "10102": {"val": 11282, "part": 35.3, "v": {"2": 97, "1": 2389, "0": 8728, "3": 68}, "nb": 0}, "10103": {"val": 1159, "part": 25.9, "v": {"1": 384, "0": 754, "3": 15, "2": 6}, "nb": 0}, "10104": {"val": 4683, "part": 38.6, "v": {"2": 20, "3": 18, "1": 1479, "0": 3166}, "nb": 0}, "10105": {"val": 7908, "part": 48.3, "v": {"0": 5185, "2": 36, "1": 2674, "3": 13}, "nb": 0}, "10106": {"val": 5116, "part": 31.5, "v": {"1": 2284, "3": 29, "2": 23, "0": 2780}, "nb": 0}, "10107": {"val": 7811, "part": 48.8, "v": {"1": 2077, "2": 27, "3": 25, "0": 5682}, "nb": 0}, "10108": {"val": 5095, "part": 33.2, "v": {"2": 30, "3": 14, "1": 1633, "0": 3418}, "nb": 0}, "10109": {"val": 21854, "part": 53.3, "v": {"1": 7734, "2": 64, "3": 51, "0": 14005}, "nb": 0}, "10201": {"val": 16660, "part": 40.5, "v": {"0": 13750, "3": 36, "1": 2830, "2": 44}, "nb": 0}, "10202": {"val": 14360, "part": 37.2, "v": {"1": 2565, "0": 11694, "3": 31, "2": 70}, "nb": 0}, "10203": {"val": 3638, "part": 28.1, "v": {"2": 17, "1": 525, "3": 15, "0": 3081}, "nb": 0}, "10204": {"val": 1315, "part": 35.4, "v": {"3": 4, "2": 8, "0": 1091, "1": 212}, "nb": 0}, "10205": {"val": 4012, "part": 32.5, "v": {"1": 634, "2": 22, "3": 12, "0": 3344}, "nb": 0}, "10206": {"val": 1194, "part": 27.5, "v": {"1": 130, "2": 6, "3": 7, "0": 1051}, "nb": 0}, "10207": {"val": 1494, "part": 24.7, "v": {"3": 4, "2": 2, "0": 1320, "1": 168}, "nb": 0}, "10208": {"val": 8657, "part": 38.4, "v": {"0": 6745, "2": 57, "1": 1804, "3": 51}, "nb": 0}, "10209": {"val": 2324, "part": 25.9, "v": {"0": 1922, "3": 16, "1": 377, "2": 9}, "nb": 0}, "10210": {"val": 2989, "part": 32.3, "v": {"3": 18, "2": 19, "0": 2536, "1": 416}, "nb": 0}, "10301": {"val": 70256, "part": 49.1, "v": {"1": 18202, "0": 51694, "2": 244, "3": 116}, "nb": 0}, "10302": {"val": 3591, "part": 40.4, "v": {"3": 12, "2": 11, "0": 2623, "1": 945}, "nb": 0}, "10303": {"val": 7891, "part": 39.9, "v": {"0": 5168, "3": 32, "1": 2655, "2": 36}, "nb": 0}, "10304": {"val": 4693, "part": 41.0, "v": {"0": 3208, "2": 33, "3": 20, "1": 1432}, "nb": 0}, "10305": {"val": 5288, "part": 39.9, "v": {"0": 3616, "3": 15, "1": 1635, "2": 22}, "nb": 0}, "10306": {"val": 3177, "part": 40.4, "v": {"0": 2530, "2": 15, "1": 613, "3": 19}, "nb": 0}, "10307": {"val": 4091, "part": 41.5, "v": {"1": 1111, "3": 13, "2": 26, "0": 2941}, "nb": 0}, "10401": {"val": 1363, "part": 26.9, "v": {"2": 7, "1": 387, "3": 5, "0": 964}, "nb": 0}, "10402": {"val": 965, "part": 25.4, "v": {"2": 2, "1": 330, "0": 630, "3": 3}, "nb": 0}, "10403": {"val": 2871, "part": 34.2, "v": {"0": 2325, "3": 9, "2": 13, "1": 524}, "nb": 0}, "10404": {"val": 636, "part": 27.2, "v": {"0": 422, "2": 6, "1": 202, "3": 6}, "nb": 0}, "1101": {"val": 80371, "part": 47.9, "v": {"0": 61103, "2": 275, "3": 114, "1": 18879}, "nb": 0}, "1107": {"val": 26258, "part": 45.5, "v": {"0": 21589, "2": 98, "3": 37, "1": 4534}, "nb": 0}, "11101": {"val": 22512, "part": 41.7, "v": {"2": 61, "1": 5243, "3": 43, "0": 17165}, "nb": 0}, "11102": {"val": 373, "part": 32.2, "v": {"1": 124, "2": 0, "3": 2, "0": 247}, "nb": 0}, "11201": {"val": 8984, "part": 40.1, "v": {"0": 7223, "2": 42, "3": 21, "1": 1698}, "nb": 0}, "11202": {"val": 1740, "part": 38.8, "v": {"2": 4, "3": 5, "1": 525, "0": 1206}, "nb": 0}, "11203": {"val": 607, "part": 38.1, "v": {"3": 2, "0": 488, "1": 117, "2": 0}, "nb": 0}, "11301": {"val": 1181, "part": 35.1, "v": {"0": 892, "2": 5, "3": 2, "1": 282}, "nb": 0}, "11303": {"val": 207, "part": 37.9, "v": {"1": 23, "2": 0, "3": 0, "0": 184}, "nb": 0}, "11401": {"val": 1685, "part": 26.4, "v": {"3": 4, "2": 5, "0": 1397, "1": 279}, "nb": 0}, "11402": {"val": 932, "part": 32.6, "v": {"1": 287, "2": 2, "3": 6, "0": 637}, "nb": 0}, "12101": {"val": 54128, "part": 44.2, "v": {"0": 42928, "3": 60, "2": 131, "1": 11009}, "nb": 0}, "12102": {"val": 201, "part": 24.3, "v": {"2": 0, "3": 0, "1": 62, "0": 139}, "nb": 0}, "12103": {"val": 183, "part": 23.7, "v": {"2": 0, "1": 58, "3": 1, "0": 124}, "nb": 0}, "12104": {"val": 205, "part": 22.8, "v": {"1": 74, "3": 1, "2": 0, "0": 130}, "nb": 0}, "12201": {"val": 645, "part": 33.7, "v": {"2": 1, "1": 269, "0": 375, "3": 0}, "nb": 0}, "12202": {"val": 31, "part": 11.5, "v": {"2": 0, "1": 21, "3": 0, "0": 10}, "nb": 0}, "12301": {"val": 1866, "part": 30.3, "v": {"3": 0, "2": 6, "0": 1539, "1": 321}, "nb": 0}, "12302": {"val": 253, "part": 20.0, "v": {"0": 218, "3": 0, "1": 35, "2": 0}, "nb": 0}, "12303": {"val": 94, "part": 11.3, "v": {"0": 63, "3": 0, "2": 1, "1": 30}, "nb": 0}, "12401": {"val": 7798, "part": 34.8, "v": {"3": 16, "0": 6506, "1": 1251, "2": 25}, "nb": 0}, "12402": {"val": 592, "part": 34.1, "v": {"1": 114, "2": 4, "3": 2, "0": 472}, "nb": 0}, "13101": {"val": 149864, "part": 44.4, "v": {"3": 184, "2": 413, "0": 119139, "1": 30128}, "nb": 0}, "13102": {"val": 37318, "part": 55.0, "v": {"3": 34, "2": 120, "0": 31192, "1": 5972}, "nb": 0}, "13103": {"val": 64083, "part": 55.0, "v": {"1": 7818, "2": 260, "3": 119, "0": 55886}, "nb": 0}, "13104": {"val": 65706, "part": 54.8, "v": {"3": 90, "2": 204, "0": 56395, "1": 9017}, "nb": 0}, "13105": {"val": 75831, "part": 54.6, "v": {"2": 274, "1": 11059, "0": 64391, "3": 107}, "nb": 0}, "13106": {"val": 62940, "part": 49.4, "v": {"2": 241, "3": 66, "1": 9905, "0": 52728}, "nb": 0}, "13107": {"val": 45959, "part": 63.2, "v": {"2": 153, "3": 71, "1": 8562, "0": 37173}, "nb": 0}, "13108": {"val": 38471, "part": 47.2, "v": {"2": 130, "1": 6991, "0": 31299, "3": 51}, "nb": 0}, "13109": {"val": 45847, "part": 54.9, "v": {"1": 8483, "2": 124, "3": 42, "0": 37198}, "nb": 0}, "13110": {"val": 182589, "part": 59.3, "v": {"0": 153235, "3": 179, "2": 479, "1": 28696}, "nb": 0}, "13111": {"val": 57326, "part": 54.6, "v": {"3": 74, "2": 206, "0": 49981, "1": 7065}, "nb": 0}, "13112": {"val": 73723, "part": 52.8, "v": {"3": 117, "2": 340, "0": 64779, "1": 8487}, "nb": 0}, "13113": {"val": 59183, "part": 64.5, "v": {"0": 39970, "3": 83, "2": 127, "1": 19003}, "nb": 0}, "13114": {"val": 166543, "part": 62.2, "v": {"1": 92459, "0": 73386, "3": 237, "2": 461}, "nb": 0}, "13115": {"val": 55258, "part": 67.9, "v": {"0": 21111, "2": 178, "3": 66, "1": 33903}, "nb": 0}, "13116": {"val": 50594, "part": 55.1, "v": {"0": 44806, "2": 215, "1": 5474, "3": 99}, "nb": 0}, "13117": {"val": 51366, "part": 57.2, "v": {"1": 6697, "0": 44379, "3": 74, "2": 216}, "nb": 0}, "13118": {"val": 60392, "part": 59.4, "v": {"1": 10384, "2": 170, "3": 76, "0": 49762}, "nb": 0}, "13119": {"val": 243115, "part": 62.4, "v": {"2": 644, "1": 33518, "3": 206, "0": 208747}, "nb": 0}, "13120": {"val": 125508, "part": 64.2, "v": {"1": 29798, "0": 95362, "2": 226, "3": 122}, "nb": 0}, "13121": {"val": 55710, "part": 59.2, "v": {"1": 6787, "2": 228, "3": 81, "0": 48614}, "nb": 0}, "13122": {"val": 115226, "part": 59.9, "v": {"3": 169, "2": 440, "0": 96529, "1": 18088}, "nb": 0}, "13123": {"val": 94109, "part": 55.4, "v": {"0": 60130, "3": 100, "1": 33672, "2": 207}, "nb": 0}, "13124": {"val": 99725, "part": 59.2, "v": {"0": 87139, "3": 122, "1": 12162, "2": 302}, "nb": 0}, "13125": {"val": 84048, "part": 60.8, "v": {"0": 73637, "3": 75, "2": 216, "1": 10120}, "nb": 0}, "13126": {"val": 55219, "part": 53.8, "v": {"3": 75, "0": 46729, "1": 8235, "2": 180}, "nb": 0}, "13127": {"val": 76388, "part": 53.1, "v": {"3": 117, "2": 318, "0": 64286, "1": 11667}, "nb": 0}, "13128": {"val": 65224, "part": 55.7, "v": {"3": 88, "2": 242, "0": 57657, "1": 7237}, "nb": 0}, "13129": {"val": 48221, "part": 58.0, "v": {"1": 6210, "2": 149, "3": 62, "0": 41800}, "nb": 0}, "13130": {"val": 57222, "part": 54.8, "v": {"1": 10624, "0": 46402, "3": 39, "2": 157}, "nb": 0}, "13131": {"val": 45247, "part": 54.9, "v": {"0": 38971, "3": 98, "1": 5951, "2": 227}, "nb": 0}, "13132": {"val": 60325, "part": 68.0, "v": {"2": 162, "1": 40323, "0": 19746, "3": 94}, "nb": 0}, "13201": {"val": 232278, "part": 58.2, "v": {"0": 204801, "3": 238, "1": 26598, "2": 641}, "nb": 0}, "13202": {"val": 13102, "part": 60.3, "v": {"0": 10055, "3": 18, "1": 2994, "2": 35}, "nb": 0}, "13203": {"val": 8929, "part": 57.2, "v": {"1": 1373, "2": 27, "3": 22, "0": 7507}, "nb": 0}, "13301": {"val": 49452, "part": 56.2, "v": {"1": 16625, "3": 99, "2": 204, "0": 32524}, "nb": 0}, "13302": {"val": 31541, "part": 55.3, "v": {"1": 5399, "2": 94, "3": 53, "0": 25995}, "nb": 0}, "13303": {"val": 8051, "part": 56.0, "v": {"1": 1213, "2": 37, "3": 13, "0": 6788}, "nb": 0}, "13401": {"val": 119822, "part": 52.5, "v": {"2": 461, "1": 17606, "0": 101585, "3": 170}, "nb": 0}, "13402": {"val": 40587, "part": 55.2, "v": {"2": 124, "3": 59, "1": 7166, "0": 33238}, "nb": 0}, "13403": {"val": 12750, "part": 57.9, "v": {"2": 41, "1": 3340, "3": 17, "0": 9352}, "nb": 0}, "13404": {"val": 27951, "part": 53.2, "v": {"1": 5141, "2": 115, "3": 58, "0": 22637}, "nb": 0}, "13501": {"val": 43097, "part": 44.6, "v": {"0": 34983, "2": 150, "1": 7901, "3": 63}, "nb": 0}, "13502": {"val": 2640, "part": 44.0, "v": {"0": 2323, "2": 7, "1": 309, "3": 1}, "nb": 0}, "13503": {"val": 14789, "part": 57.2, "v": {"1": 2969, "2": 79, "3": 28, "0": 11713}, "nb": 0}, "13504": {"val": 5473, "part": 48.6, "v": {"1": 1022, "0": 4424, "3": 12, "2": 15}, "nb": 0}, "13505": {"val": 3029, "part": 36.7, "v": {"1": 629, "2": 16, "3": 10, "0": 2374}, "nb": 0}, "13601": {"val": 34530, "part": 59.9, "v": {"1": 6577, "2": 114, "3": 53, "0": 27786}, "nb": 0}, "13602": {"val": 15075, "part": 55.0, "v": {"2": 64, "1": 2378, "0": 12605, "3": 28}, "nb": 0}, "13603": {"val": 15226, "part": 55.8, "v": {"2": 59, "1": 2765, "3": 21, "0": 12381}, "nb": 0}, "13604": {"val": 26116, "part": 61.0, "v": {"1": 3501, "3": 22, "2": 95, "0": 22498}, "nb": 0}, "13605": {"val": 43190, "part": 60.0, "v": {"1": 6127, "2": 103, "3": 71, "0": 36889}, "nb": 0}, "1401": {"val": 4846, "part": 40.8, "v": {"0": 3730, "3": 11, "2": 29, "1": 1076}, "nb": 0}, "1402": {"val": 513, "part": 20.1, "v": {"1": 207, "3": 2, "2": 11, "0": 293}, "nb": 0}, "1403": {"val": 524, "part": 17.5, "v": {"1": 374, "0": 131, "3": 3, "2": 16}, "nb": 0}, "1404": {"val": 1529, "part": 16.9, "v": {"2": 8, "1": 379, "0": 1136, "3": 6}, "nb": 0}, "1405": {"val": 2435, "part": 44.6, "v": {"0": 1769, "2": 16, "1": 646, "3": 4}, "nb": 0}, "14101": {"val": 75159, "part": 54.7, "v": {"3": 121, "0": 58607, "1": 16175, "2": 256}, "nb": 0}, "14102": {"val": 2379, "part": 43.7, "v": {"2": 13, "1": 370, "3": 5, "0": 1991}, "nb": 0}, "14103": {"val": 6697, "part": 41.8, "v": {"0": 5084, "3": 24, "2": 28, "1": 1561}, "nb": 0}, "14104": {"val": 7512, "part": 39.8, "v": {"1": 2050, "0": 5399, "2": 38, "3": 25}, "nb": 0}, "14105": {"val": 2853, "part": 40.8, "v": {"0": 2049, "2": 10, "1": 785, "3": 9}, "nb": 0}, "14106": {"val": 7772, "part": 41.7, "v": {"3": 24, "0": 5934, "1": 1783, "2": 31}, "nb": 0}, "14107": {"val": 7673, "part": 40.3, "v": {"1": 2188, "2": 27, "3": 24, "0": 5434}, "nb": 0}, "14108": {"val": 12449, "part": 36.0, "v": {"1": 3697, "0": 8572, "3": 72, "2": 108}, "nb": 0}, "14201": {"val": 14908, "part": 42.0, "v": {"0": 10749, "3": 26, "1": 4063, "2": 70}, "nb": 0}, "14202": {"val": 5732, "part": 39.7, "v": {"0": 3484, "3": 26, "2": 38, "1": 2184}, "nb": 0}, "14203": {"val": 3348, "part": 36.2, "v": {"0": 2093, "3": 21, "2": 26, "1": 1208}, "nb": 0}, "14204": {"val": 11648, "part": 38.0, "v": {"0": 7935, "3": 44, "1": 3613, "2": 56}, "nb": 0}, "15101": {"val": 84326, "part": 46.8, "v": {"1": 19716, "3": 167, "2": 421, "0": 64022}, "nb": 0}, "15102": {"val": 919, "part": 26.5, "v": {"0": 756, "3": 2, "1": 159, "2": 2}, "nb": 0}, "15201": {"val": 1075, "part": 19.4, "v": {"0": 719, "2": 7, "1": 346, "3": 3}, "nb": 0}, "15202": {"val": 313, "part": 14.5, "v": {"1": 80, "0": 220, "2": 9, "3": 4}, "nb": 0}, "16101": {"val": 75892, "part": 49.6, "v": {"0": 54338, "3": 124, "2": 279, "1": 21151}, "nb": 0}, "16102": {"val": 7803, "part": 38.0, "v": {"1": 2163, "3": 22, "2": 44, "0": 5574}, "nb": 0}, "16103": {"val": 11274, "part": 52.1, "v": {"0": 8077, "3": 20, "1": 3142, "2": 35}, "nb": 0}, "16104": {"val": 3774, "part": 30.6, "v": {"0": 2390, "3": 13, "1": 1353, "2": 18}, "nb": 0}, "16105": {"val": 2880, "part": 35.4, "v": {"3": 11, "2": 10, "0": 1935, "1": 924}, "nb": 0}, "16106": {"val": 4300, "part": 39.0, "v": {"0": 2235, "3": 22, "1": 2014, "2": 29}, "nb": 0}, "16107": {"val": 5913, "part": 38.5, "v": {"3": 16, "2": 32, "0": 4072, "1": 1793}, "nb": 0}, "16108": {"val": 4950, "part": 34.4, "v": {"0": 3255, "2": 32, "3": 15, "1": 1648}, "nb": 0}, "16109": {"val": 6891, "part": 42.6, "v": {"2": 29, "1": 1584, "3": 16, "0": 5262}, "nb": 0}, "16201": {"val": 3986, "part": 36.5, "v": {"0": 3159, "2": 32, "1": 781, "3": 14}, "nb": 0}, "16202": {"val": 2075, "part": 36.8, "v": {"1": 459, "0": 1595, "3": 11, "2": 10}, "nb": 0}, "16203": {"val": 6790, "part": 44.5, "v": {"2": 28, "1": 2203, "3": 21, "0": 4538}, "nb": 0}, "16204": {"val": 1920, "part": 31.9, "v": {"0": 1353, "2": 14, "1": 547, "3": 6}, "nb": 0}, "16205": {"val": 2038, "part": 35.4, "v": {"0": 1420, "2": 7, "1": 606, "3": 5}, "nb": 0}, "16206": {"val": 2199, "part": 39.7, "v": {"0": 1505, "3": 7, "1": 672, "2": 15}, "nb": 0}, "16207": {"val": 2115, "part": 36.0, "v": {"3": 9, "2": 9, "0": 1569, "1": 528}, "nb": 0}, "16301": {"val": 18120, "part": 38.2, "v": {"0": 12268, "2": 89, "1": 5729, "3": 34}, "nb": 0}, "16302": {"val": 7229, "part": 33.1, "v": {"0": 4420, "2": 47, "3": 25, "1": 2737}, "nb": 0}, "16303": {"val": 3259, "part": 31.4, "v": {"0": 2003, "2": 17, "3": 11, "1": 1228}, "nb": 0}, "16304": {"val": 1898, "part": 39.2, "v": {"1": 512, "2": 12, "3": 7, "0": 1367}, "nb": 0}, "16305": {"val": 4741, "part": 41.4, "v": {"1": 1352, "2": 34, "3": 21, "0": 3334}, "nb": 0}, "2101": {"val": 144079, "part": 50.7, "v": {"1": 23533, "2": 430, "3": 130, "0": 119986}, "nb": 0}, "2102": {"val": 5128, "part": 52.2, "v": {"0": 4572, "3": 7, "2": 16, "1": 533}, "nb": 0}, "2103": {"val": 856, "part": 27.0, "v": {"0": 749, "3": 0, "2": 3, "1": 104}, "nb": 0}, "2104": {"val": 4665, "part": 44.8, "v": {"1": 565, "0": 4072, "3": 9, "2": 19}, "nb": 0}, "2201": {"val": 62783, "part": 47.4, "v": {"1": 10280, "2": 355, "3": 91, "0": 52057}, "nb": 0}, "2202": {"val": 379, "part": 21.2, "v": {"1": 61, "3": 0, "2": 1, "0": 317}, "nb": 0}, "2203": {"val": 3337, "part": 48.2, "v": {"3": 12, "0": 2911, "1": 398, "2": 16}, "nb": 0}, "2301": {"val": 10288, "part": 46.1, "v": {"3": 17, "0": 9211, "1": 1023, "2": 37}, "nb": 0}, "2302": {"val": 2138, "part": 33.1, "v": {"1": 187, "0": 1938, "3": 5, "2": 8}, "nb": 0}, "3101": {"val": 61103, "part": 49.5, "v": {"0": 51149, "3": 64, "2": 230, "1": 9660}, "nb": 0}, "3102": {"val": 7985, "part": 54.5, "v": {"0": 6812, "3": 12, "2": 34, "1": 1127}, "nb": 0}, "3103": {"val": 5785, "part": 45.3, "v": {"1": 660, "2": 26, "3": 15, "0": 5084}, "nb": 0}, "3201": {"val": 5760, "part": 48.0, "v": {"0": 5185, "3": 14, "1": 544, "2": 17}, "nb": 0}, "3202": {"val": 5410, "part": 40.2, "v": {"1": 499, "2": 17, "3": 8, "0": 4886}, "nb": 0}, "3301": {"val": 21075, "part": 46.4, "v": {"1": 2463, "3": 37, "2": 90, "0": 18485}, "nb": 0}, "3302": {"val": 1817, "part": 37.3, "v": {"0": 1559, "3": 8, "1": 241, "2": 9}, "nb": 0}, "3303": {"val": 2701, "part": 45.8, "v": {"3": 1, "2": 14, "0": 2465, "1": 221}, "nb": 0}, "3304": {"val": 4236, "part": 50.9, "v": {"1": 404, "3": 6, "2": 18, "0": 3808}, "nb": 0}, "4101": {"val": 90124, "part": 52.3, "v": {"1": 16545, "2": 224, "3": 101, "0": 73254}, "nb": 0}, "4102": {"val": 82530, "part": 49.9, "v": {"0": 69539, "3": 102, "2": 274, "1": 12615}, "nb": 0}, "4103": {"val": 6071, "part": 54.1, "v": {"1": 582, "0": 5450, "3": 13, "2": 26}, "nb": 0}, "4104": {"val": 1564, "part": 36.5, "v": {"2": 9, "3": 4, "1": 206, "0": 1345}, "nb": 0}, "4105": {"val": 2414, "part": 47.1, "v": {"1": 442, "2": 8, "3": 6, "0": 1958}, "nb": 0}, "4106": {"val": 10857, "part": 47.0, "v": {"1": 1308, "0": 9483, "2": 45, "3": 21}, "nb": 0}, "4201": {"val": 12633, "part": 45.7, "v": {"0": 11166, "3": 29, "1": 1382, "2": 56}, "nb": 0}, "4202": {"val": 3781, "part": 42.4, "v": {"0": 3320, "2": 16, "1": 433, "3": 12}, "nb": 0}, "4203": {"val": 8875, "part": 49.1, "v": {"0": 7679, "3": 18, "1": 1153, "2": 25}, "nb": 0}, "4204": {"val": 10523, "part": 45.4, "v": {"0": 8984, "2": 53, "1": 1470, "3": 16}, "nb": 0}, "4301": {"val": 40319, "part": 44.1, "v": {"2": 151, "1": 5898, "0": 34181, "3": 89}, "nb": 0}, "4302": {"val": 5064, "part": 40.6, "v": {"1": 604, "3": 15, "2": 17, "0": 4428}, "nb": 0}, "4303": {"val": 11192, "part": 40.1, "v": {"3": 23, "0": 9838, "1": 1275, "2": 56}, "nb": 0}, "4304": {"val": 4183, "part": 39.6, "v": {"0": 3627, "2": 27, "3": 24, "1": 505}, "nb": 0}, "4305": {"val": 1638, "part": 34.9, "v": {"0": 1353, "3": 10, "1": 266, "2": 9}, "nb": 0}, "5101": {"val": 148145, "part": 50.9, "v": {"0": 122068, "3": 186, "1": 25405, "2": 486}, "nb": 0}, "5102": {"val": 11508, "part": 52.0, "v": {"1": 2292, "3": 16, "2": 52, "0": 9148}, "nb": 0}, "5103": {"val": 24384, "part": 63.9, "v": {"2": 74, "3": 32, "1": 8573, "0": 15705}, "nb": 0}, "5104": {"val": 439, "part": 47.9, "v": {"2": 0, "1": 62, "0": 377, "3": 0}, "nb": 0}, "5105": {"val": 8659, "part": 56.8, "v": {"3": 24, "2": 19, "0": 7244, "1": 1372}, "nb": 0}, "5107": {"val": 12943, "part": 53.4, "v": {"0": 10452, "2": 70, "3": 21, "1": 2400}, "nb": 0}, "5109": {"val": 160831, "part": 53.4, "v": {"2": 492, "1": 43263, "3": 190, "0": 116886}, "nb": 0}, "5201": {"val": 2726, "part": 45.0, "v": {"1": 416, "0": 2292, "2": 11, "3": 7}, "nb": 0}, "5301": {"val": 31276, "part": 55.8, "v": {"1": 5773, "0": 25366, "3": 37, "2": 100}, "nb": 0}, "5302": {"val": 6609, "part": 58.7, "v": {"0": 5607, "3": 10, "1": 955, "2": 37}, "nb": 0}, "5303": {"val": 5434, "part": 59.1, "v": {"1": 1036, "0": 4365, "2": 18, "3": 15}, "nb": 0}, "5304": {"val": 8639, "part": 58.0, "v": {"3": 16, "2": 46, "0": 7115, "1": 1462}, "nb": 0}, "5401": {"val": 16001, "part": 53.1, "v": {"3": 24, "0": 13580, "1": 2340, "2": 57}, "nb": 0}, "5402": {"val": 9099, "part": 50.4, "v": {"0": 7948, "2": 35, "3": 16, "1": 1100}, "nb": 0}, "5403": {"val": 3499, "part": 62.0, "v": {"0": 2780, "2": 13, "1": 701, "3": 5}, "nb": 0}, "5404": {"val": 4639, "part": 49.8, "v": {"2": 20, "3": 15, "1": 458, "0": 4146}, "nb": 0}, "5405": {"val": 4909, "part": 61.9, "v": {"3": 3, "2": 13, "0": 3250, "1": 1643}, "nb": 0}, "5501": {"val": 39004, "part": 52.0, "v": {"3": 51, "2": 149, "0": 30871, "1": 7933}, "nb": 0}, "5502": {"val": 24125, "part": 53.6, "v": {"3": 45, "2": 94, "0": 20625, "1": 3361}, "nb": 0}, "5503": {"val": 7648, "part": 49.6, "v": {"0": 6338, "2": 28, "1": 1266, "3": 16}, "nb": 0}, "5504": {"val": 9006, "part": 57.1, "v": {"0": 6989, "3": 7, "1": 1988, "2": 22}, "nb": 0}, "5506": {"val": 10812, "part": 55.0, "v": {"3": 25, "2": 46, "0": 9520, "1": 1221}, "nb": 0}, "5601": {"val": 44040, "part": 56.1, "v": {"2": 98, "3": 34, "1": 4939, "0": 38969}, "nb": 0}, "5602": {"val": 7086, "part": 54.9, "v": {"2": 23, "1": 2118, "0": 4932, "3": 13}, "nb": 0}, "5603": {"val": 9075, "part": 51.2, "v": {"0": 7346, "2": 18, "1": 1700, "3": 11}, "nb": 0}, "5604": {"val": 7241, "part": 56.1, "v": {"2": 30, "1": 1437, "3": 7, "0": 5767}, "nb": 0}, "5605": {"val": 5842, "part": 56.7, "v": {"2": 19, "1": 1142, "3": 6, "0": 4675}, "nb": 0}, "5606": {"val": 6623, "part": 60.8, "v": {"3": 15, "2": 22, "0": 4003, "1": 2583}, "nb": 0}, "5701": {"val": 33389, "part": 55.6, "v": {"2": 121, "3": 44, "1": 6123, "0": 27101}, "nb": 0}, "5702": {"val": 5965, "part": 49.5, "v": {"1": 711, "2": 46, "3": 9, "0": 5199}, "nb": 0}, "5703": {"val": 11645, "part": 56.2, "v": {"3": 15, "2": 51, "0": 10304, "1": 1275}, "nb": 0}, "5704": {"val": 3588, "part": 56.3, "v": {"2": 12, "1": 718, "3": 0, "0": 2858}, "nb": 0}, "5705": {"val": 7246, "part": 52.3, "v": {"2": 32, "1": 968, "3": 24, "0": 6222}, "nb": 0}, "5706": {"val": 6466, "part": 54.2, "v": {"2": 28, "1": 1085, "0": 5345, "3": 8}, "nb": 0}, "5801": {"val": 74059, "part": 55.6, "v": {"1": 16247, "0": 57470, "2": 270, "3": 72}, "nb": 0}, "5802": {"val": 20221, "part": 52.4, "v": {"1": 4531, "3": 41, "2": 77, "0": 15572}, "nb": 0}, "5803": {"val": 8031, "part": 49.8, "v": {"3": 11, "2": 39, "0": 5984, "1": 1997}, "nb": 0}, "5804": {"val": 53381, "part": 55.1, "v": {"2": 162, "1": 12054, "3": 56, "0": 41109}, "nb": 0}, "6101": {"val": 107084, "part": 55.0, "v": {"3": 111, "2": 325, "0": 87494, "1": 19154}, "nb": 0}, "6102": {"val": 5932, "part": 52.5, "v": {"3": 6, "0": 5034, "1": 871, "2": 21}, "nb": 0}, "6103": {"val": 3346, "part": 47.7, "v": {"3": 7, "2": 22, "0": 2616, "1": 701}, "nb": 0}, "6104": {"val": 7545, "part": 47.4, "v": {"2": 34, "1": 1340, "3": 16, "0": 6155}, "nb": 0}, "6105": {"val": 9423, "part": 52.2, "v": {"0": 7987, "2": 29, "1": 1393, "3": 14}, "nb": 0}, "6106": {"val": 15292, "part": 57.5, "v": {"0": 12968, "3": 33, "1": 2230, "2": 61}, "nb": 0}, "6107": {"val": 8668, "part": 43.5, "v": {"1": 1426, "0": 7187, "2": 36, "3": 19}, "nb": 0}, "6108": {"val": 20932, "part": 58.6, "v": {"0": 16393, "3": 35, "1": 4461, "2": 43}, "nb": 0}, "6109": {"val": 5435, "part": 44.9, "v": {"2": 26, "1": 1149, "3": 14, "0": 4246}, "nb": 0}, "6110": {"val": 11438, "part": 55.4, "v": {"0": 9673, "3": 21, "2": 32, "1": 1712}, "nb": 0}, "6111": {"val": 6485, "part": 52.7, "v": {"1": 1336, "2": 17, "3": 11, "0": 5121}, "nb": 0}, "6112": {"val": 6230, "part": 49.0, "v": {"1": 843, "0": 5355, "2": 18, "3": 14}, "nb": 0}, "6113": {"val": 6471, "part": 39.2, "v": {"0": 5350, "3": 19, "2": 22, "1": 1080}, "nb": 0}, "6114": {"val": 6460, "part": 52.4, "v": {"3": 10, "2": 17, "0": 5504, "1": 929}, "nb": 0}, "6115": {"val": 24849, "part": 51.5, "v": {"1": 4264, "3": 51, "2": 101, "0": 20433}, "nb": 0}, "6116": {"val": 12078, "part": 53.3, "v": {"0": 9428, "3": 20, "1": 2590, "2": 40}, "nb": 0}, "6117": {"val": 19897, "part": 49.3, "v": {"0": 16379, "2": 54, "3": 38, "1": 3426}, "nb": 0}, "6201": {"val": 7618, "part": 50.9, "v": {"2": 29, "1": 1407, "3": 9, "0": 6173}, "nb": 0}, "6202": {"val": 1484, "part": 42.9, "v": {"0": 1158, "2": 8, "1": 315, "3": 3}, "nb": 0}, "6203": {"val": 2529, "part": 41.1, "v": {"2": 7, "3": 4, "1": 547, "0": 1971}, "nb": 0}, "6204": {"val": 2926, "part": 43.1, "v": {"1": 499, "2": 11, "3": 8, "0": 2408}, "nb": 0}, "6205": {"val": 2914, "part": 46.3, "v": {"0": 2322, "3": 10, "1": 568, "2": 14}, "nb": 0}, "6206": {"val": 2471, "part": 37.1, "v": {"2": 21, "1": 467, "3": 9, "0": 1974}, "nb": 0}, "6301": {"val": 33308, "part": 53.1, "v": {"1": 7135, "2": 87, "3": 41, "0": 26045}, "nb": 0}, "6302": {"val": 4915, "part": 36.2, "v": {"1": 1119, "3": 5, "2": 17, "0": 3774}, "nb": 0}, "6303": {"val": 13802, "part": 45.6, "v": {"0": 11218, "2": 64, "1": 2498, "3": 22}, "nb": 0}, "6304": {"val": 2433, "part": 36.2, "v": {"3": 10, "0": 1815, "1": 593, "2": 15}, "nb": 0}, "6305": {"val": 7059, "part": 46.7, "v": {"0": 5840, "3": 9, "2": 23, "1": 1187}, "nb": 0}, "6306": {"val": 4336, "part": 42.1, "v": {"0": 3500, "3": 6, "1": 822, "2": 8}, "nb": 0}, "6307": {"val": 4540, "part": 45.1, "v": {"0": 3608, "3": 6, "1": 911, "2": 15}, "nb": 0}, "6308": {"val": 3945, "part": 48.6, "v": {"2": 15, "1": 703, "0": 3222, "3": 5}, "nb": 0}, "6309": {"val": 1574, "part": 40.8, "v": {"2": 6, "1": 342, "0": 1222, "3": 4}, "nb": 0}, "6310": {"val": 13556, "part": 43.7, "v": {"2": 55, "3": 29, "1": 3232, "0": 10240}, "nb": 0}, "7101": {"val": 96924, "part": 54.0, "v": {"1": 21587, "0": 74989, "2": 240, "3": 108}, "nb": 0}, "7102": {"val": 18307, "part": 45.9, "v": {"0": 14300, "3": 38, "2": 81, "1": 3888}, "nb": 0}, "7103": {"val": 3560, "part": 35.1, "v": {"1": 736, "0": 2793, "2": 15, "3": 16}, "nb": 0}, "7104": {"val": 1513, "part": 34.7, "v": {"1": 676, "2": 9, "3": 7, "0": 821}, "nb": 0}, "7105": {"val": 10877, "part": 47.8, "v": {"2": 52, "1": 2454, "0": 8355, "3": 16}, "nb": 0}, "7106": {"val": 3391, "part": 40.4, "v": {"0": 2589, "2": 15, "3": 4, "1": 783}, "nb": 0}, "7107": {"val": 4169, "part": 40.7, "v": {"1": 1219, "2": 18, "3": 4, "0": 2928}, "nb": 0}, "7108": {"val": 4797, "part": 41.2, "v": {"2": 23, "1": 1017, "0": 3733, "3": 24}, "nb": 0}, "7109": {"val": 14892, "part": 40.5, "v": {"1": 3102, "0": 11647, "2": 95, "3": 48}, "nb": 0}, "7110": {"val": 3756, "part": 45.4, "v": {"1": 796, "3": 11, "2": 14, "0": 2935}, "nb": 0}, "7201": {"val": 13060, "part": 34.7, "v": {"2": 75, "1": 4697, "0": 8227, "3": 61}, "nb": 0}, "7202": {"val": 2899, "part": 31.3, "v": {"1": 1095, "2": 21, "3": 18, "0": 1765}, "nb": 0}, "7203": {"val": 2917, "part": 39.6, "v": {"0": 1944, "2": 14, "1": 952, "3": 7}, "nb": 0}, "7301": {"val": 63015, "part": 53.8, "v": {"2": 222, "1": 14296, "3": 106, "0": 48391}, "nb": 0}, "7302": {"val": 4118, "part": 43.0, "v": {"3": 10, "2": 24, "0": 3300, "1": 784}, "nb": 0}, "7303": {"val": 2929, "part": 42.8, "v": {"3": 9, "2": 16, "0": 2412, "1": 492}, "nb": 0}, "7304": {"val": 19214, "part": 49.4, "v": {"0": 15425, "2": 69, "3": 26, "1": 3694}, "nb": 0}, "7305": {"val": 4217, "part": 43.4, "v": {"1": 956, "2": 23, "3": 8, "0": 3230}, "nb": 0}, "7306": {"val": 6344, "part": 46.3, "v": {"2": 30, "1": 1748, "0": 4558, "3": 8}, "nb": 0}, "7307": {"val": 7659, "part": 48.5, "v": {"2": 52, "1": 1335, "0": 6256, "3": 16}, "nb": 0}, "7308": {"val": 10365, "part": 42.0, "v": {"3": 30, "0": 8028, "1": 2258, "2": 49}, "nb": 0}, "7309": {"val": 2232, "part": 43.8, "v": {"2": 9, "1": 649, "3": 8, "0": 1566}, "nb": 0}, "7401": {"val": 35878, "part": 43.9, "v": {"0": 25878, "3": 48, "2": 124, "1": 9828}, "nb": 0}, "7402": {"val": 6924, "part": 38.6, "v": {"3": 18, "2": 27, "0": 5375, "1": 1504}, "nb": 0}, "7403": {"val": 7859, "part": 29.7, "v": {"3": 15, "0": 5457, "1": 2346, "2": 41}, "nb": 0}, "7404": {"val": 14897, "part": 39.5, "v": {"1": 4520, "0": 10252, "3": 37, "2": 88}, "nb": 0}, "7405": {"val": 5206, "part": 30.3, "v": {"3": 24, "2": 33, "0": 3583, "1": 1566}, "nb": 0}, "7406": {"val": 15427, "part": 39.6, "v": {"0": 11301, "3": 38, "1": 4022, "2": 66}, "nb": 0}, "7407": {"val": 5435, "part": 40.2, "v": {"0": 3774, "2": 22, "1": 1628, "3": 11}, "nb": 0}, "7408": {"val": 5606, "part": 38.5, "v": {"0": 3881, "3": 15, "1": 1675, "2": 35}, "nb": 0}, "8101": {"val": 104579, "part": 52.0, "v": {"0": 77106, "2": 336, "1": 27032, "3": 105}, "nb": 0}, "8102": {"val": 44286, "part": 49.8, "v": {"0": 33464, "3": 91, "1": 10530, "2": 201}, "nb": 0}, "8103": {"val": 38312, "part": 57.3, "v": {"3": 50, "2": 148, "0": 29875, "1": 8239}, "nb": 0}, "8104": {"val": 3757, "part": 36.6, "v": {"0": 2612, "3": 12, "2": 23, "1": 1110}, "nb": 0}, "8105": {"val": 9427, "part": 46.9, "v": {"2": 59, "1": 1944, "3": 46, "0": 7378}, "nb": 0}, "8106": {"val": 22943, "part": 47.8, "v": {"0": 17051, "2": 159, "3": 69, "1": 5664}, "nb": 0}, "8107": {"val": 23135, "part": 55.0, "v": {"3": 38, "2": 92, "0": 18663, "1": 4342}, "nb": 0}, "8108": {"val": 49632, "part": 56.5, "v": {"0": 36103, "2": 159, "1": 13305, "3": 65}, "nb": 0}, "8109": {"val": 5142, "part": 40.9, "v": {"3": 24, "2": 45, "0": 3541, "1": 1532}, "nb": 0}, "8110": {"val": 67865, "part": 51.1, "v": {"1": 15589, "2": 245, "3": 98, "0": 51933}, "nb": 0}, "8111": {"val": 23520, "part": 47.4, "v": {"0": 17846, "2": 92, "1": 5527, "3": 55}, "nb": 0}, "8112": {"val": 43524, "part": 56.2, "v": {"2": 189, "1": 9006, "3": 74, "0": 34255}, "nb": 0}, "8201": {"val": 8516, "part": 38.4, "v": {"1": 2786, "2": 74, "3": 26, "0": 5630}, "nb": 0}, "8202": {"val": 14467, "part": 46.9, "v": {"3": 44, "0": 10377, "1": 3986, "2": 60}, "nb": 0}, "8203": {"val": 10523, "part": 35.9, "v": {"0": 7038, "2": 50, "1": 3405, "3": 30}, "nb": 0}, "8204": {"val": 2094, "part": 34.8, "v": {"1": 933, "3": 3, "2": 9, "0": 1149}, "nb": 0}, "8205": {"val": 13158, "part": 42.9, "v": {"3": 38, "0": 9807, "1": 3229, "2": 84}, "nb": 0}, "8206": {"val": 6650, "part": 37.3, "v": {"0": 4194, "2": 35, "1": 2393, "3": 28}, "nb": 0}, "8207": {"val": 3094, "part": 34.0, "v": {"1": 938, "0": 2100, "3": 19, "2": 37}, "nb": 0}, "8301": {"val": 68745, "part": 42.5, "v": {"0": 43288, "2": 320, "1": 24965, "3": 172}, "nb": 0}, "8302": {"val": 1793, "part": 39.3, "v": {"1": 431, "0": 1341, "2": 17, "3": 4}, "nb": 0}, "8303": {"val": 10044, "part": 40.3, "v": {"0": 6858, "3": 24, "1": 3118, "2": 44}, "nb": 0}, "8304": {"val": 9327, "part": 43.5, "v": {"3": 25, "2": 70, "0": 7030, "1": 2202}, "nb": 0}, "8305": {"val": 10136, "part": 37.9, "v": {"0": 7252, "3": 48, "2": 76, "1": 2760}, "nb": 0}, "8306": {"val": 10403, "part": 42.2, "v": {"0": 7267, "2": 47, "3": 29, "1": 3060}, "nb": 0}, "8307": {"val": 3704, "part": 41.6, "v": {"1": 1361, "0": 2287, "2": 37, "3": 19}, "nb": 0}, "8308": {"val": 1554, "part": 36.5, "v": {"1": 408, "0": 1122, "3": 6, "2": 18}, "nb": 0}, "8309": {"val": 3240, "part": 34.8, "v": {"0": 2203, "2": 23, "1": 998, "3": 16}, "nb": 0}, "8310": {"val": 1958, "part": 44.6, "v": {"3": 4, "2": 12, "0": 1591, "1": 351}, "nb": 0}, "8311": {"val": 4658, "part": 35.2, "v": {"0": 3257, "2": 30, "3": 21, "1": 1350}, "nb": 0}, "8312": {"val": 5257, "part": 40.8, "v": {"2": 29, "1": 1267, "0": 3939, "3": 22}, "nb": 0}, "8313": {"val": 7476, "part": 37.6, "v": {"0": 5246, "3": 25, "1": 2149, "2": 56}, "nb": 0}, "8314": {"val": 1805, "part": 32.9, "v": {"1": 424, "0": 1269, "2": 69, "3": 43}, "nb": 0}, "9101": {"val": 117020, "part": 49.6, "v": {"1": 38159, "0": 78332, "2": 360, "3": 169}, "nb": 0}, "9102": {"val": 7262, "part": 29.5, "v": {"0": 4978, "3": 25, "1": 2220, "2": 39}, "nb": 0}, "9103": {"val": 6082, "part": 30.6, "v": {"0": 4090, "2": 47, "3": 31, "1": 1914}, "nb": 0}, "9104": {"val": 2655, "part": 31.9, "v": {"0": 1740, "3": 12, "1": 891, "2": 12}, "nb": 0}, "9105": {"val": 7670, "part": 33.7, "v": {"2": 51, "3": 20, "1": 2401, "0": 5198}, "nb": 0}, "9106": {"val": 3537, "part": 29.5, "v": {"2": 46, "1": 995, "3": 24, "0": 2472}, "nb": 0}, "9107": {"val": 5419, "part": 35.0, "v": {"2": 25, "3": 20, "1": 2084, "0": 3290}, "nb": 0}, "9108": {"val": 12915, "part": 37.9, "v": {"2": 68, "3": 22, "1": 4788, "0": 8037}, "nb": 0}, "9109": {"val": 8237, "part": 35.7, "v": {"2": 27, "3": 13, "1": 2072, "0": 6125}, "nb": 0}, "9110": {"val": 2159, "part": 28.7, "v": {"2": 15, "1": 584, "3": 18, "0": 1542}, "nb": 0}, "9111": {"val": 12100, "part": 39.7, "v": {"2": 83, "3": 34, "1": 3218, "0": 8765}, "nb": 0}, "9112": {"val": 24121, "part": 41.6, "v": {"1": 7020, "0": 16892, "3": 67, "2": 142}, "nb": 0}, "9113": {"val": 2553, "part": 38.5, "v": {"0": 1778, "3": 7, "1": 757, "2": 11}, "nb": 0}, "9114": {"val": 8567, "part": 37.6, "v": {"0": 5566, "3": 10, "1": 2947, "2": 44}, "nb": 0}, "9115": {"val": 11375, "part": 41.5, "v": {"3": 23, "2": 36, "0": 8176, "1": 3140}, "nb": 0}, "9116": {"val": 4021, "part": 30.9, "v": {"0": 2960, "3": 27, "2": 34, "1": 1000}, "nb": 0}, "9117": {"val": 4819, "part": 34.4, "v": {"1": 1742, "2": 28, "3": 23, "0": 3026}, "nb": 0}, "9118": {"val": 3398, "part": 32.2, "v": {"0": 2126, "3": 29, "1": 1213, "2": 30}, "nb": 0}, "9119": {"val": 9119, "part": 38.0, "v": {"3": 56, "2": 70, "0": 5971, "1": 3022}, "nb": 0}, "9120": {"val": 21750, "part": 40.5, "v": {"0": 15087, "3": 40, "1": 6534, "2": 89}, "nb": 0}, "9121": {"val": 4218, "part": 40.6, "v": {"0": 2951, "3": 19, "1": 1197, "2": 51}, "nb": 0}, "9201": {"val": 19520, "part": 41.2, "v": {"1": 7349, "2": 97, "3": 57, "0": 12017}, "nb": 0}, "9202": {"val": 8340, "part": 37.9, "v": {"0": 5159, "3": 41, "1": 3075, "2": 65}, "nb": 0}, "9203": {"val": 5922, "part": 28.2, "v": {"0": 3491, "2": 33, "1": 2378, "3": 20}, "nb": 0}, "9204": {"val": 2593, "part": 32.2, "v": {"1": 1020, "0": 1521, "2": 26, "3": 26}, "nb": 0}, "9205": {"val": 3349, "part": 28.0, "v": {"0": 1963, "3": 26, "2": 42, "1": 1318}, "nb": 0}, "9206": {"val": 2495, "part": 33.9, "v": {"1": 1050, "2": 24, "3": 12, "0": 1409}, "nb": 0}, "9207": {"val": 2979, "part": 32.6, "v": {"2": 31, "1": 1206, "3": 31, "0": 1711}, "nb": 0}, "9208": {"val": 4289, "part": 35.2, "v": {"1": 1583, "2": 30, "3": 19, "0": 2657}, "nb": 0}, "9209": {"val": 3745, "part": 39.4, "v": {"2": 17, "1": 1080, "0": 2640, "3": 8}, "nb": 0}, "9210": {"val": 6402, "part": 34.3, "v": {"1": 2189, "0": 4144, "3": 35, "2": 34}, "nb": 0}, "9211": {"val": 12373, "part": 38.0, "v": {"2": 76, "1": 5193, "3": 44, "0": 7060}, "nb": 0}}, "local": {}}