{"meta": {"eleccion": "2021-05_gobernadores_1v", "label": "Gobernadores 1ª v.", "tipo": "Gobernadores", "has_local": false, "n_cand": 90}, "candidatos": [{"i": 0, "nombre": "CLAUDIO BENJAMIN ORREGO", "ape1": "ORREGO", "bloque": "Centro", "eje": 5.0, "vn": 658453}, {"i": 1, "nombre": "KARINA LORETTA OLIVA", "ape1": "OLIVA", "bloque": "Centro-izquierda", "eje": 2.8, "vn": 602537}, {"i": 2, "nombre": "NATHALIE PAULETTE JOIGNANT", "ape1": "JOIGNANT", "bloque": "Centro-izquierda", "eje": 3.0, "vn": 391741}, {"i": 3, "nombre": "MARIA CATALINA PAROT", "ape1": "PAROT", "bloque": "Centro-derecha", "eje": 6.8, "vn": 384171}, {"i": 4, "nombre": "RODRIGO EDUARDO ALEXIS MUNDACA", "ape1": "MUNDACA", "bloque": "Centro-izquierda", "eje": 2.82, "vn": 298702}, {"i": 5, "nombre": "PABLO ANTONIO ANDRES MALTES", "ape1": "MALTES", "bloque": "Izquierda", "eje": 2.0, "vn": 274639}, {"i": 6, "nombre": "JOSE MANUEL ROJO EDWARDS", "ape1": "EDWARDS", "bloque": "Derecha radical", "eje": 9.2, "vn": 171446}, {"i": 7, "nombre": "MANUEL JESUS MILLONES", "ape1": "MILLONES", "bloque": "Centro-derecha", "eje": 7.41, "vn": 162040}, {"i": 8, "nombre": "RODRIGO GONZALO DIAZ", "ape1": "DIAZ", "bloque": "Derecha radical", "eje": null, "vn": 139030}, {"i": 9, "nombre": "ALDO SALVADOR VALLE", "ape1": "VALLE", "bloque": "Centro", "eje": 4.67, "vn": 137027}, {"i": 10, "nombre": "PATRICIO IVAN VALLESPIN", "ape1": "VALLESPIN", "bloque": "Centro", "eje": 5.0, "vn": 100120}, {"i": 11, "nombre": "CRISTINA ANDREA BRAVO", "ape1": "BRAVO", "bloque": "Centro", "eje": 5.0, "vn": 98853}, {"i": 12, "nombre": "FLOR ISABEL WEISSE", "ape1": "WEISSE", "bloque": "Derecha", "eje": 8.3, "vn": 97451}, {"i": 13, "nombre": "EUGENIO TUMA", "ape1": "TUMA", "bloque": "Centro-izquierda", "eje": 4.2, "vn": 92341}, {"i": 14, "nombre": "JUAN FRANCISCO PULGAR", "ape1": "PULGAR", "bloque": "Derecha radical", "eje": null, "vn": 83692}, {"i": 15, "nombre": "PABLO MANUEL SILVA", "ape1": "SILVA", "bloque": "Centro-izquierda", "eje": 3.2, "vn": 80927}, {"i": 16, "nombre": "ANA DELIA ARANEDA", "ape1": "ARANEDA", "bloque": "Centro-izquierda", "eje": 3.0, "vn": 75565}, {"i": 17, "nombre": "EDUARDO ALEJANDRO CORNEJO", "ape1": "CORNEJO", "bloque": "Derecha", "eje": 8.3, "vn": 73695}, {"i": 18, "nombre": "ERIC MARIANO AEDO", "ape1": "AEDO", "bloque": "Centro", "eje": 5.0, "vn": 71902}, {"i": 19, "nombre": "RICARDO ALBERTO KUSCHEL", "ape1": "KUSCHEL", "bloque": "Centro-derecha", "eje": 7.3, "vn": 70718}, {"i": 20, "nombre": "ESTEBAN MANUEL VALENZUELA", "ape1": "VALENZUELA", "bloque": "Centro-izquierda", "eje": 3.5, "vn": 67887}, {"i": 21, "nombre": "RICARDO HERIBERTO DIAZ", "ape1": "DIAZ", "bloque": "Centro", "eje": 4.67, "vn": 66505}, {"i": 22, "nombre": "KRIST PIA NICOLE NARANJO", "ape1": "NARANJO", "bloque": "Centro-izquierda", "eje": 3.0, "vn": 65488}, {"i": 23, "nombre": "FRANKLIN ESTEBAN GALLARDO", "ape1": "GALLARDO", "bloque": "Centro-izquierda", "eje": 3.0, "vn": 63299}, {"i": 24, "nombre": "GEORGE RAPHAEL BORDACHAR", "ape1": "BORDACHAR", "bloque": "Centro-derecha", "eje": 7.3, "vn": 62971}, {"i": 25, "nombre": "MARCO ANTONIO SULANTAY", "ape1": "SULANTAY", "bloque": "Derecha", "eje": 8.3, "vn": 62609}, {"i": 26, "nombre": "RICARDO OSCAR CIFUENTES", "ape1": "CIFUENTES", "bloque": "Centro", "eje": 5.0, "vn": 60938}, {"i": 27, "nombre": "LUCIANO ALEJANDRO RIVAS", "ape1": "RIVAS", "bloque": "Centro-derecha", "eje": 7.41, "vn": 60634}, {"i": 28, "nombre": "RICARDO JAVIER MARTINEZ", "ape1": "MARTINEZ", "bloque": "Centro-izquierda", "eje": 3.5, "vn": 54300}, {"i": 29, "nombre": "JAVIER ANDRES VEGA", "ape1": "VEGA", "bloque": "Izquierda", "eje": 1.0, "vn": 50893}, {"i": 30, "nombre": "OSCAR MANUEL CRISOSTOMO", "ape1": "CRISOSTOMO", "bloque": "Centro-izquierda", "eje": 3.2, "vn": 50843}, {"i": 31, "nombre": "MARIA JOSE GATICA", "ape1": "GATICA", "bloque": "Centro-derecha", "eje": 7.3, "vn": 49742}, {"i": 32, "nombre": "LUIS ANTONIO LEVI", "ape1": "LEVI", "bloque": "Centro-izquierda", "eje": 3.0, "vn": 48884}, {"i": 33, "nombre": "TANIA VALENTINA CONCHA", "ape1": "CONCHA", "bloque": "Izquierda", "eje": 1.0, "vn": 47789}, {"i": 34, "nombre": "FRANCISCO JAVIER SANDOVAL", "ape1": "SANDOVAL", "bloque": "Izquierda", "eje": 1.5, "vn": 46882}, {"i": 35, "nombre": "RICARDO ENRIQUE RINCON", "ape1": "RINCON", "bloque": "Derecha radical", "eje": null, "vn": 46808}, {"i": 36, "nombre": "GABRIEL ANDRES ROJAS", "ape1": "ROJAS", "bloque": "Izquierda", "eje": 1.0, "vn": 46669}, {"i": 37, "nombre": "ALFONSO JAVIER BELMAR", "ape1": "BELMAR", "bloque": "Centro-izquierda", "eje": 3.0, "vn": 44683}, {"i": 38, "nombre": "LUIS ALFONSO CUVERTINO", "ape1": "CUVERTINO", "bloque": "Centro-izquierda", "eje": 3.2, "vn": 43927}, {"i": 39, "nombre": "JEZER SEPULVEDA", "ape1": "SEPULVEDA", "bloque": "Derecha", "eje": 8.3, "vn": 43857}, {"i": 40, "nombre": "MARCO LORENZO OYANEDEL", "ape1": "OYANEDEL", "bloque": "Izquierda", "eje": 1.5, "vn": 43461}, {"i": 41, "nombre": "FRESIA MONICA QUILODRAN", "ape1": "QUILODRAN", "bloque": "Izquierda", "eje": 1.5, "vn": 39526}, {"i": 42, "nombre": "MARCO ANTONIO DIAZ", "ape1": "DIAZ", "bloque": "Centro-derecha", "eje": 7.3, "vn": 36137}, {"i": 43, "nombre": "AUCAN HUILCAMAN", "ape1": "HUILCAMAN", "bloque": "Izquierda", "eje": 1.5, "vn": 35220}, {"i": 44, "nombre": "PAOLA ALEJANDRA VENEGAS", "ape1": "VENEGAS", "bloque": "Izquierda", "eje": 1.0, "vn": 32671}, {"i": 45, "nombre": "RICARDO MANUEL GEORGES", "ape1": "GEORGES", "bloque": "Izquierda", "eje": 2.0, "vn": 27816}, {"i": 46, "nombre": "CARLO FELIPE PEZO", "ape1": "PEZO", "bloque": "Centro", "eje": 4.67, "vn": 27669}, {"i": 47, "nombre": "PAULA VALERIA ORELLANA", "ape1": "ORELLANA", "bloque": "Centro-izquierda", "eje": 3.0, "vn": 27540}, {"i": 48, "nombre": "JAIME SALVADOR SAEZ", "ape1": "SAEZ", "bloque": "Centro-izquierda", "eje": 3.0, "vn": 26370}, {"i": 49, "nombre": "JUAN DAGOBERTO VALDEBENITO", "ape1": "VALDEBENITO", "bloque": "Derecha radical", "eje": 9.2, "vn": 26369}, {"i": 50, "nombre": "JOSE MIGUEL CARVAJAL", "ape1": "CARVAJAL", "bloque": "Centro-izquierda", "eje": 2.8, "vn": 26088}, {"i": 51, "nombre": "CESAR AUGUSTO VARGAS", "ape1": "VARGAS", "bloque": "Derecha radical", "eje": null, "vn": 25290}, {"i": 52, "nombre": "JORGE MAURICIO FLIES", "ape1": "FLIES", "bloque": "Centro", "eje": 4.67, "vn": 24768}, {"i": 53, "nombre": "MARCO ANTONIO PEREZ", "ape1": "PEREZ", "bloque": "Centro", "eje": 4.67, "vn": 23322}, {"i": 54, "nombre": "ENZO MANUEL MORALES", "ape1": "MORALES", "bloque": "Izquierda", "eje": 1.0, "vn": 22275}, {"i": 55, "nombre": "JOSE IGNACIO MARIN", "ape1": "MARIN", "bloque": "Centro-izquierda", "eje": 3.0, "vn": 22239}, {"i": 56, "nombre": "MIGUEL EDUARDO VARGAS", "ape1": "VARGAS", "bloque": "Derecha radical", "eje": null, "vn": 21702}, {"i": 57, "nombre": "LESTER PATRICIO CALDERON", "ape1": "CALDERON", "bloque": "Derecha radical", "eje": null, "vn": 21463}, {"i": 58, "nombre": "ENRIQUE SEGUNDO LEE", "ape1": "LEE", "bloque": "Centro-derecha", "eje": 7.41, "vn": 21126}, {"i": 59, "nombre": "JORGE ANDRES RAMON FISTONIC", "ape1": "FISTONIC", "bloque": "Derecha", "eje": 8.3, "vn": 19690}, {"i": 60, "nombre": "JORGE ELIAS GREGORIO DIAZ", "ape1": "DIAZ", "bloque": "Centro", "eje": 5.0, "vn": 18407}, {"i": 61, "nombre": "ANDREA JACQUELINE MACIAS", "ape1": "MACIAS", "bloque": "Centro-izquierda", "eje": 3.2, "vn": 18283}, {"i": 62, "nombre": "ORLANDO SEVERO VARGAS", "ape1": "VARGAS", "bloque": "Derecha radical", "eje": null, "vn": 17936}, {"i": 63, "nombre": "JULIO ANDRES BECERRA", "ape1": "BECERRA", "bloque": "Centro-izquierda", "eje": 3.0, "vn": 17851}, {"i": 64, "nombre": "ELIAS ISKANDA VICENTE SABAT", "ape1": "SABAT", "bloque": "Derecha radical", "eje": null, "vn": 17279}, {"i": 65, "nombre": "PEDRO ALEJANDRO NEIRA", "ape1": "NEIRA", "bloque": "Izquierda", "eje": 2.0, "vn": 17098}, {"i": 66, "nombre": "JAVIER ANIBAL CASTILLO", "ape1": "CASTILLO", "bloque": "Izquierda", "eje": 1.0, "vn": 16889}, {"i": 67, "nombre": "MANUEL ARNOLDO AMESTICA", "ape1": "AMESTICA", "bloque": "Centro-izquierda", "eje": 3.5, "vn": 16607}, {"i": 68, "nombre": "RENE ROBERTO RUBESKA", "ape1": "RUBESKA", "bloque": "Derecha radical", "eje": null, "vn": 16396}, {"i": 69, "nombre": "CLAUDIO ANDRES LAGOS", "ape1": "LAGOS", "bloque": "Centro-izquierda", "eje": 3.5, "vn": 16244}, {"i": 70, "nombre": "PAOLA XIMENA PEÑA", "ape1": "PEÑA", "bloque": "Izquierda", "eje": 1.0, "vn": 15199}, {"i": 71, "nombre": "VICENTE ALEJANDRO PAINEL", "ape1": "PAINEL", "bloque": "Centro-izquierda", "eje": 3.5, "vn": 14693}, {"i": 72, "nombre": "LUIS HUMBERTO ARAVENA", "ape1": "ARAVENA", "bloque": "Izquierda", "eje": 1.5, "vn": 14172}, {"i": 73, "nombre": "IVAN ATILIO SEPULVEDA", "ape1": "SEPULVEDA", "bloque": "Izquierda", "eje": 2.0, "vn": 14121}, {"i": 74, "nombre": "MARCO ANTONIO MATURANA", "ape1": "MATURANA", "bloque": "Centro-izquierda", "eje": 3.5, "vn": 13610}, {"i": 75, "nombre": "CHRISTIAN EDUARDO MATHESON", "ape1": "MATHESON", "bloque": "Derecha radical", "eje": null, "vn": 13118}, {"i": 76, "nombre": "RAUL EDUARDO RUDOLPHI", "ape1": "RUDOLPHI", "bloque": "Centro-derecha", "eje": 7.3, "vn": 12860}, {"i": 77, "nombre": "FERNANDO ALFONSO GHIGLINO", "ape1": "GHIGLINO", "bloque": "Centro-derecha", "eje": 7.3, "vn": 11672}, {"i": 78, "nombre": "LUIS FERNANDO VIVANCO", "ape1": "VIVANCO", "bloque": "Izquierda", "eje": 2.0, "vn": 10683}, {"i": 79, "nombre": "GUILLERMO EDGARDO RIVEROS", "ape1": "RIVEROS", "bloque": "Izquierda", "eje": 1.5, "vn": 9806}, {"i": 80, "nombre": "JOSE ANTONIO VIDELA", "ape1": "VIDELA", "bloque": "Derecha radical", "eje": 9.2, "vn": 9623}, {"i": 81, "nombre": "LUZ CELENA SOTO", "ape1": "SOTO", "bloque": "Izquierda", "eje": 2.0, "vn": 8788}, {"i": 82, "nombre": "JUAN JOSE CLAUDIO ARCOS", "ape1": "ARCOS", "bloque": "Centro-derecha", "eje": 7.41, "vn": 8689}, {"i": 83, "nombre": "GASTON ALFREDO FLORES", "ape1": "FLORES", "bloque": "Izquierda", "eje": 1.5, "vn": 7996}, {"i": 84, "nombre": "OSCAR EDUARDO FERNANDEZ", "ape1": "FERNANDEZ", "bloque": "Derecha radical", "eje": null, "vn": 7780}, {"i": 85, "nombre": "CLAUDIO ALEJANDRO FLORES", "ape1": "FLORES", "bloque": "Izquierda", "eje": 2.0, "vn": 7133}, {"i": 86, "nombre": "ROBERTO PATRIZIO QUINTANA", "ape1": "QUINTANA", "bloque": "Derecha radical", "eje": null, "vn": 6413}, {"i": 87, "nombre": "JORGE FELIPE SEPULVEDA", "ape1": "SEPULVEDA", "bloque": "Derecha radical", "eje": null, "vn": 6381}, {"i": 88, "nombre": "MANUEL JOSE CORREA", "ape1": "CORREA", "bloque": "Derecha radical", "eje": null, "vn": 5063}, {"i": 89, "nombre": "JUAN FRANCISCO MERUVIA", "ape1": "MERUVIA", "bloque": "Derecha radical", "eje": null, "vn": 3208}], "comuna": {"10101": {"val": 70479, "part": 39.5, "v": {"48": 7367, "37": 12394, "10": 26284, "19": 16725, "44": 7709}, "nb": 3213}, "10102": {"val": 11257, "part": 40.4, "v": {"48": 1257, "37": 1766, "10": 4520, "44": 1475, "19": 2239}, "nb": 1821}, "10103": {"val": 1732, "part": 45.6, "v": {"19": 541, "48": 191, "37": 187, "10": 683, "44": 130}, "nb": 383}, "10104": {"val": 4937, "part": 47.0, "v": {"44": 336, "48": 575, "37": 412, "10": 2026, "19": 1588}, "nb": 811}, "10105": {"val": 7518, "part": 47.5, "v": {"19": 3548, "48": 392, "37": 694, "10": 2295, "44": 589}, "nb": 449}, "10106": {"val": 5414, "part": 41.5, "v": {"44": 471, "19": 2003, "48": 301, "37": 640, "10": 1999}, "nb": 1370}, "10107": {"val": 6524, "part": 45.2, "v": {"48": 737, "37": 968, "10": 2627, "19": 1383, "44": 809}, "nb": 795}, "10108": {"val": 5824, "part": 43.6, "v": {"44": 359, "48": 507, "37": 585, "10": 2797, "19": 1576}, "nb": 902}, "10109": {"val": 19082, "part": 47.8, "v": {"19": 7244, "44": 1764, "48": 1803, "37": 3495, "10": 4776}, "nb": 1132}, "10201": {"val": 13423, "part": 37.3, "v": {"48": 1365, "37": 2914, "10": 3934, "19": 2666, "44": 2544}, "nb": 2008}, "10202": {"val": 13551, "part": 40.1, "v": {"19": 2816, "48": 1171, "37": 2343, "10": 4963, "44": 2258}, "nb": 2017}, "10203": {"val": 5219, "part": 49.6, "v": {"44": 767, "19": 1287, "48": 433, "37": 806, "10": 1926}, "nb": 1317}, "10204": {"val": 1651, "part": 63.8, "v": {"48": 138, "37": 219, "10": 793, "44": 179, "19": 322}, "nb": 771}, "10205": {"val": 4534, "part": 45.2, "v": {"48": 399, "37": 752, "10": 1675, "19": 1014, "44": 694}, "nb": 1156}, "10206": {"val": 1672, "part": 55.9, "v": {"19": 286, "44": 246, "48": 140, "37": 261, "10": 739}, "nb": 810}, "10207": {"val": 2691, "part": 56.0, "v": {"44": 281, "48": 153, "37": 260, "10": 1467, "19": 530}, "nb": 850}, "10208": {"val": 7269, "part": 38.0, "v": {"19": 1381, "48": 631, "37": 1274, "10": 2714, "44": 1269}, "nb": 1406}, "10209": {"val": 3148, "part": 46.1, "v": {"44": 258, "19": 736, "48": 247, "37": 408, "10": 1499}, "nb": 1028}, "10210": {"val": 3271, "part": 44.9, "v": {"48": 334, "37": 386, "10": 1542, "44": 389, "19": 620}, "nb": 958}, "10301": {"val": 48810, "part": 35.8, "v": {"48": 5234, "37": 9619, "10": 14735, "19": 12511, "44": 6711}, "nb": 2499}, "10302": {"val": 3535, "part": 45.2, "v": {"48": 261, "37": 329, "10": 1617, "44": 357, "19": 971}, "nb": 542}, "10303": {"val": 6973, "part": 38.8, "v": {"48": 530, "37": 762, "10": 3027, "19": 2096, "44": 558}, "nb": 745}, "10304": {"val": 4879, "part": 49.0, "v": {"19": 1193, "44": 560, "48": 349, "37": 592, "10": 2185}, "nb": 807}, "10305": {"val": 5473, "part": 45.9, "v": {"48": 347, "37": 614, "10": 2285, "19": 1736, "44": 491}, "nb": 700}, "10306": {"val": 3615, "part": 48.4, "v": {"19": 435, "48": 507, "37": 420, "10": 1960, "44": 293}, "nb": 353}, "10307": {"val": 4348, "part": 49.7, "v": {"44": 469, "19": 1067, "48": 359, "37": 528, "10": 1925}, "nb": 714}, "10401": {"val": 1903, "part": 47.4, "v": {"44": 140, "19": 517, "48": 154, "37": 194, "10": 898}, "nb": 549}, "10402": {"val": 1315, "part": 42.6, "v": {"48": 126, "37": 213, "10": 395, "44": 75, "19": 506}, "nb": 329}, "10403": {"val": 3668, "part": 52.0, "v": {"48": 281, "37": 571, "10": 1512, "19": 873, "44": 431}, "nb": 848}, "10404": {"val": 847, "part": 52.0, "v": {"19": 308, "48": 81, "37": 77, "10": 322, "44": 59}, "nb": 382}, "1101": {"val": 59600, "part": 37.2, "v": {"50": 13921, "59": 13410, "54": 15222, "53": 17047}, "nb": 2649}, "1107": {"val": 17970, "part": 32.6, "v": {"50": 5108, "59": 2957, "54": 5196, "53": 4709}, "nb": 1161}, "11101": {"val": 18953, "part": 36.3, "v": {"87": 2733, "61": 10188, "76": 6032}, "nb": 752}, "11102": {"val": 729, "part": 68.1, "v": {"76": 304, "87": 84, "61": 341}, "nb": 176}, "11201": {"val": 8760, "part": 41.9, "v": {"61": 3738, "76": 2895, "87": 2127}, "nb": 709}, "11202": {"val": 2167, "part": 55.0, "v": {"61": 954, "87": 309, "76": 904}, "nb": 347}, "11203": {"val": 760, "part": 56.8, "v": {"76": 221, "87": 216, "61": 323}, "nb": 230}, "11301": {"val": 1735, "part": 55.9, "v": {"61": 780, "76": 795, "87": 160}, "nb": 158}, "11302": {"val": 404, "part": 61.7, "v": {"76": 196, "61": 168, "87": 40}, "nb": 84}, "11303": {"val": 347, "part": 73.3, "v": {"87": 48, "61": 186, "76": 113}, "nb": 92}, "11401": {"val": 2274, "part": 41.6, "v": {"87": 542, "76": 728, "61": 1004}, "nb": 409}, "11402": {"val": 1395, "part": 55.8, "v": {"87": 122, "61": 601, "76": 672}, "nb": 232}, "12101": {"val": 45161, "part": 38.7, "v": {"82": 5376, "75": 10835, "85": 5610, "52": 19273, "88": 4067}, "nb": 2228}, "12102": {"val": 409, "part": 53.9, "v": {"85": 44, "88": 34, "82": 65, "75": 131, "52": 135}, "nb": 52}, "12103": {"val": 426, "part": 56.2, "v": {"82": 70, "75": 152, "85": 53, "52": 107, "88": 44}, "nb": 70}, "12104": {"val": 330, "part": 40.3, "v": {"88": 19, "52": 119, "85": 36, "82": 69, "75": 87}, "nb": 61}, "12201": {"val": 786, "part": 45.2, "v": {"82": 307, "75": 78, "52": 232, "85": 133, "88": 36}, "nb": 91}, "12202": {"val": 4, "part": 1.6, "v": {"82": 1, "75": 0, "85": 1, "52": 1, "88": 1}, "nb": 0}, "12301": {"val": 2234, "part": 40.0, "v": {"88": 106, "52": 815, "82": 843, "75": 266, "85": 204}, "nb": 227}, "12302": {"val": 490, "part": 41.8, "v": {"88": 43, "52": 212, "85": 57, "82": 86, "75": 92}, "nb": 70}, "12303": {"val": 312, "part": 43.9, "v": {"82": 92, "75": 75, "85": 23, "52": 76, "88": 46}, "nb": 38}, "12401": {"val": 7675, "part": 38.4, "v": {"88": 604, "82": 1537, "75": 1188, "85": 889, "52": 3457}, "nb": 1049}, "12402": {"val": 944, "part": 67.4, "v": {"85": 83, "52": 341, "82": 243, "75": 214, "88": 63}, "nb": 196}, "13101": {"val": 116863, "part": 35.1, "v": {"5": 10060, "28": 1606, "3": 15772, "1": 36912, "0": 27362, "41": 1716, "6": 7740, "2": 15695}, "nb": 2664}, "13102": {"val": 28081, "part": 43.3, "v": {"5": 3906, "28": 752, "3": 3184, "1": 6369, "0": 6568, "41": 537, "6": 1378, "2": 5387}, "nb": 1188}, "13103": {"val": 43041, "part": 39.0, "v": {"28": 1104, "1": 14395, "3": 3248, "5": 6764, "0": 8275, "41": 879, "6": 1432, "2": 6944}, "nb": 2011}, "13104": {"val": 47025, "part": 41.1, "v": {"0": 12074, "41": 913, "1": 10867, "3": 3889, "5": 7675, "6": 2025, "2": 8434, "28": 1148}, "nb": 1761}, "13105": {"val": 51356, "part": 38.7, "v": {"5": 7004, "1": 11469, "0": 12891, "41": 1184, "6": 2428, "2": 9659, "28": 1610, "3": 5111}, "nb": 1924}, "13106": {"val": 46763, "part": 38.1, "v": {"0": 11504, "41": 737, "5": 5496, "1": 14282, "3": 4707, "28": 954, "6": 2163, "2": 6920}, "nb": 1728}, "13107": {"val": 35809, "part": 50.6, "v": {"0": 10705, "41": 582, "5": 3973, "1": 7743, "3": 4806, "28": 709, "6": 2131, "2": 5160}, "nb": 1417}, "13108": {"val": 30020, "part": 37.9, "v": {"5": 3499, "1": 7673, "0": 7757, "41": 488, "6": 1633, "2": 4522, "28": 590, "3": 3858}, "nb": 1268}, "13109": {"val": 34640, "part": 42.8, "v": {"28": 831, "1": 8172, "3": 4040, "5": 3544, "0": 9205, "41": 588, "6": 1912, "2": 6348}, "nb": 1009}, "13110": {"val": 150605, "part": 50.7, "v": {"1": 38516, "28": 2974, "5": 15427, "6": 7719, "2": 24979, "0": 39239, "41": 2330, "3": 19421}, "nb": 5172}, "13111": {"val": 41541, "part": 41.5, "v": {"0": 12671, "41": 968, "1": 9475, "3": 2686, "5": 6489, "6": 1504, "2": 6848, "28": 900}, "nb": 1587}, "13112": {"val": 48463, "part": 36.5, "v": {"5": 9658, "28": 1412, "3": 3001, "1": 10424, "0": 12538, "41": 953, "6": 1577, "2": 8900}, "nb": 2338}, "13113": {"val": 52230, "part": 58.1, "v": {"1": 10217, "28": 437, "5": 2087, "6": 5207, "2": 4813, "0": 16994, "41": 382, "3": 12093}, "nb": 954}, "13114": {"val": 148418, "part": 55.8, "v": {"28": 761, "6": 26898, "2": 8420, "0": 34476, "41": 524, "3": 60685, "1": 13883, "5": 2771}, "nb": 1910}, "13115": {"val": 49104, "part": 60.4, "v": {"6": 9157, "2": 2268, "0": 7423, "41": 168, "28": 341, "1": 3708, "3": 24661, "5": 1378}, "nb": 800}, "13116": {"val": 35498, "part": 40.9, "v": {"0": 8359, "41": 799, "28": 1086, "5": 6213, "6": 1226, "2": 6453, "1": 8852, "3": 2510}, "nb": 1680}, "13117": {"val": 35347, "part": 41.3, "v": {"28": 792, "6": 1273, "2": 5764, "0": 9807, "41": 671, "3": 2781, "1": 8762, "5": 5497}, "nb": 1389}, "13118": {"val": 47775, "part": 48.4, "v": {"28": 888, "1": 13066, "3": 4715, "5": 4672, "0": 13990, "41": 679, "6": 2758, "2": 7007}, "nb": 1266}, "13119": {"val": 189813, "part": 49.9, "v": {"6": 8736, "2": 36328, "3": 18007, "1": 55261, "5": 21381, "0": 41697, "41": 3410, "28": 4993}, "nb": 4778}, "13120": {"val": 109030, "part": 56.2, "v": {"3": 17752, "28": 947, "0": 30334, "41": 1115, "6": 7722, "2": 11612, "5": 5812, "1": 33736}, "nb": 1703}, "13121": {"val": 39839, "part": 44.4, "v": {"28": 1001, "1": 10928, "3": 2798, "5": 6552, "0": 9618, "41": 745, "6": 1395, "2": 6802}, "nb": 1503}, "13122": {"val": 86983, "part": 46.5, "v": {"5": 9402, "28": 1220, "3": 7807, "1": 18066, "0": 35628, "41": 1217, "6": 3589, "2": 10054}, "nb": 2148}, "13123": {"val": 85496, "part": 50.9, "v": {"0": 24521, "41": 418, "6": 9119, "2": 7169, "5": 2427, "28": 601, "3": 21891, "1": 19350}, "nb": 1158}, "13124": {"val": 70476, "part": 43.2, "v": {"0": 15061, "41": 1562, "6": 2678, "2": 14459, "5": 11077, "28": 2057, "3": 5269, "1": 18313}, "nb": 2445}, "13125": {"val": 63645, "part": 47.3, "v": {"1": 15939, "28": 1898, "5": 9949, "6": 2738, "2": 13893, "0": 13223, "41": 1255, "3": 4750}, "nb": 2517}, "13126": {"val": 40879, "part": 41.2, "v": {"6": 1923, "2": 6304, "5": 5551, "1": 11578, "3": 3879, "0": 9993, "41": 722, "28": 929}, "nb": 1352}, "13127": {"val": 55047, "part": 40.0, "v": {"5": 7017, "28": 1126, "3": 5743, "1": 16480, "0": 11949, "41": 1038, "6": 3227, "2": 8467}, "nb": 2095}, "13128": {"val": 46142, "part": 41.2, "v": {"0": 13778, "41": 940, "1": 11327, "3": 2768, "5": 6745, "6": 1498, "2": 7941, "28": 1145}, "nb": 1963}, "13129": {"val": 35225, "part": 44.1, "v": {"28": 800, "1": 10258, "3": 2571, "5": 4968, "0": 8919, "41": 838, "6": 1356, "2": 5515}, "nb": 1115}, "13130": {"val": 45913, "part": 44.7, "v": {"28": 826, "6": 2765, "2": 7031, "0": 11410, "41": 666, "3": 5339, "1": 13603, "5": 4273}, "nb": 1088}, "13131": {"val": 33786, "part": 43.7, "v": {"0": 9416, "41": 879, "6": 1432, "2": 5489, "5": 5540, "28": 985, "3": 2847, "1": 7198}, "nb": 1946}, "13132": {"val": 56161, "part": 63.4, "v": {"5": 384, "1": 2938, "0": 11456, "41": 72, "6": 10580, "2": 1794, "28": 154, "3": 28783}, "nb": 504}, "13201": {"val": 168602, "part": 43.5, "v": {"0": 36943, "41": 3126, "6": 6562, "2": 33971, "5": 22180, "28": 4634, "3": 14652, "1": 46534}, "nb": 5449}, "13202": {"val": 11795, "part": 54.2, "v": {"0": 3933, "41": 130, "6": 1006, "2": 1705, "5": 870, "28": 284, "3": 1907, "1": 1960}, "nb": 481}, "13203": {"val": 7984, "part": 54.1, "v": {"3": 1061, "1": 1844, "28": 178, "6": 403, "2": 1542, "5": 693, "0": 2152, "41": 111}, "nb": 586}, "13301": {"val": 40356, "part": 46.6, "v": {"5": 3657, "3": 10695, "1": 4828, "6": 4402, "2": 5098, "28": 888, "0": 10223, "41": 565}, "nb": 1750}, "13302": {"val": 26626, "part": 47.0, "v": {"28": 793, "1": 5244, "3": 3381, "5": 3214, "0": 6921, "41": 464, "6": 1435, "2": 5174}, "nb": 1372}, "13303": {"val": 6511, "part": 47.5, "v": {"3": 995, "1": 1914, "28": 202, "6": 389, "2": 968, "5": 938, "0": 940, "41": 165}, "nb": 553}, "13401": {"val": 81430, "part": 37.1, "v": {"5": 11906, "1": 18171, "0": 18534, "41": 1569, "6": 4110, "2": 15979, "28": 3003, "3": 8158}, "nb": 3262}, "13402": {"val": 33121, "part": 46.3, "v": {"0": 8447, "41": 416, "5": 3181, "1": 5448, "3": 5091, "28": 937, "6": 2411, "2": 7190}, "nb": 1725}, "13403": {"val": 11018, "part": 52.7, "v": {"6": 906, "2": 1495, "3": 2367, "1": 1954, "5": 1027, "0": 2885, "41": 146, "28": 238}, "nb": 735}, "13404": {"val": 21428, "part": 42.4, "v": {"28": 703, "1": 3868, "3": 3155, "5": 2040, "0": 6214, "41": 325, "6": 1471, "2": 3652}, "nb": 1357}, "13501": {"val": 32689, "part": 35.3, "v": {"0": 10445, "41": 366, "28": 1010, "5": 3071, "6": 2128, "2": 4436, "1": 6767, "3": 4466}, "nb": 1619}, "13502": {"val": 3087, "part": 56.5, "v": {"0": 1784, "41": 27, "28": 45, "5": 220, "6": 80, "2": 305, "1": 380, "3": 246}, "nb": 391}, "13503": {"val": 12578, "part": 52.1, "v": {"28": 422, "1": 2329, "3": 2012, "5": 1370, "0": 3704, "41": 198, "6": 774, "2": 1769}, "nb": 1141}, "13504": {"val": 5165, "part": 49.5, "v": {"28": 141, "6": 292, "2": 734, "0": 1716, "41": 63, "3": 900, "1": 798, "5": 521}, "nb": 523}, "13505": {"val": 3709, "part": 51.5, "v": {"28": 91, "1": 414, "3": 606, "5": 283, "0": 1747, "41": 44, "6": 240, "2": 284}, "nb": 662}, "13601": {"val": 26654, "part": 48.5, "v": {"28": 686, "1": 4581, "3": 3381, "5": 2842, "0": 8404, "41": 481, "6": 1718, "2": 4561}, "nb": 1549}, "13602": {"val": 12695, "part": 50.3, "v": {"5": 1422, "1": 2019, "0": 4177, "41": 221, "6": 676, "2": 2229, "28": 394, "3": 1557}, "nb": 1302}, "13603": {"val": 12992, "part": 49.5, "v": {"6": 727, "2": 2069, "3": 1827, "1": 2260, "5": 1231, "0": 4351, "41": 176, "28": 351}, "nb": 858}, "13604": {"val": 21700, "part": 50.9, "v": {"5": 2833, "3": 2312, "1": 4322, "6": 1012, "2": 4610, "28": 658, "0": 5539, "41": 414}, "nb": 1041}, "13605": {"val": 35659, "part": 52.0, "v": {"3": 4030, "1": 7142, "28": 1065, "6": 1785, "2": 6591, "5": 3949, "0": 10553, "41": 544}, "nb": 2068}, "1401": {"val": 5220, "part": 46.2, "v": {"50": 3433, "59": 660, "54": 626, "53": 501}, "nb": 281}, "1402": {"val": 1271, "part": 53.6, "v": {"53": 151, "59": 444, "54": 216, "50": 460}, "nb": 231}, "1403": {"val": 1574, "part": 52.4, "v": {"53": 228, "50": 558, "59": 543, "54": 245}, "nb": 239}, "1404": {"val": 2463, "part": 28.0, "v": {"59": 700, "54": 276, "50": 1102, "53": 385}, "nb": 162}, "1405": {"val": 3277, "part": 61.0, "v": {"53": 301, "59": 976, "54": 494, "50": 1506}, "nb": 248}, "14101": {"val": 57521, "part": 43.2, "v": {"64": 4714, "31": 18489, "81": 4995, "38": 20362, "70": 8961}, "nb": 2360}, "14102": {"val": 2809, "part": 58.5, "v": {"81": 238, "64": 542, "38": 984, "31": 772, "70": 273}, "nb": 447}, "14103": {"val": 6585, "part": 42.2, "v": {"64": 413, "70": 187, "38": 4015, "31": 1795, "81": 175}, "nb": 278}, "14104": {"val": 6814, "part": 38.6, "v": {"81": 308, "70": 874, "31": 2846, "38": 1717, "64": 1069}, "nb": 547}, "14105": {"val": 3301, "part": 50.3, "v": {"31": 1488, "38": 1042, "70": 222, "64": 355, "81": 194}, "nb": 300}, "14106": {"val": 7616, "part": 44.2, "v": {"64": 649, "31": 3163, "81": 317, "38": 3040, "70": 447}, "nb": 777}, "14107": {"val": 7566, "part": 43.8, "v": {"70": 882, "64": 949, "81": 441, "38": 1938, "31": 3356}, "nb": 862}, "14108": {"val": 11245, "part": 34.7, "v": {"38": 2198, "31": 3349, "70": 879, "81": 472, "64": 4347}, "nb": 965}, "14201": {"val": 12684, "part": 38.1, "v": {"70": 947, "81": 558, "64": 1453, "31": 5914, "38": 3812}, "nb": 935}, "14202": {"val": 5343, "part": 40.9, "v": {"64": 775, "70": 460, "38": 1394, "31": 2435, "81": 279}, "nb": 646}, "14203": {"val": 3562, "part": 42.7, "v": {"64": 592, "70": 271, "38": 776, "31": 1671, "81": 252}, "nb": 473}, "14204": {"val": 9889, "part": 34.8, "v": {"70": 796, "81": 559, "64": 1421, "31": 4464, "38": 2649}, "nb": 832}, "15101": {"val": 62645, "part": 36.5, "v": {"62": 17018, "89": 3071, "86": 6201, "58": 19670, "60": 16685}, "nb": 2989}, "15102": {"val": 1629, "part": 52.1, "v": {"58": 377, "60": 817, "86": 56, "62": 326, "89": 53}, "nb": 137}, "15201": {"val": 2130, "part": 38.0, "v": {"86": 132, "58": 890, "60": 619, "62": 422, "89": 67}, "nb": 173}, "15202": {"val": 686, "part": 37.5, "v": {"86": 24, "58": 189, "60": 286, "62": 170, "89": 17}, "nb": 67}, "16101": {"val": 52746, "part": 36.0, "v": {"79": 2762, "84": 1608, "55": 8860, "80": 2407, "63": 7223, "30": 15666, "39": 14220}, "nb": 2277}, "16102": {"val": 8003, "part": 44.1, "v": {"30": 2597, "39": 1785, "80": 392, "63": 708, "79": 602, "84": 980, "55": 939}, "nb": 1047}, "16103": {"val": 9182, "part": 44.6, "v": {"80": 645, "63": 1180, "55": 1388, "79": 557, "84": 439, "30": 3028, "39": 1945}, "nb": 826}, "16104": {"val": 5731, "part": 53.8, "v": {"79": 278, "84": 229, "39": 2066, "30": 1914, "55": 650, "80": 267, "63": 327}, "nb": 988}, "16105": {"val": 3814, "part": 53.6, "v": {"55": 335, "79": 176, "84": 196, "39": 1130, "80": 202, "63": 230, "30": 1545}, "nb": 663}, "16106": {"val": 4531, "part": 50.6, "v": {"79": 290, "84": 224, "39": 1603, "30": 964, "55": 697, "80": 303, "63": 450}, "nb": 1198}, "16107": {"val": 5399, "part": 41.5, "v": {"55": 563, "79": 451, "84": 378, "39": 1168, "80": 426, "63": 626, "30": 1787}, "nb": 1108}, "16108": {"val": 5236, "part": 41.7, "v": {"30": 1430, "55": 815, "79": 364, "84": 320, "80": 317, "63": 543, "39": 1447}, "nb": 865}, "16109": {"val": 6217, "part": 43.8, "v": {"79": 434, "84": 339, "80": 388, "63": 726, "39": 1314, "55": 850, "30": 2166}, "nb": 935}, "16201": {"val": 5085, "part": 53.5, "v": {"30": 1687, "80": 186, "63": 339, "55": 513, "39": 1950, "79": 236, "84": 174}, "nb": 804}, "16202": {"val": 3246, "part": 69.0, "v": {"55": 257, "30": 862, "79": 143, "84": 95, "80": 126, "63": 291, "39": 1472}, "nb": 812}, "16203": {"val": 7353, "part": 56.5, "v": {"79": 551, "84": 436, "80": 431, "63": 686, "39": 1554, "55": 662, "30": 3033}, "nb": 1352}, "16204": {"val": 3302, "part": 63.9, "v": {"30": 1194, "80": 112, "63": 196, "55": 736, "39": 815, "79": 130, "84": 119}, "nb": 742}, "16205": {"val": 2567, "part": 52.8, "v": {"30": 697, "80": 105, "63": 162, "55": 268, "39": 1105, "79": 124, "84": 106}, "nb": 520}, "16206": {"val": 3034, "part": 64.3, "v": {"79": 191, "84": 176, "39": 798, "30": 1093, "55": 351, "80": 164, "63": 261}, "nb": 708}, "16207": {"val": 3475, "part": 68.3, "v": {"55": 283, "79": 234, "84": 268, "39": 733, "80": 204, "63": 330, "30": 1423}, "nb": 912}, "16301": {"val": 14014, "part": 32.7, "v": {"30": 4702, "80": 1426, "63": 1673, "55": 1709, "39": 2970, "79": 907, "84": 627}, "nb": 1596}, "16302": {"val": 7325, "part": 39.0, "v": {"30": 1634, "55": 848, "79": 582, "84": 407, "80": 497, "63": 677, "39": 2680}, "nb": 1319}, "16303": {"val": 3898, "part": 44.4, "v": {"30": 948, "55": 437, "79": 279, "84": 233, "80": 377, "63": 324, "39": 1300}, "nb": 827}, "16304": {"val": 2489, "part": 61.1, "v": {"30": 910, "39": 559, "79": 153, "84": 110, "80": 222, "63": 274, "55": 261}, "nb": 632}, "16305": {"val": 5352, "part": 54.7, "v": {"30": 1563, "39": 1243, "79": 362, "84": 316, "80": 426, "63": 625, "55": 817}, "nb": 1063}, "2101": {"val": 101186, "part": 36.7, "v": {"69": 6968, "57": 13670, "42": 22474, "47": 17278, "21": 40796}, "nb": 4050}, "2102": {"val": 4723, "part": 52.8, "v": {"57": 768, "42": 905, "47": 698, "21": 2090, "69": 262}, "nb": 578}, "2103": {"val": 1090, "part": 38.2, "v": {"57": 100, "42": 349, "47": 135, "21": 454, "69": 52}, "nb": 194}, "2104": {"val": 4339, "part": 47.8, "v": {"69": 457, "42": 986, "21": 1651, "57": 503, "47": 742}, "nb": 690}, "2201": {"val": 43357, "part": 34.6, "v": {"42": 8380, "57": 4668, "21": 16484, "69": 7459, "47": 6366}, "nb": 2487}, "2202": {"val": 693, "part": 46.8, "v": {"69": 91, "21": 212, "47": 113, "57": 45, "42": 232}, "nb": 100}, "2203": {"val": 3399, "part": 53.5, "v": {"47": 617, "57": 347, "69": 428, "21": 1281, "42": 726}, "nb": 450}, "2301": {"val": 7277, "part": 37.8, "v": {"47": 1229, "57": 1073, "69": 405, "21": 2860, "42": 1710}, "nb": 1170}, "2302": {"val": 1825, "part": 34.1, "v": {"69": 122, "42": 375, "21": 677, "57": 289, "47": 362}, "nb": 348}, "3101": {"val": 43520, "part": 36.2, "v": {"66": 9272, "46": 9058, "74": 8685, "77": 5932, "56": 10573}, "nb": 1343}, "3102": {"val": 6885, "part": 48.8, "v": {"66": 753, "46": 2122, "74": 728, "77": 875, "56": 2407}, "nb": 446}, "3103": {"val": 5574, "part": 47.4, "v": {"74": 526, "77": 717, "56": 1188, "66": 1536, "46": 1607}, "nb": 486}, "3201": {"val": 4899, "part": 45.1, "v": {"46": 1563, "66": 715, "74": 529, "77": 514, "56": 1578}, "nb": 535}, "3202": {"val": 4853, "part": 39.1, "v": {"66": 1425, "74": 440, "77": 545, "56": 787, "46": 1656}, "nb": 380}, "3301": {"val": 16644, "part": 39.3, "v": {"77": 1850, "56": 3175, "74": 1921, "46": 7732, "66": 1966}, "nb": 1233}, "3302": {"val": 2426, "part": 55.7, "v": {"46": 1046, "66": 272, "77": 442, "56": 407, "74": 259}, "nb": 474}, "3303": {"val": 2789, "part": 52.6, "v": {"74": 195, "77": 349, "56": 795, "46": 1005, "66": 445}, "nb": 374}, "3304": {"val": 3952, "part": 53.7, "v": {"77": 448, "56": 792, "74": 327, "46": 1880, "66": 505}, "nb": 563}, "4101": {"val": 68336, "part": 40.2, "v": {"26": 15808, "25": 16424, "22": 20673, "29": 15431}, "nb": 1892}, "4102": {"val": 62483, "part": 38.6, "v": {"26": 11857, "22": 20423, "29": 13219, "25": 16984}, "nb": 2271}, "4103": {"val": 5572, "part": 54.0, "v": {"22": 1231, "29": 1646, "26": 1368, "25": 1327}, "nb": 526}, "4104": {"val": 2185, "part": 56.3, "v": {"25": 854, "26": 403, "22": 279, "29": 649}, "nb": 353}, "4105": {"val": 3064, "part": 61.4, "v": {"22": 696, "29": 353, "26": 778, "25": 1237}, "nb": 243}, "4106": {"val": 11237, "part": 50.5, "v": {"25": 3258, "22": 2072, "29": 1111, "26": 4796}, "nb": 722}, "4201": {"val": 12249, "part": 47.4, "v": {"25": 2481, "22": 2414, "29": 2546, "26": 4808}, "nb": 989}, "4202": {"val": 4759, "part": 59.2, "v": {"22": 752, "29": 1688, "25": 1180, "26": 1139}, "nb": 598}, "4203": {"val": 7326, "part": 44.0, "v": {"25": 1593, "22": 2203, "29": 1710, "26": 1820}, "nb": 711}, "4204": {"val": 9287, "part": 43.9, "v": {"22": 2147, "29": 2017, "25": 2671, "26": 2452}, "nb": 994}, "4301": {"val": 31033, "part": 35.6, "v": {"26": 8097, "22": 7766, "29": 6281, "25": 8889}, "nb": 1654}, "4302": {"val": 4984, "part": 44.4, "v": {"25": 1160, "26": 1775, "22": 910, "29": 1139}, "nb": 587}, "4303": {"val": 10789, "part": 42.6, "v": {"25": 2741, "26": 3716, "22": 2482, "29": 1850}, "nb": 1147}, "4304": {"val": 4394, "part": 46.3, "v": {"22": 992, "29": 988, "26": 1367, "25": 1047}, "nb": 589}, "4305": {"val": 2230, "part": 51.6, "v": {"25": 763, "22": 448, "29": 265, "26": 754}, "nb": 318}, "5101": {"val": 112896, "part": 40.2, "v": {"9": 21991, "4": 58095, "45": 3412, "7": 22496, "72": 2028, "40": 4874}, "nb": 3757}, "5102": {"val": 9863, "part": 48.9, "v": {"72": 198, "40": 720, "45": 440, "4": 4025, "7": 2617, "9": 1863}, "nb": 1118}, "5103": {"val": 21587, "part": 57.3, "v": {"9": 4065, "72": 417, "45": 644, "7": 9030, "40": 1030, "4": 6401}, "nb": 1024}, "5104": {"val": 544, "part": 66.2, "v": {"45": 27, "7": 127, "4": 206, "9": 156, "72": 6, "40": 22}, "nb": 104}, "5105": {"val": 8326, "part": 57.8, "v": {"40": 666, "9": 1305, "7": 2203, "45": 415, "72": 181, "4": 3556}, "nb": 922}, "5107": {"val": 10320, "part": 46.4, "v": {"9": 2162, "4": 3885, "7": 2440, "45": 661, "40": 935, "72": 237}, "nb": 1159}, "5109": {"val": 127271, "part": 43.4, "v": {"4": 52128, "7": 38286, "45": 3420, "40": 5402, "72": 2343, "9": 25692}, "nb": 3412}, "5201": {"val": 2737, "part": 55.2, "v": {"4": 898, "9": 393, "72": 74, "40": 270, "45": 234, "7": 868}, "nb": 739}, "5301": {"val": 23048, "part": 43.4, "v": {"40": 1966, "72": 469, "9": 4903, "7": 5551, "4": 8962, "45": 1197}, "nb": 1225}, "5302": {"val": 5332, "part": 51.4, "v": {"9": 1614, "4": 1458, "45": 401, "7": 1169, "72": 102, "40": 588}, "nb": 551}, "5303": {"val": 5430, "part": 63.7, "v": {"4": 1511, "9": 1133, "72": 113, "40": 549, "45": 421, "7": 1703}, "nb": 603}, "5304": {"val": 7757, "part": 56.5, "v": {"45": 487, "72": 203, "40": 718, "7": 1487, "9": 2072, "4": 2790}, "nb": 884}, "5401": {"val": 13958, "part": 49.2, "v": {"4": 9169, "45": 410, "7": 2345, "72": 276, "9": 1087, "40": 671}, "nb": 882}, "5402": {"val": 7630, "part": 46.7, "v": {"9": 1180, "4": 4755, "7": 773, "45": 307, "40": 453, "72": 162}, "nb": 786}, "5403": {"val": 4037, "part": 72.9, "v": {"72": 69, "9": 334, "40": 173, "4": 2399, "45": 139, "7": 923}, "nb": 410}, "5404": {"val": 4502, "part": 52.2, "v": {"9": 524, "72": 69, "45": 162, "7": 519, "40": 161, "4": 3067}, "nb": 438}, "5405": {"val": 5868, "part": 73.3, "v": {"40": 260, "9": 526, "7": 2138, "45": 148, "72": 89, "4": 2707}, "nb": 517}, "5501": {"val": 29056, "part": 40.5, "v": {"40": 2014, "9": 7335, "7": 6114, "45": 1103, "72": 568, "4": 11922}, "nb": 1535}, "5502": {"val": 18300, "part": 43.3, "v": {"45": 778, "72": 384, "40": 1744, "7": 3078, "9": 3534, "4": 8782}, "nb": 1177}, "5503": {"val": 6767, "part": 47.9, "v": {"72": 153, "9": 1239, "40": 734, "4": 2874, "45": 343, "7": 1424}, "nb": 709}, "5504": {"val": 8193, "part": 53.6, "v": {"9": 2330, "4": 2658, "45": 297, "7": 2146, "72": 167, "40": 595}, "nb": 555}, "5506": {"val": 9117, "part": 51.6, "v": {"45": 489, "72": 221, "40": 786, "7": 1936, "9": 1575, "4": 4110}, "nb": 1055}, "5601": {"val": 32354, "part": 44.8, "v": {"9": 6724, "72": 1156, "45": 1997, "7": 4196, "40": 2486, "4": 15795}, "nb": 2795}, "5602": {"val": 7024, "part": 55.1, "v": {"45": 349, "7": 2502, "4": 2091, "9": 1244, "72": 211, "40": 627}, "nb": 564}, "5603": {"val": 7722, "part": 46.1, "v": {"72": 229, "9": 1751, "40": 747, "4": 2945, "45": 470, "7": 1580}, "nb": 685}, "5604": {"val": 7259, "part": 57.4, "v": {"4": 2725, "7": 1566, "45": 477, "40": 629, "72": 219, "9": 1643}, "nb": 649}, "5605": {"val": 6475, "part": 59.5, "v": {"4": 2345, "7": 1313, "45": 429, "40": 562, "72": 243, "9": 1583}, "nb": 624}, "5606": {"val": 6089, "part": 59.1, "v": {"40": 377, "9": 1024, "7": 2783, "45": 275, "72": 182, "4": 1448}, "nb": 725}, "5701": {"val": 24053, "part": 42.9, "v": {"9": 5127, "72": 490, "45": 1562, "7": 5568, "40": 2029, "4": 9277}, "nb": 1722}, "5702": {"val": 5339, "part": 49.0, "v": {"40": 487, "72": 130, "7": 935, "45": 304, "4": 2607, "9": 876}, "nb": 633}, "5703": {"val": 9417, "part": 49.4, "v": {"40": 706, "9": 1329, "7": 1441, "45": 592, "72": 176, "4": 5173}, "nb": 918}, "5704": {"val": 3532, "part": 61.4, "v": {"4": 1351, "7": 974, "45": 188, "40": 255, "72": 85, "9": 679}, "nb": 520}, "5705": {"val": 5768, "part": 46.2, "v": {"4": 2757, "7": 989, "45": 344, "40": 497, "72": 198, "9": 983}, "nb": 718}, "5706": {"val": 5290, "part": 48.6, "v": {"45": 262, "7": 1045, "4": 1435, "9": 1894, "72": 122, "40": 532}, "nb": 602}, "5801": {"val": 56281, "part": 43.2, "v": {"4": 24458, "9": 12871, "72": 949, "40": 3992, "45": 1897, "7": 12114}, "nb": 1819}, "5802": {"val": 16954, "part": 45.9, "v": {"72": 373, "40": 1258, "45": 696, "4": 7104, "7": 4708, "9": 2815}, "nb": 1153}, "5803": {"val": 7075, "part": 48.1, "v": {"40": 479, "9": 1102, "7": 2065, "45": 662, "72": 161, "4": 2606}, "nb": 816}, "5804": {"val": 40047, "part": 42.2, "v": {"4": 18227, "7": 8888, "45": 1377, "40": 2467, "72": 719, "9": 8369}, "nb": 1547}, "6101": {"val": 74490, "part": 39.6, "v": {"35": 8505, "17": 12389, "23": 20097, "20": 17424, "15": 16075}, "nb": 2556}, "6102": {"val": 6132, "part": 58.3, "v": {"15": 1446, "17": 874, "35": 1136, "23": 1374, "20": 1302}, "nb": 674}, "6103": {"val": 3638, "part": 59.8, "v": {"35": 506, "17": 772, "23": 665, "20": 826, "15": 869}, "nb": 694}, "6104": {"val": 7284, "part": 50.7, "v": {"17": 1462, "15": 1753, "35": 1589, "23": 1248, "20": 1232}, "nb": 913}, "6105": {"val": 8934, "part": 53.5, "v": {"23": 1699, "20": 2222, "15": 1834, "35": 1873, "17": 1306}, "nb": 916}, "6106": {"val": 12200, "part": 50.2, "v": {"17": 1550, "23": 2681, "20": 2586, "35": 2692, "15": 2691}, "nb": 1287}, "6107": {"val": 8615, "part": 49.0, "v": {"15": 2126, "17": 1864, "23": 1335, "20": 1671, "35": 1619}, "nb": 1381}, "6108": {"val": 18681, "part": 53.4, "v": {"15": 3118, "35": 2679, "23": 3671, "20": 5292, "17": 3921}, "nb": 1119}, "6109": {"val": 5386, "part": 51.7, "v": {"17": 1148, "15": 1261, "35": 925, "23": 877, "20": 1175}, "nb": 974}, "6110": {"val": 9539, "part": 49.4, "v": {"35": 1679, "15": 2127, "23": 2437, "20": 1796, "17": 1500}, "nb": 820}, "6111": {"val": 5911, "part": 51.7, "v": {"23": 1110, "20": 1082, "17": 1234, "35": 1131, "15": 1354}, "nb": 555}, "6112": {"val": 5979, "part": 53.9, "v": {"15": 1826, "17": 998, "23": 1099, "20": 1412, "35": 644}, "nb": 938}, "6113": {"val": 6876, "part": 47.7, "v": {"35": 834, "15": 1511, "23": 966, "20": 1977, "17": 1588}, "nb": 1170}, "6114": {"val": 5946, "part": 54.7, "v": {"35": 1135, "17": 1144, "23": 1003, "20": 1063, "15": 1601}, "nb": 869}, "6115": {"val": 19837, "part": 44.9, "v": {"17": 3492, "23": 3906, "20": 4337, "15": 3623, "35": 4479}, "nb": 1993}, "6116": {"val": 9600, "part": 45.9, "v": {"17": 2345, "23": 1812, "20": 1493, "35": 1826, "15": 2124}, "nb": 969}, "6117": {"val": 17215, "part": 46.8, "v": {"35": 2222, "15": 5771, "17": 3574, "23": 2656, "20": 2992}, "nb": 1732}, "6201": {"val": 8463, "part": 61.2, "v": {"17": 2189, "15": 2027, "35": 1173, "23": 1200, "20": 1874}, "nb": 1245}, "6202": {"val": 2185, "part": 69.4, "v": {"23": 243, "20": 469, "15": 284, "35": 391, "17": 798}, "nb": 408}, "6203": {"val": 3640, "part": 65.3, "v": {"35": 524, "15": 624, "23": 347, "20": 763, "17": 1382}, "nb": 613}, "6204": {"val": 3793, "part": 64.2, "v": {"17": 1352, "15": 591, "23": 361, "20": 1157, "35": 332}, "nb": 746}, "6205": {"val": 3624, "part": 61.2, "v": {"17": 974, "23": 488, "20": 688, "35": 368, "15": 1106}, "nb": 662}, "6206": {"val": 3737, "part": 68.9, "v": {"17": 1098, "15": 906, "35": 373, "23": 479, "20": 881}, "nb": 1135}, "6301": {"val": 26859, "part": 45.4, "v": {"23": 4034, "20": 4308, "17": 7106, "35": 2627, "15": 8784}, "nb": 1724}, "6302": {"val": 5179, "part": 44.2, "v": {"17": 1793, "23": 659, "20": 658, "15": 1475, "35": 594}, "nb": 899}, "6303": {"val": 11099, "part": 41.2, "v": {"23": 1906, "20": 1700, "15": 3617, "35": 1252, "17": 2624}, "nb": 1469}, "6304": {"val": 3570, "part": 64.6, "v": {"15": 921, "17": 1216, "35": 396, "23": 516, "20": 521}, "nb": 878}, "6305": {"val": 6436, "part": 46.8, "v": {"35": 630, "15": 2166, "23": 933, "20": 961, "17": 1746}, "nb": 691}, "6306": {"val": 4592, "part": 52.0, "v": {"17": 1450, "23": 676, "20": 563, "35": 544, "15": 1359}, "nb": 834}, "6307": {"val": 4529, "part": 51.4, "v": {"15": 1232, "35": 378, "23": 622, "20": 667, "17": 1630}, "nb": 649}, "6308": {"val": 4130, "part": 57.8, "v": {"23": 585, "20": 566, "15": 1517, "35": 643, "17": 819}, "nb": 634}, "6309": {"val": 2854, "part": 72.2, "v": {"23": 138, "20": 171, "15": 194, "35": 116, "17": 2235}, "nb": 274}, "6310": {"val": 11663, "part": 41.5, "v": {"35": 993, "15": 3014, "23": 1476, "20": 2058, "17": 4122}, "nb": 1299}, "7101": {"val": 71216, "part": 41.2, "v": {"36": 16971, "24": 8979, "73": 3098, "14": 18360, "11": 11895, "67": 2232, "49": 9681}, "nb": 2869}, "7102": {"val": 16225, "part": 45.9, "v": {"49": 1021, "11": 4731, "67": 564, "36": 4250, "14": 2965, "73": 699, "24": 1995}, "nb": 2125}, "7103": {"val": 4437, "part": 50.7, "v": {"36": 1218, "24": 647, "73": 168, "14": 635, "11": 1217, "67": 172, "49": 380}, "nb": 793}, "7104": {"val": 2290, "part": 66.5, "v": {"24": 305, "49": 265, "14": 467, "73": 99, "11": 843, "67": 109, "36": 202}, "nb": 784}, "7105": {"val": 10825, "part": 49.0, "v": {"49": 1328, "36": 1547, "73": 481, "11": 2983, "67": 316, "14": 3235, "24": 935}, "nb": 1191}, "7106": {"val": 3570, "part": 47.6, "v": {"14": 1145, "11": 1073, "67": 94, "73": 134, "36": 279, "24": 433, "49": 412}, "nb": 495}, "7107": {"val": 5239, "part": 57.9, "v": {"24": 812, "49": 597, "14": 881, "73": 179, "11": 2112, "67": 145, "36": 513}, "nb": 844}, "7108": {"val": 5363, "part": 51.7, "v": {"49": 400, "36": 516, "73": 212, "11": 1232, "67": 185, "14": 1153, "24": 1665}, "nb": 850}, "7109": {"val": 12833, "part": 38.0, "v": {"36": 2161, "24": 1246, "73": 469, "14": 4270, "11": 3640, "67": 334, "49": 713}, "nb": 1276}, "7110": {"val": 3862, "part": 53.2, "v": {"14": 812, "49": 609, "24": 379, "36": 350, "11": 1464, "67": 118, "73": 130}, "nb": 658}, "7201": {"val": 12751, "part": 39.6, "v": {"49": 853, "36": 1361, "73": 662, "11": 4300, "67": 531, "14": 1742, "24": 3302}, "nb": 2159}, "7202": {"val": 4029, "part": 60.5, "v": {"14": 441, "24": 952, "11": 1527, "67": 179, "49": 346, "36": 340, "73": 244}, "nb": 1714}, "7203": {"val": 4106, "part": 69.2, "v": {"73": 241, "14": 580, "36": 403, "49": 428, "11": 1494, "67": 198, "24": 762}, "nb": 1321}, "7301": {"val": 45645, "part": 40.1, "v": {"11": 15326, "67": 2099, "24": 10469, "36": 3601, "49": 1197, "14": 11389, "73": 1564}, "nb": 1652}, "7302": {"val": 5051, "part": 58.3, "v": {"49": 139, "24": 894, "73": 175, "14": 636, "36": 210, "11": 2736, "67": 261}, "nb": 653}, "7303": {"val": 3624, "part": 60.4, "v": {"73": 77, "24": 1129, "49": 159, "11": 1336, "67": 84, "36": 181, "14": 658}, "nb": 521}, "7304": {"val": 17543, "part": 47.9, "v": {"14": 6190, "11": 6028, "67": 815, "73": 556, "36": 1429, "24": 1955, "49": 570}, "nb": 1339}, "7305": {"val": 4269, "part": 49.0, "v": {"14": 808, "24": 861, "11": 1677, "67": 388, "49": 137, "36": 252, "73": 146}, "nb": 610}, "7306": {"val": 6040, "part": 47.9, "v": {"49": 236, "36": 356, "73": 203, "11": 2459, "67": 233, "14": 980, "24": 1573}, "nb": 588}, "7307": {"val": 7400, "part": 53.1, "v": {"49": 283, "36": 438, "73": 318, "11": 2712, "67": 681, "14": 1393, "24": 1575}, "nb": 1084}, "7308": {"val": 8504, "part": 36.3, "v": {"36": 406, "11": 2029, "67": 2833, "49": 240, "24": 1364, "73": 177, "14": 1455}, "nb": 555}, "7309": {"val": 3406, "part": 73.7, "v": {"11": 1697, "67": 64, "24": 789, "36": 144, "49": 142, "14": 480, "73": 90}, "nb": 630}, "7401": {"val": 28167, "part": 36.9, "v": {"49": 1415, "11": 6702, "67": 1195, "36": 3207, "14": 7846, "73": 920, "24": 6882}, "nb": 2007}, "7402": {"val": 8658, "part": 55.1, "v": {"49": 577, "24": 766, "73": 414, "14": 3173, "36": 765, "11": 2569, "67": 394}, "nb": 1500}, "7403": {"val": 9454, "part": 43.0, "v": {"36": 900, "11": 2444, "67": 452, "49": 843, "24": 2192, "73": 494, "14": 2129}, "nb": 2043}, "7404": {"val": 13545, "part": 42.1, "v": {"14": 3420, "11": 3028, "67": 597, "73": 677, "24": 3130, "36": 1309, "49": 1384}, "nb": 2386}, "7405": {"val": 6673, "part": 46.4, "v": {"73": 338, "24": 2010, "49": 616, "11": 1482, "67": 241, "36": 449, "14": 1537}, "nb": 1494}, "7406": {"val": 13119, "part": 37.3, "v": {"24": 2577, "11": 4518, "67": 579, "14": 2305, "36": 1800, "73": 616, "49": 724}, "nb": 1532}, "7407": {"val": 5698, "part": 48.2, "v": {"73": 282, "14": 1255, "36": 680, "49": 335, "11": 1504, "67": 267, "24": 1375}, "nb": 981}, "7408": {"val": 5740, "part": 46.2, "v": {"24": 1018, "11": 2095, "67": 247, "14": 1352, "36": 431, "73": 258, "49": 339}, "nb": 1117}, "8101": {"val": 78623, "part": 40.3, "v": {"65": 1421, "8": 24003, "83": 696, "12": 14556, "18": 10626, "33": 4919, "34": 9573, "16": 12829}, "nb": 2307}, "8102": {"val": 35916, "part": 42.7, "v": {"34": 1849, "16": 3429, "12": 3371, "18": 3355, "33": 12079, "83": 504, "65": 2381, "8": 8948}, "nb": 2452}, "8103": {"val": 29337, "part": 45.5, "v": {"12": 3886, "18": 4667, "33": 2051, "83": 342, "65": 658, "8": 9828, "34": 2694, "16": 5211}, "nb": 1359}, "8104": {"val": 3803, "part": 42.3, "v": {"34": 431, "16": 460, "83": 144, "12": 872, "18": 513, "33": 157, "65": 150, "8": 1076}, "nb": 616}, "8105": {"val": 8514, "part": 47.4, "v": {"12": 1062, "18": 1403, "33": 573, "34": 819, "16": 1224, "65": 344, "8": 2887, "83": 202}, "nb": 1209}, "8106": {"val": 19105, "part": 45.2, "v": {"34": 1125, "16": 2154, "83": 352, "12": 2401, "18": 3094, "33": 4589, "65": 966, "8": 4424}, "nb": 2542}, "8107": {"val": 18332, "part": 47.0, "v": {"65": 510, "8": 6019, "12": 1867, "18": 3376, "33": 1321, "83": 273, "34": 2087, "16": 2879}, "nb": 1516}, "8108": {"val": 37574, "part": 43.5, "v": {"65": 792, "8": 12273, "83": 357, "12": 6759, "18": 4503, "33": 2596, "34": 3173, "16": 7121}, "nb": 1394}, "8109": {"val": 5456, "part": 50.7, "v": {"12": 1090, "18": 967, "33": 333, "83": 99, "65": 191, "8": 1423, "34": 539, "16": 814}, "nb": 1147}, "8110": {"val": 47659, "part": 37.6, "v": {"34": 5099, "16": 8957, "12": 8521, "18": 6701, "33": 3468, "65": 1048, "8": 13100, "83": 765}, "nb": 2137}, "8111": {"val": 20696, "part": 45.8, "v": {"65": 639, "8": 5186, "83": 349, "12": 2880, "18": 3637, "33": 1624, "34": 3095, "16": 3286}, "nb": 2113}, "8112": {"val": 32904, "part": 44.7, "v": {"12": 4250, "18": 5143, "33": 2407, "34": 3525, "16": 5451, "65": 843, "8": 10834, "83": 451}, "nb": 1802}, "8201": {"val": 8198, "part": 42.5, "v": {"34": 649, "16": 758, "12": 3145, "18": 588, "33": 554, "65": 297, "8": 2067, "83": 140}, "nb": 1291}, "8202": {"val": 12283, "part": 43.3, "v": {"65": 501, "8": 2628, "83": 185, "12": 4746, "18": 946, "33": 875, "34": 834, "16": 1568}, "nb": 1197}, "8203": {"val": 9099, "part": 34.0, "v": {"65": 261, "8": 1547, "83": 135, "12": 4327, "18": 670, "33": 788, "34": 481, "16": 890}, "nb": 934}, "8204": {"val": 2701, "part": 57.0, "v": {"34": 120, "16": 294, "65": 95, "8": 392, "12": 1384, "18": 242, "33": 112, "83": 62}, "nb": 748}, "8205": {"val": 11491, "part": 41.2, "v": {"65": 403, "8": 1991, "83": 173, "12": 4542, "18": 1189, "33": 1189, "34": 732, "16": 1272}, "nb": 1137}, "8206": {"val": 7210, "part": 45.6, "v": {"65": 314, "8": 1442, "83": 147, "12": 3078, "18": 719, "33": 477, "34": 436, "16": 597}, "nb": 1032}, "8207": {"val": 3290, "part": 47.4, "v": {"12": 1190, "18": 174, "33": 205, "65": 140, "8": 983, "34": 235, "16": 299, "83": 64}, "nb": 1053}, "8301": {"val": 44903, "part": 29.6, "v": {"65": 1512, "8": 10021, "83": 751, "12": 11863, "18": 8037, "33": 3004, "34": 3151, "16": 6564}, "nb": 3331}, "8302": {"val": 2038, "part": 54.1, "v": {"83": 39, "34": 212, "16": 266, "65": 87, "8": 566, "12": 312, "18": 439, "33": 117}, "nb": 513}, "8303": {"val": 9675, "part": 48.7, "v": {"83": 318, "34": 780, "16": 1619, "65": 441, "8": 2640, "12": 1390, "18": 1873, "33": 614}, "nb": 2551}, "8304": {"val": 8566, "part": 45.3, "v": {"12": 1347, "18": 935, "33": 701, "83": 219, "65": 482, "8": 2671, "34": 1059, "16": 1152}, "nb": 1219}, "8305": {"val": 8308, "part": 36.7, "v": {"34": 837, "16": 1257, "83": 221, "12": 1406, "18": 1850, "33": 505, "65": 550, "8": 1682}, "nb": 1542}, "8306": {"val": 8390, "part": 39.0, "v": {"34": 792, "16": 1196, "83": 197, "12": 1476, "18": 1335, "33": 559, "65": 390, "8": 2445}, "nb": 1222}, "8307": {"val": 3658, "part": 53.3, "v": {"83": 130, "34": 404, "16": 505, "65": 278, "8": 870, "12": 820, "18": 454, "33": 197}, "nb": 1181}, "8308": {"val": 1909, "part": 56.3, "v": {"12": 408, "18": 385, "33": 92, "65": 118, "8": 437, "34": 169, "16": 255, "83": 45}, "nb": 545}, "8309": {"val": 3626, "part": 50.1, "v": {"65": 210, "8": 861, "83": 126, "12": 741, "18": 509, "33": 254, "34": 421, "16": 504}, "nb": 1205}, "8310": {"val": 2345, "part": 61.6, "v": {"65": 89, "8": 1236, "12": 225, "18": 312, "33": 143, "83": 36, "34": 120, "16": 184}, "nb": 382}, "8311": {"val": 3817, "part": 34.9, "v": {"34": 363, "16": 603, "83": 79, "12": 885, "18": 730, "33": 203, "65": 167, "8": 787}, "nb": 837}, "8312": {"val": 4743, "part": 44.6, "v": {"83": 87, "65": 210, "8": 1156, "34": 351, "16": 612, "12": 1175, "18": 735, "33": 417}, "nb": 1085}, "8313": {"val": 7765, "part": 46.7, "v": {"83": 233, "34": 489, "16": 1108, "65": 389, "8": 2215, "12": 1171, "18": 1591, "33": 569}, "nb": 1633}, "8314": {"val": 1779, "part": 58.9, "v": {"83": 75, "34": 238, "16": 247, "65": 221, "8": 392, "12": 305, "18": 204, "33": 97}, "nb": 1495}, "9101": {"val": 81602, "part": 35.9, "v": {"51": 8198, "71": 5241, "27": 19683, "32": 15639, "43": 5905, "78": 2928, "68": 2117, "13": 21891}, "nb": 3471}, "9102": {"val": 9278, "part": 43.6, "v": {"27": 1104, "32": 742, "13": 5461, "51": 468, "71": 272, "43": 815, "78": 187, "68": 229}, "nb": 1499}, "9103": {"val": 6516, "part": 39.5, "v": {"43": 715, "78": 621, "27": 1043, "32": 963, "51": 479, "71": 370, "13": 2034, "68": 291}, "nb": 1394}, "9104": {"val": 2857, "part": 45.5, "v": {"27": 422, "32": 511, "13": 761, "51": 170, "71": 95, "43": 575, "78": 73, "68": 250}, "nb": 1015}, "9105": {"val": 7619, "part": 37.5, "v": {"13": 3292, "51": 411, "71": 257, "68": 250, "27": 1312, "32": 978, "43": 940, "78": 179}, "nb": 950}, "9106": {"val": 4890, "part": 49.0, "v": {"27": 775, "13": 1707, "68": 168, "51": 249, "71": 131, "43": 901, "78": 129, "32": 830}, "nb": 1063}, "9107": {"val": 6121, "part": 46.1, "v": {"13": 2035, "51": 312, "71": 192, "68": 228, "27": 2164, "32": 552, "43": 517, "78": 121}, "nb": 1090}, "9108": {"val": 10527, "part": 36.0, "v": {"13": 3372, "51": 1042, "71": 375, "68": 378, "27": 1916, "32": 1466, "43": 1531, "78": 447}, "nb": 1812}, "9109": {"val": 8121, "part": 41.2, "v": {"13": 2549, "51": 549, "71": 367, "68": 610, "27": 1352, "32": 1186, "43": 1216, "78": 292}, "nb": 1435}, "9110": {"val": 2730, "part": 47.9, "v": {"27": 354, "13": 797, "68": 107, "51": 175, "71": 91, "43": 385, "78": 415, "32": 406}, "nb": 1026}, "9111": {"val": 12282, "part": 44.5, "v": {"13": 5873, "51": 863, "71": 962, "68": 426, "27": 1161, "32": 1330, "43": 1422, "78": 245}, "nb": 1365}, "9112": {"val": 17621, "part": 32.8, "v": {"68": 560, "43": 2211, "78": 650, "32": 3419, "27": 2601, "13": 5403, "51": 1681, "71": 1096}, "nb": 1709}, "9113": {"val": 3098, "part": 56.8, "v": {"27": 347, "32": 577, "13": 1292, "51": 232, "71": 89, "43": 326, "78": 109, "68": 126}, "nb": 776}, "9114": {"val": 9015, "part": 42.7, "v": {"51": 469, "71": 373, "43": 890, "78": 207, "32": 898, "27": 2282, "68": 377, "13": 3519}, "nb": 855}, "9115": {"val": 9700, "part": 38.1, "v": {"32": 1936, "13": 1780, "43": 1919, "78": 266, "51": 772, "71": 484, "68": 944, "27": 1599}, "nb": 1094}, "9116": {"val": 5591, "part": 52.6, "v": {"43": 1275, "78": 174, "13": 2040, "27": 501, "32": 825, "68": 195, "51": 294, "71": 287}, "nb": 1394}, "9117": {"val": 5758, "part": 49.0, "v": {"43": 630, "78": 144, "32": 597, "68": 290, "51": 303, "71": 295, "13": 2516, "27": 983}, "nb": 1122}, "9118": {"val": 3651, "part": 43.9, "v": {"51": 275, "71": 137, "43": 473, "78": 119, "32": 571, "27": 961, "68": 163, "13": 952}, "nb": 1002}, "9119": {"val": 9287, "part": 44.8, "v": {"68": 292, "13": 3630, "43": 936, "78": 298, "51": 800, "71": 383, "32": 1204, "27": 1744}, "nb": 1667}, "9120": {"val": 17855, "part": 34.8, "v": {"27": 2104, "32": 3019, "13": 2848, "51": 1001, "71": 744, "43": 2209, "78": 475, "68": 5455}, "nb": 1242}, "9121": {"val": 5296, "part": 58.6, "v": {"51": 331, "71": 206, "43": 771, "78": 164, "32": 1012, "27": 631, "68": 144, "13": 2037}, "nb": 1207}, "9201": {"val": 13927, "part": 34.3, "v": {"43": 1638, "78": 530, "32": 2316, "68": 550, "51": 1443, "71": 520, "13": 2959, "27": 3971}, "nb": 2252}, "9202": {"val": 6789, "part": 38.1, "v": {"27": 1430, "32": 1023, "13": 1782, "51": 855, "71": 246, "43": 797, "78": 374, "68": 282}, "nb": 1661}, "9203": {"val": 5089, "part": 30.8, "v": {"68": 273, "32": 862, "27": 949, "43": 480, "78": 206, "51": 606, "71": 151, "13": 1562}, "nb": 1443}, "9204": {"val": 2665, "part": 44.8, "v": {"51": 256, "71": 229, "27": 543, "32": 353, "43": 554, "78": 110, "68": 84, "13": 536}, "nb": 984}, "9205": {"val": 4596, "part": 52.9, "v": {"43": 1124, "78": 100, "13": 1385, "27": 835, "32": 571, "68": 242, "51": 249, "71": 90}, "nb": 1861}, "9206": {"val": 3087, "part": 55.3, "v": {"43": 393, "78": 96, "32": 406, "68": 191, "51": 286, "71": 133, "13": 678, "27": 904}, "nb": 1079}, "9207": {"val": 3875, "part": 54.4, "v": {"27": 1280, "13": 964, "68": 130, "51": 226, "71": 98, "43": 695, "78": 113, "32": 369}, "nb": 1172}, "9208": {"val": 4522, "part": 47.3, "v": {"68": 196, "51": 363, "71": 123, "43": 681, "78": 162, "13": 1367, "27": 954, "32": 676}, "nb": 1264}, "9209": {"val": 3655, "part": 48.9, "v": {"13": 755, "32": 704, "27": 709, "43": 627, "78": 160, "68": 186, "51": 355, "71": 159}, "nb": 1182}, "9210": {"val": 5997, "part": 39.6, "v": {"68": 236, "43": 859, "78": 181, "32": 734, "27": 1721, "13": 1705, "51": 381, "71": 180}, "nb": 1380}, "9211": {"val": 10524, "part": 38.7, "v": {"27": 2299, "13": 2859, "68": 426, "51": 1196, "71": 317, "43": 810, "78": 408, "32": 2209}, "nb": 2147}}, "local": {}}